{
    "output": {
        "justification": [
            "Leadership experience is implied in the role of managing a data analytics team and achieving targets, but not explicitly demonstrated with international teams or strategic missions.",
            "Relevant experience in business development is present, but lacks the international focus needed for the job role.",
            "Strategic Planning skills are listed but not extensively demonstrated in terms of leading large-scale international initiatives.",
            "Competitive Analysis is implied through tasks like analyzing sales channels and product adaptation, but there is no explicit experience in competitive landscapes required for the role."
        ],
        "scores": {
            "macro_scores": [
                {
                    "criteria": "leadership",
                    "score": 6
                },
                {
                    "criteria": "strategic planning",
                    "score": 5
                }
            ],
            "micro_scores": [
                {
                    "criteria": "competitive analysis",
                    "score": 5
                }
            ],
            "requirements": [
                {
                    "criteria": "Proficiency in strategic planning and client management",
                    "meets": false
                }
            ],
            "aggregated_scores": {
                "macro_scores": 5.41,
                "micro_scores": 5.0
            }
        },
        "personal_info": {
            "name": "SAAD BIN HASSAN",
            "email": "saadbinhassan000@gmail.com",
            "phone": "923133162249",
            "current_position": "Junior Project Associate",
            "current_company": "ProntoDigital, LLC",
            "employment_start_date_current_company": "03-2022",
            "first_company_start_date": "06-2021",
            "urls": [
                {
                    "website_name": "LinkedIn",
                    "url": "https://www.linkedin.com/in/saad-bin-hassan-096118183/"
                }
            ]
        },
        "valid_resume_and_jd": true
    },
    "input": {
        "job_description": "### Job Title: International Business Development Manager\n\n#### Company: InnovateTech Solutions\n\n**Location:** Lahore, Pakistan  \n\n**About InnovateTech Solutions:**  \nInnovateTech Solutions is a leading global provider of innovative technology solutions, specializing in expanding business operations across diverse international markets. We are seeking a highly motivated and experienced International Business Development Manager to join our team and lead strategic market entry initiatives.\n\n#### Responsibilities:\n\n- Develop and implement comprehensive strategies for foreign market entry, expansion, and product launches in new territories.\n- Lead international trade missions to research, analyze, and secure new business opportunities in the EU and US markets.\n- Build and maintain strong relationships with clients and key stakeholders by employing effective negotiation and communication skills.\n- Collaborate with cross-functional teams to design market entry strategies and oversee implementation of marketing and sales plans.\n- Manage a team of business development officers, providing guidance and support to achieve departmental objectives.\n- Coordinate and attend international exhibitions and trade shows to promote company products and secure new contracts.\n- Analyze market trends and competitive landscapes to identify business opportunities and recommend strategic changes.\n- Ensure compliance with international market regulations and standards in collaboration with regulatory consultants.\n\n#### Qualifications:\n\n- Bachelor's degree in Business, Marketing, or a relevant field; a Master's degree is a plus.\n- Minimum of 5 years of experience in international business development or related roles.\n- Proven track record of strategic planning and securing high-value contracts with international clients.\n- Strong analytical and problem-solving skills with a keen attention to detail.\n- Excellent communication and interpersonal skills, with proficiency in multiple languages being an advantage.\n\n#### Why Join Us?\n\n- Fast-paced and dynamic work environment with opportunities for career growth.\n- Chance to lead strategic initiatives and make a significant impact on international expansion efforts.\n- Competitive salary package and benefits.\n\nIf you are passionate about driving international business growth and have the skills to succeed, we would like to meet you!\n\n**To Apply:** Please submit your resume and cover letter detailing your relevant experience and achievements.",
        "macro_dict": {
            "leadership": 41,
            "strategic planning": 59
        },
        "micro_dict": {
            "competitive analysis": 100
        },
        "additional_info": null,
        "minimum_requirements": [
            "Proficiency in strategic planning and client management"
        ],
        "resume": "  SAAD BIN HASSAN  \nHometown: Lahore  \nCell: 923133162249  | saadbinhassan000@gmail.com  \nDate of Birth: 0 7/04/1998  \nLinkedin Profile: https://www.linkedin.com/in/saad -bin-hassan -096118183/  \nEDUCATION & QUALIFICATIONS  \nMasters of Business Administration  May 2022 \nLahore School of Economics  \nBachelors in Business Administration  (Honors)   June  2021  \nMajor (Marketing) Minor (Media Studies)  \nLahore School of Economics           \nPROFESSIONAL EXPERIENCE         \nProntoDigital, LLC                                                                                               June  2021 \u2013 February 2022  \nBusiness Development Executive  \n\uf0b7 Responsible for finding and retaining new clients, Handling Upwork profiles.  \n\uf0b7 Maintained relationships with clients by providing them information and guidance.  \n\uf0b7 Generated weekly sales reports and provided useful insights.  \nProntoDigital, LLC                                                                        March  2022 \u2013 May 2022  \nJunior Project Associate  \n\uf0b7 Managed and build a Data Analytics team.  \n\uf0b7 Managed to achieve the target of $20,000 in 3 months.  \nBank of Punjab                       June-August  2018 \nOperations Intern, Operations  \n\uf0b7 Responsible to deal with branch daily operations and Opening of new accounts.  \nDetechgear  \nMarketing Executive                                                                                                                                                     July- Dec 2020  \n\uf0b7 Managed all Digital Marketing  of the business.  \n\uf0b7 Achieved sales of 500,000 in 5 months.  \nPROJECTS  \nStrategic Management : Strategic decision making and analyzing a company\u2019s performance by looking at different factors. \nUsing tools like IFE, EFE, CPM, QSPM , etc.  \nAdvertising:  Product adaption of Clear Shampoo according to Pakistani Market. Devised the entire advertising plan \nincorporating all the strategies and storyboard . \nSales Force Management : Analyzed the Sales channel of FFC and developed the strategy to strengthen the Salesforce  \nchannel.  \nMarketing Research: Conducted qualitative and quantita tive research on Nokia Pakistan.  \nADDITIONAL EXPERIENCE  \nTeacher Assistant , Lahore School of Economics                                                                                                2021 \u2013 2022 \nMarketing Intern , Signature Lifestyle.  \n\uf0b7 Managed all Digital Marketing campaigns and marketing strategies.              March -July 2022   \nHONORS & AWARDS  \n\uf0b7 Winner of LSE Business Fiesta 2021  \n\uf0b7 25% Scholarship in Lahore  School of Economics  \nSKILLS & INTERESTS  \n\uf0b7 Competent user of M icrosoft Office , Vegas Pro, SPSS, Smar t PLS , Shopify, and Ecommerce \nManagement.  \n\uf0b7     Digital Marketing, Upwork , Click Up, Slack, FB Ads, Google AdWords , Google Analytics, Canva.  \n       \uf0b7     Strategic Planning, Leadership, Comfortable in Team work.  \n"
    },
    "details": {
        "name": "Saad Bin Hassan",
        "number": "923133162249",
        "skills": [
            "Microsoft Office",
            "Vegas Pro",
            "SPSS",
            "Smart PLS",
            "Shopify",
            "Ecommerce Management",
            "Digital Marketing",
            "Upwork",
            "Click Up",
            "Slack",
            "FB Ads",
            "Google AdWords",
            "Google Analytics",
            "Canva"
        ],
        "email_id": "saadbinhassan000@gmail.com",
        "location": "Lahore",
        "projects": [
            {
                "title": "Strategic Management",
                "description": "Strategic decision making and analyzing a company\u2019s performance by looking at different factors."
            },
            {
                "title": "Advertising",
                "description": "Product adaption of Clear Shampoo according to Pakistani Market."
            },
            {
                "title": "Sales Force Management",
                "description": "Analyzed the Sales channel of FFC and developed the strategy to strengthen the Salesforce channel."
            },
            {
                "title": "Marketing Research",
                "description": "Conducted qualitative and quantitative research on Nokia Pakistan."
            }
        ],
        "education": [
            {
                "end_date": "05-2022",
                "university": "Lahore School of Economics",
                "degree_title": "Masters of Business Administration"
            },
            {
                "end_date": "06-2021",
                "university": "Lahore School of Economics",
                "degree_title": "Bachelors in Business Administration (Honors)"
            }
        ],
        "achievements": [
            "Winner of LSE Business Fiesta 2021",
            "25% Scholarship in Lahore School of Economics"
        ],
        "publications": [],
        "certifications": [],
        "additional_urls": [
            {
                "url": "linkedin.com/in/saad-bin-hassan-096118183/",
                "website_name": "LinkedIn"
            }
        ],
        "executive_summary": "Saad Bin Hassan is a skilled professional with a strong background in business development and digital marketing, holding an MBA from the Lahore School of Economics. He has demonstrated expertise in managing teams and achieving sales targets, along with a solid foundation in various technical tools and platforms.",
        "employment_history": [
            {
                "details": "Responsible for finding and retaining new clients, Handling Upwork profiles. Maintained relationships with clients by providing them information and guidance. Generated weekly sales reports and provided useful insights.",
                "end_date": "02-2022",
                "location": "Lahore",
                "job_title": "Business Development Executive",
                "start_date": "06-2021",
                "company_name": "ProntoDigital, LLC"
            },
            {
                "details": "Managed and build a Data Analytics team. Managed to achieve the target of $20,000 in 3 months.",
                "end_date": "05-2022",
                "location": "Lahore",
                "job_title": "Junior Project Associate",
                "start_date": "03-2022",
                "company_name": "ProntoDigital, LLC"
            },
            {
                "details": "Responsible to deal with branch daily operations and Opening of new accounts.",
                "end_date": "08-2018",
                "location": "Lahore",
                "job_title": "Operations Intern",
                "start_date": "06-2018",
                "company_name": "Bank of Punjab"
            },
            {
                "details": "Managed all Digital Marketing of the business. Achieved sales of 500,000 in 5 months.",
                "end_date": "12-2020",
                "location": "Lahore",
                "job_title": "Marketing Executive",
                "start_date": "07-2020",
                "company_name": "Detechgear"
            },
            {
                "details": "Managed all Digital Marketing campaigns and marketing strategies.",
                "end_date": "07-2022",
                "location": "Lahore",
                "job_title": "Marketing Intern",
                "start_date": "03-2022",
                "company_name": "Signature Lifestyle"
            }
        ]
    }
}