{
    "output": {
        "justification": [
            "The candidate does not have a bachelor's degree in Business Administration, Marketing, or a related field; their degree is in Information Technology, which is not directly related.",
            "There's no specific mention of leadership or mentoring roles in the resume experience, which is a key requirement in both the job description and internal document.",
            "The resume mentions experience with CRM systems but does not specify HubSpot or Salesforce; proficiency in these tools is not demonstrated clearly as required by the job description.",
            "The experience listed in Business Development roles does not total 5+ years, falling short of the job description's preference."
        ],
        "scores": {
            "macro_scores": [
                {
                    "criteria": "marketing expertise",
                    "score": 4
                }
            ],
            "micro_scores": [
                {
                    "criteria": "email marketing",
                    "score": 5
                }
            ],
            "requirements": [
                {
                    "criteria": "Bachelor's degree in Business Administration, Marketing, or related field",
                    "meets": false
                },
                {
                    "criteria": "Demonstrated ability in team leadership and mentoring",
                    "meets": false
                },
                {
                    "criteria": "Proficiency in CRM software (e.g., HubSpot, Salesforce)",
                    "meets": false
                },
                {
                    "criteria": "5+ years of experience in sales and marketing roles",
                    "meets": false
                }
            ],
            "aggregated_scores": {
                "macro_scores": 4.0,
                "micro_scores": 5.0
            }
        },
        "personal_info": {
            "name": "Samha Ahmed",
            "email": "samhaahmed39@gmail.com",
            "phone": "+923324817353",
            "current_position": "Business Development Executive",
            "current_company": "Rolustech",
            "employment_start_date_current_company": "09-2021",
            "first_company_start_date": "05-2021",
            "urls": []
        },
        "valid_resume_and_jd": true
    },
    "input": {
        "job_description": "## Join Our Dynamic Team as a Senior Sales and Marketing Executive\n\n### Position Overview\n\n[Acme Corp], a leader in providing cutting-edge digital marketing solutions, is on the hunt for a driven **Senior Sales and Marketing Executive** to play a key role in our growing team. You\u2019ll leverage your skills in sales management, business development, and digital marketing to drive business growth and maximize client satisfaction. Use your talent in leadership to mentor our young team, ensuring we hit key business targets while setting new standards in the industry.\n\n### Key Responsibilities\n- Drive sales strategies to achieve performance targets and expand our market reach.\n- Manage end-to-end sales processes including customer prospecting, lead generation, and closing sales. \n- Work collaboratively with the digital marketing team to conceive, manage, and execute marketing campaigns.\n- Utilize CRM tools such as HubSpot for tracking and analytics to boost sales efficiency.\n- Conduct market research and data analysis to inform business strategies.\n- Mentor new hires and facilitate continuous professional development.\n\n### Essential Skills and Experience\n- Proven experience in sales management and digital marketing (5+ years preferred).\n- Strong command over marketing automation tools and CRMs like HubSpot and Salesforce.\n- Ability to set strategic goals with excellent problem-solving and communication skills.\n- Aptitude for data visualization and analytics to drive informed marketing decisions.\n- Familiarity with SEO, SEM, email marketing campaigns, and business intelligence tools.\n- Demonstrated proficiency in leading and supervising a dynamic team environment.\n\n### What We Offer\n- Competitive salary and a comprehensive benefits package.\n- Opportunity to work with an innovative team and environment.\n- Continuous learning opportunities and growth potential within the company.\n\nJoin us to make an impact on the digital landscape and drive success!",
        "macro_dict": {
            "marketing expertise": 100
        },
        "micro_dict": {
            "email marketing": 100
        },
        "additional_info": "At Acme Corp, we prioritize candidates from diverse educational backgrounds with proven experience in high-pressure sales environments. We welcome graduates from reputable institutions but hold no particular preference for any university. Relocation support is available on a case-by-case basis. Skills assessment will include a practical marketing project to gauge capability in real-world scenarios, complemented by personal interviews to evaluate cultural fit and growth potential.",
        "minimum_requirements": [
            "Bachelor's degree in Business Administration, Marketing, or related field",
            "Demonstrated ability in team leadership and mentoring",
            "Proficiency in CRM software (e.g., HubSpot, Salesforce)",
            "5+ years of experience in sales and marketing roles"
        ],
        "resume": "SAMHA\nAHMED\nAddress: Lahore, Pakistan \u2013 Phone: +923324817353\nEmail:\nsamhaahmed39@gmail.com\nOBJECTIVE\nTo work in a challenging environment where I can better utilize my skills and enhance my experience in\nthe domain of sales and business development.\nWORK EXPERIENCE\nBUSINESS DEVELOPMENT EXECUTIVE\nRolustech\n(September 2021 \u2013 Present)\nBUSINESS DEVELOPMENT EXECUTIVE\nTxLabz\n(May 2021 \u2013 September 2021)\nASSOCIATE PROJECT MANAGER\nTxLabz\n(June 2021 \u2013 September 2021)\nEDUCATION\nBS INFORMATION TECHNOLOGY\n(2017\u20132021)\nPunjab University College of Information Technology, Lahore\n(OOP, DSA, DB, Web, Android, SQA)\nF.SC PRE-ENGINEERING\n(2015 \u2013 2017)\nPunjab College of Science, Lahore\n(Chemistry, Physics, Mathematics)\nPercentage: 80%\nMATRICULATION\n(2013 \u2013 2015)\nWapda Girls High School, Lahore\n(Computer, Mathematics, Physics, Chemistry)\nPercentage: 93%PERSONAL SKILLS\n\u25cf\nStrong interpersonal skills\n\u25cf\nE\ufb00ective Listening\n\u25cf\nAbility to negotiate\n\u25cf\nAbility to Multitask\n\u25cf\nAttention to details\n\u25cf\nProfessional behavior\n\u25cf\nTime and resource \nmanagement\n\u25cf\nE\ufb00ective Decision making\nORGANIZATIONAL/ MANAGERIAL SKILLS\n\u25cf\nBusiness intelligence and marketing skills\n\u25cf\nHands-on experience in Upwork bidding and utilization of freelancing platforms for lead\ngeneration\n\u25cf\nKnowledge of all the stages of a sales cycle\n\u25cf\nExperience with CRM systems\n\u25cf\nStrong knowledge of lead generation using email campaigns and popular marketing tools\n\u25cf\nAbility to analyze market trends and suggest new ideas/strategies for improving sales\n\u25cf\nAbility to interact and e\ufb00ectively communicate with people from diverse backgrounds\n\u25cf\nStrong persuasion skills that help in maximizing customer satisfaction\n\u25cf\nGood at creating and goal setting and meeting goals, decision making, managing\nappointments, team management, and strategic thinking\nSEMESTER PROJECTS\nCAMPUS MANAGEMENT SYSTEM\nSubject: Programming Fundamentals, It was developed in C++.\nNGO DATABASE SYSTEM\nSubject: Database System. It was developed in ORACLE using PHP, HTML, and CSS.\nLUDO GAME\nSubject: OOAD (Object-Oriented Analysis and Design). It was developed in JAVA.\nONLINE ART GALLERY\nSubject: Web Development. It was developed using HTML, CSS, Bootstrap, JavaScript, AJAX,\nJQUERY, and JSON.FINAL YEAR PROJECT\nPU E-BUS TRACKING APPLICATION\nIt is an application that will provide Real-time Bus locations to the students. It is an\nAndroid-based project. The application has two modules; one is for drivers, the other for\nstudents. When a driver opens the app, his real-time location in Firebase is saved. When\na student opens the app, nearby buses within a 3km of radius are shown to the student.\nWe have also developed a Website for admins who can remove or add buses.\nTools for Android: Java, XML, Gradle, and Firebase Database.\nTools for Web: HTML5, CSS3, JavaScript, jQuery, React, Python and MySQL."
    },
    "details": {
        "name": "Samha Ahmed",
        "number": "923324817353",
        "skills": [
            "C++",
            "ORACLE",
            "PHP",
            "HTML",
            "CSS",
            "JAVA",
            "HTML5",
            "CSS3",
            "JavaScript",
            "jQuery",
            "React",
            "Python",
            "MySQL",
            "XML",
            "Gradle",
            "Firebase Database"
        ],
        "email_id": "samhaahmed39@gmail.com",
        "location": "Lahore, Pakistan",
        "projects": [
            {
                "title": "Campus Management System",
                "description": "Developed in C++."
            },
            {
                "title": "NGO Database System",
                "description": "Developed in ORACLE using PHP, HTML, and CSS."
            },
            {
                "title": "Ludo Game",
                "description": "Developed in JAVA."
            },
            {
                "title": "Online Art Gallery",
                "description": "Developed using HTML, CSS, Bootstrap, JavaScript, AJAX, jQuery, and JSON."
            },
            {
                "title": "PU E-Bus Tracking Application",
                "description": "Android-based application providing real-time bus locations."
            }
        ],
        "education": [
            {
                "end_date": "06-2021",
                "university": "Punjab University College of Information Technology, Lahore",
                "degree_title": "BS Information Technology"
            },
            {
                "end_date": "05-2017",
                "university": "Punjab College of Science, Lahore",
                "degree_title": "F.Sc Pre-Engineering"
            },
            {
                "end_date": "05-2015",
                "university": "Wapda Girls High School, Lahore",
                "degree_title": "Matriculation"
            }
        ],
        "achievements": [],
        "publications": [],
        "certifications": [],
        "additional_urls": [],
        "executive_summary": "Samha Ahmed is a skilled business development executive with a strong background in information technology. She has experience in various programming languages and technologies, demonstrating her technical proficiency in software development and project management.",
        "employment_history": [
            {
                "details": "Business Development Executive at Rolustech.",
                "end_date": "Present",
                "location": "Lahore, Pakistan",
                "job_title": "Business Development Executive",
                "start_date": "09-2021",
                "company_name": "Rolustech"
            },
            {
                "details": "Business Development Executive at TxLabz.",
                "end_date": "09-2021",
                "location": "Lahore, Pakistan",
                "job_title": "Business Development Executive",
                "start_date": "05-2021",
                "company_name": "TxLabz"
            },
            {
                "details": "Associate Project Manager at TxLabz.",
                "end_date": "09-2021",
                "location": "Lahore, Pakistan",
                "job_title": "Associate Project Manager",
                "start_date": "06-2021",
                "company_name": "TxLabz"
            }
        ]
    }
}