{
    "output": {
        "justification": [
            "Yahya Malik has over 9 years of experience in business development and sales, which exceeds the 5-year minimum requirement for the position.",
            "The role as a Business Development Manager at ACET Solutions since June 2021 aligns with the job title sought, indicating relevant experience.",
            "Skills in strategy planning and execution, as well as leadership roles, match the strategic planning and leadership requirements outlined in the job description.",
            "Advanced knowledge of CRM tools like Salesforce and market insights-driven strategy execution aligns with the preferred skills for the role at MarketPros Enterprises."
        ],
        "scores": {
            "macro_scores": [
                {
                    "criteria": "strategic planning",
                    "score": 8
                }
            ],
            "micro_scores": [
                {
                    "criteria": "digital marketing",
                    "score": 7
                }
            ],
            "requirements": [
                {
                    "criteria": "Strong analytical and strategic planning skills",
                    "meets": true
                },
                {
                    "criteria": "5+ years of experience in business development or sales management",
                    "meets": true
                }
            ],
            "aggregated_scores": {
                "macro_scores": 8.0,
                "micro_scores": 7.0
            }
        },
        "personal_info": {
            "name": "Yahya Malik",
            "email": "yahyamalik1@outlook.com",
            "phone": "+971504680678",
            "current_position": "Business Development Manager",
            "current_company": "ACET Solutions",
            "employment_start_date_current_company": "06-2021",
            "first_company_start_date": "01-2015",
            "urls": [
                {
                    "website_name": "LinkedIn",
                    "url": "www.linkedin.com/in/engryahyamalik"
                }
            ]
        },
        "valid_resume_and_jd": true
    },
    "input": {
        "job_description": "**Title: Business Development Manager**  \n\n**Company: MarketPros Enterprises**  \n\n**Location: Remote with potential travel to client locations**  \n\n**About Us:**  \nMarketPros Enterprises is a leading global provider of innovative business solutions with the aim of maximizing brand growth. We work with diverse industries to enhance their sales infrastructure and provide unparalleled customer engagement strategies.  \n\n**Role Overview:**  \nAs a Business Development Manager at MarketPros Enterprises, you will be responsible for leading strategic initiatives that drive business growth, increase market share, and strengthen client relationships. You will manage cross-functional teams to implement sales strategies, harness market insights, and drive brand expansion.  \n\n**Key Responsibilities:**  \n- Develop and implement comprehensive business strategies to enhance revenue growth.  \n- Lead a team in executing marketing campaigns and optimizing sales pipelines.  \n- Utilize data analytics tools to produce actionable insights improving overall performance.  \n- Conduct market research to identify industry trends and new business opportunities.  \n- Engage with potential clients via presentations and foster long-term relationships.  \n- Manage CRM systems (Salesforce, HubSpot) to streamline operations and enhance productivity.  \n\n**Preferred Skills:**  \n- Proficiency in strategic planning and market analysis.  \n- Strong leadership skills with proven experience in team development.  \n- Advanced knowledge of CRM software and digital marketing tools.  \n- Excellent communication and negotiation skills.  \n\nJoin us to push the boundaries of business innovation and help us achieve our expansion goals.  \n",
        "macro_dict": {
            "strategic planning": 100
        },
        "micro_dict": {
            "digital marketing": 100
        },
        "additional_info": "MarketPros Enterprises values diversity in hiring and encourages applications from seasoned business professionals with varied backgrounds. Preferred universities include Ivy League institutions and top business schools. We offer relocation benefits for exceptional candidates and facilitate remote working arrangements. Technical and strategic competencies are assessed through a mix of psychometric evaluations and case study interviews.",
        "minimum_requirements": [
            "Strong analytical and strategic planning skills",
            "5+ years of experience in business development or sales management"
        ],
        "resume": "\u00a0 \u00a0\nContact\nDubai,United Arab Emirates \nUAE Number: +971504680678\nPAK Number: +923108141420\nKSA Number: +966546978135\nyahyamalik1@outlook.com\nwww.linkedin.com/in/\nengryahyamalik  (LinkedIn)\nTop Skills\nAutomation\nInstrumentation\nOT Cyber Security\nLanguages\nEnglish  (Professional Working)\nCertifications\nISA 62443 Cybersecurity\nFundamentals Specialist\nNSE 1,2,3 Network Security\nAssociate\nNozomi Certified Sales Professional\n(NNCTSP) \nIELTS General \nHoneywell Certified Sales\nProfessional on Process Control\nSystems\nHonors-Awards\nOrganizer - Annual Technical\nConference 2017\nOrganizer - POGEE 2018\nOrganizer-OT Cybersecurity\nImplementation Conference by ISA\nOrganizer-Cybersecurity for Critical\nAssets MENA\nEmployee of the Month AwardYahya M.\nBusiness Development Manager | Sales Leader | Industrial\nAutomation | Account Manager | OT Cybersecurity ISA 62443 CFS\n| Digital Transformation | IT/OT Integration | Closed Multimillion $\nProjects in last 5 years\nDubai, United Arab Emirates\nSummary\nyahyamalik1@outlook.com \nYahya Malik is a Seasoned Engineer-turned Marketer, with 9+\nyears of diverse experience in the field of B2B Sales, Negotiation,\nCustomer Relations Management, Product Management Process\nAutomation & OT Cybersecurity with a keen interest in IIOT.\nWorked with Industry leaders such as Nozomi Networks, Palo Alto,\nFortinet, ABB, Rockwell Automation, Yokogawa, Honeywell, General\nMonitors, Trend Micro, TXOne & Schneider. Creating win to win\nstrategy for my organization and for my customers as well\nCurrently, I am working as Business Development Manager at ACET\nSolutions. Here, we are not only helping enterprises with our OT and\nICS solutions but also helping them secure their digital infrastructure\nthrough our in-depth cybersecurity practices. With deep expertise in\nmature and emerging OT/IT means, we are helping various verticals\nautomate their processes, secure their infrastructure, and enhance\noperational productivity\nMy forte ranging from Lead Generation, Market Research, Business\nDevelopment, International Sales, Key Accounts Management, Sales\nOperations, Sales Strategy, Product Management, New Business\nDevelopment and Customer Satisfaction\nFundamental understanding of OT/ICS Cyber security basics and\nmodern concepts related to;\n-Firewalls, Intrusion detection and prevention, DMZ's, Remote\nAccess Solutions \n-Data leakage prevention\n-Secure Cloud, Data security, Security operations tools,\n\u00a0 Page 1 of 3\u00a0 \u00a0\n-ISA 62443 & Other OT Cybersecurity Standards\nTechnologies: \nIndustrial Automation | Industry 4.0 | Industrial IOT | IT/OT\nIntegration | Enterprise Management System | Data Historian &\ncloud | Cybersecurity | SCADA | Solar | Electrical | Instrumentation |\nRenewable Energy | \nIndustry Verticals:\nOil & Gas | Process | Utilities & Power | Metals | FMCG\nGeographies:\nPakistan | GCC | West Africa | Singapore | USA\nClients: \nFortune 100 | Government | EPCs | OEMs \nFunctional Competencies: \nStrategy Planning & Execution | Product and Solutions Proposals\n| P&L Management | Key Account Management | Negotiations\n| Business Development | Customer Relationship Management\n| Competitive Analysis | Solution & Services Sales Demand\nGeneration | Brand Positioning | Strategic Alliances & Partnerships |\nDigital transformation | Control Systems (PLC,DCS,SCADA) | EPC\nConnect with Yahya:\nWatsapp UAE: +971 50 468 0678\nWatsapp KSA: +966 54 697 8135\nWatsapp PAK: +92 310 814 1420 \nOfficial Email ID: yahya.malik@acetsolutions.com\nExperience\nACET Solutions\nBusiness Development Manager\nJune 2021\u00a0-\u00a0Present\u00a0 (2 years)\nUnited Arab Emirates\n\u00a0 Page 2 of 3\u00a0 \u00a0\n-Looking after Sales and Business Development of Automation, OT\nCybersecurity & Digital Enterprise Technology solutions in Pakistan & Middle\nEast Market\nInternational Society of Automation (ISA)\n2 years 5 months\nPresident Elect\nOctober 2022\u00a0-\u00a0Present\u00a0 (8 months)\nBoard Member (Webinars & Seminars)\nJanuary 2021\u00a0-\u00a0October 2022\u00a0 (1 year 10 months)\nDescon\nBusiness Development Manager\nNovember 2017\u00a0-\u00a0May 2021\u00a0 (3 years 7 months)\nUnited Arab Emirates\nLean Automation\nDesign Application Engineer\nJanuary 2016\u00a0-\u00a0October 2017\u00a0 (1 year 10 months)\nUnited Arab Emirates\nCoca-Cola Beverages Pakistan Limited\nGraduate Management Trainee\nJanuary 2015\u00a0-\u00a0December 2015\u00a0 (1 year)\nPakistan\nEducation\nLahore University of Management Sciences\nArt of Selling Ideas-Advertising 101,\u00a0Print, Outdoor and Digital\nMarketing \u00a0\u00b7\u00a0(March 2021)\nNEBOSH\nNebosh International General Certificate in Occupational Health and\nSafety,\u00a0Occupational Health and Safety \u00a0\u00b7\u00a0(January 2021)\nCOMSATS University\nEngineer\u2019s Degree,\u00a0Electrical and Electronics Engineering \u00a0\u00b7\u00a0(2010)\n\u00a0 Page 3 of 3"
    },
    "details": {
        "name": "Yahya Malik",
        "number": "971504680678",
        "skills": [
            "Automation",
            "Instrumentation",
            "OT Cyber Security",
            "Industrial Automation",
            "Industry 4.0",
            "Industrial IOT",
            "IT/OT Integration",
            "Enterprise Management System",
            "Data Historian & cloud",
            "Cybersecurity",
            "SCADA",
            "Solar",
            "Electrical",
            "Instrumentation",
            "Renewable Energy"
        ],
        "email_id": "yahyamalik1@outlook.com",
        "location": "Dubai, United Arab Emirates",
        "projects": [],
        "education": [
            {
                "end_date": "03-2021",
                "university": "Lahore University of Management Sciences",
                "degree_title": "Art of Selling Ideas-Advertising 101, Print, Outdoor and Digital Marketing"
            },
            {
                "end_date": "01-2021",
                "university": "NEBOSH",
                "degree_title": "Nebosh International General Certificate in Occupational Health and Safety"
            },
            {
                "end_date": "2010",
                "university": "COMSATS University",
                "degree_title": "Engineer\u2019s Degree, Electrical and Electronics Engineering"
            }
        ],
        "achievements": [
            "Organizer - Annual Technical Conference 2017",
            "Organizer - POGEE 2018",
            "Organizer - OT Cybersecurity Implementation Conference by ISA",
            "Organizer - Cybersecurity for Critical Assets MENA",
            "Employee of the Month Award"
        ],
        "publications": [],
        "certifications": [
            {
                "certification_name": "ISA 62443 Cybersecurity Fundamentals Specialist",
                "issuing_organization": "ISA",
                "date_of_issuance": "01-2021"
            },
            {
                "certification_name": "NSE 1,2,3 Network Security Associate",
                "issuing_organization": "Fortinet",
                "date_of_issuance": "01-2021"
            },
            {
                "certification_name": "Nozomi Certified Sales Professional (NNCTSP)",
                "issuing_organization": "Nozomi Networks",
                "date_of_issuance": "01-2021"
            },
            {
                "certification_name": "Honeywell Certified Sales Professional on Process Control Systems",
                "issuing_organization": "Honeywell",
                "date_of_issuance": "01-2021"
            }
        ],
        "additional_urls": [
            {
                "url": "linkedin.com/in/engryahyamalik",
                "website_name": "LinkedIn"
            }
        ],
        "executive_summary": "Yahya Malik is a seasoned engineer-turned marketer with over 9 years of diverse experience in B2B sales, negotiation, customer relations management, product management, process automation, and OT cybersecurity. He has worked with industry leaders and is currently a Business Development Manager at ACET Solutions, focusing on automation and cybersecurity solutions. His expertise includes managing multimillion-dollar projects and enhancing operational productivity across various sectors.",
        "employment_history": [
            {
                "details": "Looking after Sales and Business Development of Automation, OT Cybersecurity & Digital Enterprise Technology solutions in Pakistan & Middle East Market",
                "end_date": "Present",
                "location": "United Arab Emirates",
                "job_title": "Business Development Manager",
                "start_date": "06-2021",
                "company_name": "ACET Solutions"
            },
            {
                "details": "President Elect, overseeing webinars and seminars for the organization",
                "end_date": "Present",
                "location": "United Arab Emirates",
                "job_title": "President Elect",
                "start_date": "10-2022",
                "company_name": "International Society of Automation (ISA)"
            },
            {
                "details": "Managed business development activities in the UAE market",
                "end_date": "05-2021",
                "location": "United Arab Emirates",
                "job_title": "Business Development Manager",
                "start_date": "11-2017",
                "company_name": "Descon"
            },
            {
                "details": "Worked on design applications in automation",
                "end_date": "10-2017",
                "location": "United Arab Emirates",
                "job_title": "Design Application Engineer",
                "start_date": "01-2016",
                "company_name": "Lean Automation"
            },
            {
                "details": "Completed a management trainee program focusing on various business functions",
                "end_date": "12-2015",
                "location": "Pakistan",
                "job_title": "Graduate Management Trainee",
                "start_date": "01-2015",
                "company_name": "Coca-Cola Beverages Pakistan Limited"
            }
        ]
    }
}