{
    "output": {
        "justification": [
            "The candidate demonstrates significant leadership experience as Director of Sales, managing teams and driving revenue, scoring highly on leadership.",
            "Relevant experience in sales and SEO roles is evident, although the resume lacks explicit details on digital marketing specifics or SEO strategies, scoring moderately.",
            "The resume does not explicitly mention skills in Excel or Python, making these difficult to score and therefore marked low.",
            "The resume fits the requirement for 3+ years of sales experience but lacks evidence of a Master's degree as listed in the job description."
        ],
        "scores": {
            "macro_scores": [
                {
                    "criteria": "leadership",
                    "score": 8
                }
            ],
            "micro_scores": [
                {
                    "criteria": "team management",
                    "score": 8
                }
            ],
            "requirements": [
                {
                    "criteria": "3+ years of experience in SEO and digital marketing",
                    "meets": false
                },
                {
                    "criteria": "Strong analytical and strategic thinking skills",
                    "meets": true
                },
                {
                    "criteria": "Proven track record in sales and client relationship management",
                    "meets": true
                },
                {
                    "criteria": "Master's degree in Business Administration or related field",
                    "meets": false
                }
            ],
            "aggregated_scores": {
                "macro_scores": 8.0,
                "micro_scores": 8.0
            }
        },
        "personal_info": {
            "name": "Zeeshan Ashraf",
            "email": "zshanashraf257@gmail.com",
            "phone": "+923345934550",
            "current_position": "Director of Sales and Business Development",
            "current_company": "Stella Technology",
            "employment_start_date_current_company": "10-2021",
            "first_company_start_date": "09-2014",
            "urls": [
                {
                    "website_name": "Bold Profile",
                    "url": "https://bold.pro/my/sardarzeeshan-ashraf-230213093500/276"
                }
            ]
        },
        "valid_resume_and_jd": true
    },
    "input": {
        "job_description": "## Job Title: Sales and SEO Management Specialist  \n\n### Location: Lahore, Pakistan  \n\n### Company: Innovate Digital Solutions Inc.  \n\n### Job Summary:  \nJoin Innovate Digital Solutions Inc. as a Sales and SEO Management Specialist. You will be part of a dynamic team responsible for driving client engagement and ensuring optimal performance in digital marketing strategies. Your role will include managing client relationships, improving SEO strategies, and leading your team to achieve sales targets.  \n\n### Key Responsibilities:  \n- Proactively engage with prospective clients to understand their business needs and provide innovative solutions.  \n- Design and execute SEO strategies in alignment with client\u2019s marketing objectives.  \n- Manage and optimize PPC campaigns to maximize ROI and brand visibility.  \n- Develop and maintain strong client relationships through tailored marketing solutions.  \n- Lead a team to achieve and surpass sales targets while providing exceptional customer service.  \n- Analyze market trends and algorithms to tailor SEO strategies accordingly.  \n- Produce reports that track progress and measure success against KPIs.  \n\n### Ideal Candidate Profile:  \nYou are a skilled sales and marketing professional with strong analytical skills suited to identifying and executing SEO opportunities. You excel at client interactions, possessing the ability to transform potential leads into satisfied clients through strategic and well-executed marketing initiatives. Leadership and team management skills will be pivotal to drive sales and motivate your team.  \n\n### Benefits:  \n- Competitive salary package  \n- Health and wellness benefits  \n- Performance bonuses  \n- Opportunities for career advancement  \n\nJoin us to redefine digital engagement and lead market strategies with agility and innovation.",
        "macro_dict": {
            "leadership": 100
        },
        "micro_dict": {
            "team management": 100
        },
        "additional_info": "Innovate Digital Solutions Inc. prefers candidates from reputable institutions such as [University of Lahore], [Punjab University]. Remote work options are available subject to roles and responsibilities. We assess skills through a combination of technical tests, interviews, and real-world problem-solving scenarios to gauge practical competency in strategic marketing contexts.",
        "minimum_requirements": [
            "3+ years of experience in SEO and digital marketing",
            "Strong analytical and strategic thinking skills",
            "Proven track record in sales and client relationship management",
            "Master's degree in Business Administration or related field"
        ],
        "resume": "Zeeshan Ashraf\nDirector Of Sales And Business\nDevelopmentza\nProfessional Summary\nFocused Sales Development leader committed to\nmotivating others and offering extensive\nknowledge penetrating new territories and\npromoting product lines. Highly effective mentor\ndriven to assess individual and group\nperformance to implement improvements and\nset goals. Determined individual with background\nin establishing and nurturing lucrative\npartnerships. Expert in increasing productivity and\ncustomer satisfaction while driving revenue and\nsales. Committed to streamlining procedures\nwhile optimizing employee talent.\nWork History\n2021-10  -\nCurrentDirector of Sales and Business\nDevelopment\nStella Technology ,Islamabad\nIn liaison with technical team of engineers,\nmanaged to turn multiple healthcare software\ndevelopment leads to sales.\nManaged to arrange various booths on\nhealthcare exhibitions worldwide i.e. HIMSS\n(USA), VIVE (USA),HLTH (KSA) LEAP (KSA) & Arab\nHealth (UAE).\nEnsured the completion and facilitation of\nvarious certifications for the team i.e. FHIR\nstandards, HL7 certifications.\nIdentified, hired and trained highly-qualified\nstaff by teaching best practices, procedures,\nand sales strategies\nMaintained ethical and positive working\nenvironment to reduce turnover and promote\nhigh retention rates\nManage to help grow annual revenue from\nContact\nAddress\nIslamabad, Pakistan 44000\nPhone\n+923345934550\nE-mail\nzshanashraf257@gmail.com\nWWW\nhttps://bold.pro\n/my/sardarzeeshan-ashraf-\n230213093500/276\nSkills\nExcellent\nMS Office and presentation\nskills\nExcellent\nRFQ- Quote creation.\nExcellent\nVerbal and written\ncommunication\nExcellent\nStrategic account\ndevelopment\nExcellent$20M to $50M\nOverhauled client onboarding processes\nwhich improved client engagement by 50%\nHandled customer relations issues, enabling\nquick resolution, and client satisfaction\nCoached employees in successful selling\nmethods and encouraged cross-selling to drive\nrevenue.\nResolved customer issues quickly to close deals\nand boost client satisfaction.\nMet with clients, delivering presentations, and\neducating on product and service features\nand offerings.\nMaintained relationships with customers and\nfound new ones by identifying needs and\noffering appropriate services.\nReported on leads, sales opportunities,\nprogress and activity, informing weekly\nforecasts and monthly pipeline development.\n2021-01  -\n2021-09Director of Sales Operations\nConvo ,Islamabad\nRecommended sales strategies for\nimprovement based on regular market\nresearch and competitor analysis\nBuilt, trained and managed sales and\noperational teams to carry out sales initiatives\nand reach objectives\nStandardized and reduced email\ncommunications between employees by\nformulating and implementing field\ncommunication processes\nDemonstrated products to show potential\ncustomers benefits and advantages and\nencourage purchases\nEngaged in product training, demonstrations,\nconsumer awareness, branding, and\nacquisition initiatives to raise awareness and\nrevenues\nAchieved sales goals and service targets by\ncultivating and securing new customer\nrelationships\nImplemented and executed sales and\noperational policies, experiments andPOS CRM/Salesforce\nVery Good\nHubSpot expert\nExcellent\nDirect sales\nExcellent\nSales expertise\nExcellent\nTime management\nExcellent\nAnalytical Problem Solver\nExcellent\nEmpowers high-performing\nsales teams\nExcellent\nSales operation\nExcellent\nLeadership and\nmanagement\nExcellent\nLanguages\nEnglish\nExcellent\nUrdu\nExcellent\nHindi\nExcellent\nPunjabi\nExcellent\nHindkostandards across multiple facilities and\nsub-brands\nIdentified, developed and launched\ninnovative tools or systems to achieve sales\nstrategies.\n2017-10  -\n2020-12Manager Commercial\nZones LLC ,Islamabad\nStrengthened communication skills through\nregular interactions with others\nWorked effectively in fast-paced environments\nPaid attention to detail while completing\nassignments\nSkilled at working independently and\ncollaboratively in team environment\nDeveloped and maintained courteous and\neffective working relationships\nVolunteered at local community organizations,\nproviding assistance with day-to-day\noperations\nUsed critical thinking to break down problems,\nevaluate solutions and make decisions\nWorked well in team setting, providing support\nand guidance\nIdentified issues, analyzed information and\nprovided solutions to problems\nExercised leadership capabilities by\nsuccessfully motivating and inspiring others.\n2016-08  -\n2017-09Sr. Project Coordinator PSO\nOvex Technologies ,Islamabad\nProvided services to Ovex Technologies for\ntheir client En Pointe Sales LLC (Based in USA)\nas Sr.Project coordinator\nExtended support to manage all ongoing and\ncompleted projects by means of tracking,\nuploading into software \u201cOpenAir\u201d and\nscheduling and conducting meetings related\nto projects both with customers and relevant\naccount managers/executives\nAs part of this role, I dealt with preparation of\nscope of work (SOW) and defined all contentsExcellentwith regards to resource's allocation, billing\nterms, solicitation and time frame of activity\nbeing performed.\nDealt with the Microsoft team for the allocation\nof MS (Microsoft funding) and their track and\naccounting adapt to the procedures and\ntimelines defined by Microsoft.\nPlayed key role in reporting by means of\nextraction of relevant data from the software\nand putting into a desired presentable report\non weekly, fortnightly, and monthly basis\nClose condition with GL (General Ledger),\nRebates, Commissions, and all other\ndepartments to get financial entries posted\nCreating the productive utilization report of\nresources to update the management about\nthe revenue being generated by the\ndeployment of resources\nExtended services to audit vendor invoices\nthat are being received in case of 3rd party\nresource deployment\nDealing with initial and final entries related to\nthe billing to customers and creating the\npresentation every month to depict the flow of\nrevenue generated.\n2014-09  -\n2016-07Sales Specialist\nCisco Systems Inc ,Islamabad\nDone the compliance of ongoing deals which\nare expected to get converted in\nopportunities then sales.\nExtended services to customers globally in all\ntheatres i.e. APJC, EMEAR, USA and Americas\nto introduce new products and services being\nlaunched and get WebEx meetings scheduled\nfor demo and \u201cHealth Check\u201d of currently\ninstalled applications on their servers.\nFollowing the goal defined, I have extended\nmy services to ensure that the revenue\ngeneration is up to the mark by adopting\nvarious strategies to ease and benefit the\ncustomer considering organization's best\ninterests.\nMaintaining close liaison between theorganization and partner companies and end\ncustomers thereafter to pull out maximum\nbusiness opportunities.\nWorked on various projects of organization to\nlaunch and introduce them to international as\nwell as domestic customers i.e. Demo and\nhealth check of UCS (Unified computing\nservices) along with other Cisco products.\nCompiling comparative reports to forecast\nfuture trend of business and to prepare prior\nstrategies to cope with uncertainties.\nMade strategies in accordance with results of\ninterim audit to mitigate vulnerabilities in\nongoing operations.\nBriefed about product/services structure and\nfeatures to international customers.\nTracking progress against targets on an\nongoing basis and take necessary actions to\nrefocus efforts if targets are not being met.\nWorked on special projects in accordance\nwith the management plan and ensured the\nmaximum output with minimum resource\ndeployed in minimum time slot.\nEducation\nMatriculation : Science Education\nBoard of Intermediate & Secondary Edu RWP\nIntermediate : Banking, Statistics,\nMarketing\nIslamabad Model Post Graduate College of\nCommerce\nB.COM Bachelors of Commerce :\nCommerce & IT\nIslamabad Model Post Graduate College of\nCommerce\nCA Foundation\nICAPAccomplishments\nFast track promotion at Zones from Account\nExecutive to Sales Manager within one year\nbecause of extra ordinary sales results\nRecognized consistently by management for\nclosing every quarter and year with\noutstanding numbers in terms of GMD and\nRevenue\nWinner of various R & R's within the process\nAdditional Information\nManaging Multiple Projects -providing\non-demand and well managed IT support\nservices\nRecently attended Arab Health exhibition by\nInforma Markets in Dubai UAE where I met\nhundred of prospects to increase sales\nspectrum\nTrainings and Certifications\n\u00a0\nAWS PartnerCast - New ISV partner orientation\n(Business)\nAWS Partner: Modern applications on AWS -\nSales Best Practices.\nAWS Partner: Amazon Connect (Business)\n(Digital)\nAWS Partner: APN Technology Partners\nCo-Selling with AWS (Business)\nAWS Partner: Accreditation (Business)ion\n(Business)\nCisco Meraki Fit 1"
    },
    "details": {
        "name": "Zeeshan Ashraf",
        "number": "923345934550",
        "skills": [
            "POS CRM/Salesforce",
            "HubSpot",
            "Direct sales",
            "Sales expertise",
            "Time management",
            "Sales operation",
            "Leadership and management"
        ],
        "email_id": "zshanashraf257@gmail.com",
        "location": "Islamabad, Pakistan 44000",
        "projects": [],
        "education": [
            {
                "end_date": "07-2016",
                "university": "Islamabad Model Post Graduate College of Commerce",
                "degree_title": "B.COM Bachelors of Commerce : Commerce & IT"
            },
            {
                "end_date": "01-2014",
                "university": "Islamabad Model Post Graduate College of Commerce",
                "degree_title": "Intermediate : Banking, Statistics, Marketing"
            },
            {
                "end_date": "09-2011",
                "university": "Board of Intermediate & Secondary Edu RWP",
                "degree_title": "Matriculation : Science Education"
            }
        ],
        "achievements": [
            "Fast track promotion at Zones from Account Executive to Sales Manager within one year because of extraordinary sales results",
            "Recognized consistently by management for closing every quarter and year with outstanding numbers in terms of GMD and Revenue",
            "Winner of various R & R's within the process"
        ],
        "publications": [],
        "certifications": [
            {
                "certification_name": "AWS PartnerCast - New ISV partner orientation",
                "issuing_organization": "AWS Partner",
                "date_of_issuance": "01-2023"
            },
            {
                "certification_name": "AWS Partner: Modern applications on AWS - Sales Best Practices",
                "issuing_organization": "AWS Partner",
                "date_of_issuance": "01-2023"
            },
            {
                "certification_name": "AWS Partner: Amazon Connect (Business)",
                "issuing_organization": "AWS Partner",
                "date_of_issuance": "01-2023"
            },
            {
                "certification_name": "AWS Partner: APN Technology Partners Co-Selling with AWS",
                "issuing_organization": "AWS Partner",
                "date_of_issuance": "01-2023"
            },
            {
                "certification_name": "AWS Partner: Accreditation",
                "issuing_organization": "AWS Partner",
                "date_of_issuance": "01-2023"
            },
            {
                "certification_name": "Cisco Meraki Fit 1",
                "issuing_organization": "Cisco",
                "date_of_issuance": "01-2023"
            }
        ],
        "additional_urls": [
            {
                "url": "bold.pro/my/sardarzeeshan-ashraf-230213093500/276",
                "website_name": "bold.pro"
            }
        ],
        "executive_summary": "Zeeshan Ashraf is a dedicated Director of Sales and Business Development with a proven track record in driving revenue growth and managing successful sales teams. With extensive experience in healthcare software sales and a strong background in operational management, he excels in developing strategic partnerships and optimizing sales processes to enhance customer satisfaction and business performance.",
        "employment_history": [
            {
                "details": "In liaison with technical team of engineers, managed to turn multiple healthcare software development leads to sales. Managed to arrange various booths on healthcare exhibitions worldwide i.e. HIMSS (USA), VIVE (USA), HLTH (KSA) LEAP (KSA) & Arab Health (UAE). Ensured the completion and facilitation of various certifications for the team i.e. FHIR standards, HL7 certifications. Identified, hired and trained highly-qualified staff by teaching best practices, procedures, and sales strategies.",
                "end_date": "Current",
                "location": "Islamabad",
                "job_title": "Director of Sales and Business Development",
                "start_date": "10-2021",
                "company_name": "Stella Technology"
            },
            {
                "details": "Recommended sales strategies for improvement based on regular market research and competitor analysis. Built, trained and managed sales and operational teams to carry out sales initiatives and reach objectives. Standardized and reduced email communications between employees by formulating and implementing field communication processes.",
                "end_date": "09-2021",
                "location": "Islamabad",
                "job_title": "Director of Sales Operations",
                "start_date": "01-2021",
                "company_name": "Convo"
            },
            {
                "details": "Strengthened communication skills through regular interactions with others. Worked effectively in fast-paced environments. Paid attention to detail while completing assignments. Developed and maintained courteous and effective working relationships.",
                "end_date": "12-2020",
                "location": "Islamabad",
                "job_title": "Manager Commercial",
                "start_date": "10-2017",
                "company_name": "Zones LLC"
            },
            {
                "details": "Provided services to Ovex Technologies for their client En Pointe Sales LLC (Based in USA) as Sr.Project coordinator. Extended support to manage all ongoing and completed projects by means of tracking, uploading into software 'OpenAir' and scheduling and conducting meetings related to projects both with customers and relevant account managers/executives.",
                "end_date": "09-2017",
                "location": "Islamabad",
                "job_title": "Sr. Project Coordinator",
                "start_date": "08-2016",
                "company_name": "Ovex Technologies"
            },
            {
                "details": "Done the compliance of ongoing deals which are expected to get converted in opportunities then sales. Extended services to customers globally in all theatres i.e. APJC, EMEAR, USA and Americas to introduce new products and services being launched and get WebEx meetings scheduled for demo and 'Health Check' of currently installed applications on their servers.",
                "end_date": "07-2016",
                "location": "Islamabad",
                "job_title": "Sales Specialist",
                "start_date": "09-2014",
                "company_name": "Cisco Systems Inc"
            }
        ]
    }
}