{
    "output": {
        "justification": [
            "The candidate has demonstrated significant leadership by serving as a President Elect and a board member in ISA, which is relevant for leadership roles.",
            "The candidate's experience includes a range of business development activities which aligns well with the responsibilities of the role.",
            "Although the candidate has strong experience in automation and cybersecurity, there is limited mention of specific lead generation and data management tasks required by the job description.",
            "The candidate lacks specific mention of using digital marketing skills, email marketing, CRM, or tools like Power BI and Tableau, hence lower scores in those areas."
        ],
        "scores": {
            "macro_scores": [
                {
                    "criteria": "leadership",
                    "score": 8
                },
                {
                    "criteria": "experience",
                    "score": 6
                },
                {
                    "criteria": "innovation and adaptability",
                    "score": 7
                }
            ],
            "micro_scores": [
                {
                    "criteria": "crm and data management",
                    "score": 4
                },
                {
                    "criteria": "digital marketing skills",
                    "score": 5
                },
                {
                    "criteria": "project management",
                    "score": 5
                }
            ],
            "requirements": [
                {
                    "criteria": "3+ years of experience in lead generation or business intelligence",
                    "meets": false
                }
            ],
            "aggregated_scores": {
                "macro_scores": 7.33,
                "micro_scores": 4.59
            }
        },
        "personal_info": {
            "name": "Yahya Malik",
            "email": "yahyamalik1@outlook.com",
            "phone": "+971504680678",
            "current_position": "Business Development Manager",
            "current_company": "ACET Solutions",
            "employment_start_date_current_company": "06-2021",
            "first_company_start_date": "01-2015",
            "urls": [
                {
                    "website_name": "LinkedIn",
                    "url": "www.linkedin.com/in/engryahyamalik"
                }
            ]
        },
        "valid_resume_and_jd": true
    },
    "input": {
        "job_description": "## Lead Generation and Business Intelligence Specialist\n\nJoin **Innovate Connections Inc.** as a Lead Generation and Business Intelligence Specialist. You will play a pivotal role in driving business growth by spearheading lead generation initiatives and providing strategic insights through data analytics. We are looking for a highly skilled professional with a strong background in lead generation, data management, and business intelligence.\n\n### Key Responsibilities:\n- Develop and execute lead generation strategies using digital marketing techniques, cold calling, and data scraping tools.\n- Collaborate with cross-functional teams to optimize customer acquisition strategies.\n- Utilize CRM systems to manage and analyze client data for lead qualification.\n- Create and manage detailed project schedules and work plans, utilizing best practices and standards for project execution.\n- Develop financial models and business growth strategies based on data insights.\n- Utilize tools such as Power BI, SQL, and Tableau for developing comprehensive data reports and dashboards.\n\n### Desired Skills and Experience:\n- Strong programming skills in C++, HTML, and CSS.\n- Proficiency in digital marketing, email marketing, and social media platforms.\n- Experience in managing large data sets and using BI tools (Power BI, Excel, Tableau).\n- Excellent communication skills and ability to develop strong client relationships.\n- Ability to work independently and manage multiple projects simultaneously.\n\n### Why Innovate Connections Inc.?\n- We innovate at the forefront of technology and enable our team members to grow alongside the company.\n- We value data-driven decision-making and empower our teams with the right tools to succeed.\n- Offering a supportive work environment and opportunities for career advancement.\n\n### How to Apply:\nSubmit your resume and cover letter detailing your relevant experience and why you are interested in joining Innovate Connections Inc.",
        "macro_dict": {
            "leadership": 58,
            "experience": 25,
            "innovation and adaptability": 17
        },
        "micro_dict": {
            "crm and data management": 41,
            "digital marketing skills": 8,
            "project management": 51
        },
        "additional_info": "Innovate Connections Inc. prefers candidates from recognized universities such as the University of Management & Technology and Lahore School of Economics. We encourage a remote working environment but require physical presence for team-building and strategic sessions twice a quarter. Relocation assistance is available for exceptional candidates. Our comprehensive assessment includes a technical test followed by structured interviews to evaluate both technical and soft skills comprehensively.",
        "minimum_requirements": [
            "3+ years of experience in lead generation or business intelligence"
        ],
        "resume": "\u00a0 \u00a0\nContact\nDubai,United Arab Emirates \nUAE Number: +971504680678\nPAK Number: +923108141420\nKSA Number: +966546978135\nyahyamalik1@outlook.com\nwww.linkedin.com/in/\nengryahyamalik  (LinkedIn)\nTop Skills\nAutomation\nInstrumentation\nOT Cyber Security\nLanguages\nEnglish  (Professional Working)\nCertifications\nISA 62443 Cybersecurity\nFundamentals Specialist\nNSE 1,2,3 Network Security\nAssociate\nNozomi Certified Sales Professional\n(NNCTSP) \nIELTS General \nHoneywell Certified Sales\nProfessional on Process Control\nSystems\nHonors-Awards\nOrganizer - Annual Technical\nConference 2017\nOrganizer - POGEE 2018\nOrganizer-OT Cybersecurity\nImplementation Conference by ISA\nOrganizer-Cybersecurity for Critical\nAssets MENA\nEmployee of the Month AwardYahya M.\nBusiness Development Manager | Sales Leader | Industrial\nAutomation | Account Manager | OT Cybersecurity ISA 62443 CFS\n| Digital Transformation | IT/OT Integration | Closed Multimillion $\nProjects in last 5 years\nDubai, United Arab Emirates\nSummary\nyahyamalik1@outlook.com \nYahya Malik is a Seasoned Engineer-turned Marketer, with 9+\nyears of diverse experience in the field of B2B Sales, Negotiation,\nCustomer Relations Management, Product Management Process\nAutomation & OT Cybersecurity with a keen interest in IIOT.\nWorked with Industry leaders such as Nozomi Networks, Palo Alto,\nFortinet, ABB, Rockwell Automation, Yokogawa, Honeywell, General\nMonitors, Trend Micro, TXOne & Schneider. Creating win to win\nstrategy for my organization and for my customers as well\nCurrently, I am working as Business Development Manager at ACET\nSolutions. Here, we are not only helping enterprises with our OT and\nICS solutions but also helping them secure their digital infrastructure\nthrough our in-depth cybersecurity practices. With deep expertise in\nmature and emerging OT/IT means, we are helping various verticals\nautomate their processes, secure their infrastructure, and enhance\noperational productivity\nMy forte ranging from Lead Generation, Market Research, Business\nDevelopment, International Sales, Key Accounts Management, Sales\nOperations, Sales Strategy, Product Management, New Business\nDevelopment and Customer Satisfaction\nFundamental understanding of OT/ICS Cyber security basics and\nmodern concepts related to;\n-Firewalls, Intrusion detection and prevention, DMZ's, Remote\nAccess Solutions \n-Data leakage prevention\n-Secure Cloud, Data security, Security operations tools,\n\u00a0 Page 1 of 3\u00a0 \u00a0\n-ISA 62443 & Other OT Cybersecurity Standards\nTechnologies: \nIndustrial Automation | Industry 4.0 | Industrial IOT | IT/OT\nIntegration | Enterprise Management System | Data Historian &\ncloud | Cybersecurity | SCADA | Solar | Electrical | Instrumentation |\nRenewable Energy | \nIndustry Verticals:\nOil & Gas | Process | Utilities & Power | Metals | FMCG\nGeographies:\nPakistan | GCC | West Africa | Singapore | USA\nClients: \nFortune 100 | Government | EPCs | OEMs \nFunctional Competencies: \nStrategy Planning & Execution | Product and Solutions Proposals\n| P&L Management | Key Account Management | Negotiations\n| Business Development | Customer Relationship Management\n| Competitive Analysis | Solution & Services Sales Demand\nGeneration | Brand Positioning | Strategic Alliances & Partnerships |\nDigital transformation | Control Systems (PLC,DCS,SCADA) | EPC\nConnect with Yahya:\nWatsapp UAE: +971 50 468 0678\nWatsapp KSA: +966 54 697 8135\nWatsapp PAK: +92 310 814 1420 \nOfficial Email ID: yahya.malik@acetsolutions.com\nExperience\nACET Solutions\nBusiness Development Manager\nJune 2021\u00a0-\u00a0Present\u00a0 (2 years)\nUnited Arab Emirates\n\u00a0 Page 2 of 3\u00a0 \u00a0\n-Looking after Sales and Business Development of Automation, OT\nCybersecurity & Digital Enterprise Technology solutions in Pakistan & Middle\nEast Market\nInternational Society of Automation (ISA)\n2 years 5 months\nPresident Elect\nOctober 2022\u00a0-\u00a0Present\u00a0 (8 months)\nBoard Member (Webinars & Seminars)\nJanuary 2021\u00a0-\u00a0October 2022\u00a0 (1 year 10 months)\nDescon\nBusiness Development Manager\nNovember 2017\u00a0-\u00a0May 2021\u00a0 (3 years 7 months)\nUnited Arab Emirates\nLean Automation\nDesign Application Engineer\nJanuary 2016\u00a0-\u00a0October 2017\u00a0 (1 year 10 months)\nUnited Arab Emirates\nCoca-Cola Beverages Pakistan Limited\nGraduate Management Trainee\nJanuary 2015\u00a0-\u00a0December 2015\u00a0 (1 year)\nPakistan\nEducation\nLahore University of Management Sciences\nArt of Selling Ideas-Advertising 101,\u00a0Print, Outdoor and Digital\nMarketing \u00a0\u00b7\u00a0(March 2021)\nNEBOSH\nNebosh International General Certificate in Occupational Health and\nSafety,\u00a0Occupational Health and Safety \u00a0\u00b7\u00a0(January 2021)\nCOMSATS University\nEngineer\u2019s Degree,\u00a0Electrical and Electronics Engineering \u00a0\u00b7\u00a0(2010)\n\u00a0 Page 3 of 3"
    },
    "details": {
        "name": "Yahya Malik",
        "number": "971504680678",
        "skills": [
            "Automation",
            "Instrumentation",
            "OT Cyber Security",
            "Industrial Automation",
            "Industry 4.0",
            "Industrial IOT",
            "IT/OT Integration",
            "Enterprise Management System",
            "Data Historian & cloud",
            "Cybersecurity",
            "SCADA",
            "Solar",
            "Electrical",
            "Instrumentation",
            "Renewable Energy"
        ],
        "email_id": "yahyamalik1@outlook.com",
        "location": "Dubai, United Arab Emirates",
        "projects": [],
        "education": [
            {
                "end_date": "03-2021",
                "university": "Lahore University of Management Sciences",
                "degree_title": "Art of Selling Ideas-Advertising 101, Print, Outdoor and Digital Marketing"
            },
            {
                "end_date": "01-2021",
                "university": "NEBOSH",
                "degree_title": "Nebosh International General Certificate in Occupational Health and Safety"
            },
            {
                "end_date": "2010",
                "university": "COMSATS University",
                "degree_title": "Engineer\u2019s Degree, Electrical and Electronics Engineering"
            }
        ],
        "achievements": [
            "Organizer - Annual Technical Conference 2017",
            "Organizer - POGEE 2018",
            "Organizer - OT Cybersecurity Implementation Conference by ISA",
            "Organizer - Cybersecurity for Critical Assets MENA",
            "Employee of the Month Award"
        ],
        "publications": [],
        "certifications": [
            {
                "certification_name": "ISA 62443 Cybersecurity Fundamentals Specialist",
                "issuing_organization": "ISA",
                "date_of_issuance": "01-2021"
            },
            {
                "certification_name": "NSE 1,2,3 Network Security Associate",
                "issuing_organization": "Fortinet",
                "date_of_issuance": "01-2021"
            },
            {
                "certification_name": "Nozomi Certified Sales Professional (NNCTSP)",
                "issuing_organization": "Nozomi Networks",
                "date_of_issuance": "01-2021"
            },
            {
                "certification_name": "IELTS General",
                "issuing_organization": "British Council",
                "date_of_issuance": "01-2021"
            },
            {
                "certification_name": "Honeywell Certified Sales Professional on Process Control Systems",
                "issuing_organization": "Honeywell",
                "date_of_issuance": "01-2021"
            }
        ],
        "additional_urls": [
            {
                "url": "linkedin.com/in/engryahyamalik",
                "website_name": "LinkedIn"
            }
        ],
        "executive_summary": "Yahya Malik is a seasoned engineer-turned marketer with over 9 years of diverse experience in B2B sales, negotiation, customer relations management, product management, process automation, and OT cybersecurity. He has worked with industry leaders and is currently a Business Development Manager at ACET Solutions, focusing on automation and cybersecurity solutions. His expertise includes lead generation, market research, and digital transformation, making him a valuable asset in enhancing operational productivity across various sectors.",
        "employment_history": [
            {
                "details": "Looking after Sales and Business Development of Automation, OT Cybersecurity & Digital Enterprise Technology solutions in Pakistan & Middle East Market",
                "end_date": "Present",
                "location": "United Arab Emirates",
                "job_title": "Business Development Manager",
                "start_date": "06-2021",
                "company_name": "ACET Solutions"
            },
            {
                "details": "President Elect and Board Member (Webinars & Seminars)",
                "end_date": "Present",
                "location": "United Arab Emirates",
                "job_title": "President Elect",
                "start_date": "10-2022",
                "company_name": "International Society of Automation (ISA)"
            },
            {
                "details": "Business Development Manager",
                "end_date": "05-2021",
                "location": "United Arab Emirates",
                "job_title": "Business Development Manager",
                "start_date": "11-2017",
                "company_name": "Descon"
            },
            {
                "details": "Design Application Engineer",
                "end_date": "10-2017",
                "location": "United Arab Emirates",
                "job_title": "Design Application Engineer",
                "start_date": "01-2016",
                "company_name": "Lean Automation"
            },
            {
                "details": "Graduate Management Trainee",
                "end_date": "12-2015",
                "location": "Pakistan",
                "job_title": "Graduate Management Trainee",
                "start_date": "01-2015",
                "company_name": "Coca-Cola Beverages Pakistan Limited"
            }
        ]
    }
}