{
    "output": {
        "justification": [
            "Candidate has extensive experience in B2B sales and business development, yet lacks direct SEO expertise.",
            "The candidate shows strong leadership experience through managerial and presidential roles.",
            "No mention of specific skills in SEO strategy development or team management in resume.",
            "University attended is not listed as a preferred institution in the additional info."
        ],
        "scores": {
            "macro_scores": [
                {
                    "criteria": "experience",
                    "score": 6
                }
            ],
            "micro_scores": [
                {
                    "criteria": "seo strategy development",
                    "score": 3
                },
                {
                    "criteria": "team management",
                    "score": 7
                },
                {
                    "criteria": "client engagement",
                    "score": 8
                }
            ],
            "requirements": [
                {
                    "criteria": "Proficiency in Microsoft Office and CRM systems",
                    "meets": true
                },
                {
                    "criteria": "3+ years of experience in SEO and digital marketing",
                    "meets": false
                },
                {
                    "criteria": "Strong analytical and strategic thinking skills",
                    "meets": true
                },
                {
                    "criteria": "Proven track record in sales and client relationship management",
                    "meets": true
                },
                {
                    "criteria": "Master's degree in Business Administration or related field",
                    "meets": false
                }
            ],
            "aggregated_scores": {
                "macro_scores": 6.0,
                "micro_scores": 6.9399999999999995
            }
        },
        "personal_info": {
            "name": "Yahya Malik",
            "email": "yahyamalik1@outlook.com",
            "phone": "+971504680678",
            "current_position": "Business Development Manager",
            "current_company": "ACET Solutions",
            "employment_start_date_current_company": "06-2021",
            "first_company_start_date": "01-2015",
            "urls": [
                {
                    "website_name": "LinkedIn",
                    "url": "www.linkedin.com/in/engryahyamalik"
                }
            ]
        },
        "valid_resume_and_jd": true
    },
    "input": {
        "job_description": "## Job Title: Sales and SEO Management Specialist  \n\n### Location: Lahore, Pakistan  \n\n### Company: Innovate Digital Solutions Inc.  \n\n### Job Summary:  \nJoin Innovate Digital Solutions Inc. as a Sales and SEO Management Specialist. You will be part of a dynamic team responsible for driving client engagement and ensuring optimal performance in digital marketing strategies. Your role will include managing client relationships, improving SEO strategies, and leading your team to achieve sales targets.  \n\n### Key Responsibilities:  \n- Proactively engage with prospective clients to understand their business needs and provide innovative solutions.  \n- Design and execute SEO strategies in alignment with client\u2019s marketing objectives.  \n- Manage and optimize PPC campaigns to maximize ROI and brand visibility.  \n- Develop and maintain strong client relationships through tailored marketing solutions.  \n- Lead a team to achieve and surpass sales targets while providing exceptional customer service.  \n- Analyze market trends and algorithms to tailor SEO strategies accordingly.  \n- Produce reports that track progress and measure success against KPIs.  \n\n### Ideal Candidate Profile:  \nYou are a skilled sales and marketing professional with strong analytical skills suited to identifying and executing SEO opportunities. You excel at client interactions, possessing the ability to transform potential leads into satisfied clients through strategic and well-executed marketing initiatives. Leadership and team management skills will be pivotal to drive sales and motivate your team.  \n\n### Benefits:  \n- Competitive salary package  \n- Health and wellness benefits  \n- Performance bonuses  \n- Opportunities for career advancement  \n\nJoin us to redefine digital engagement and lead market strategies with agility and innovation.",
        "macro_dict": {
            "experience": 100
        },
        "micro_dict": {
            "seo strategy development": 12,
            "team management": 46,
            "client engagement": 42
        },
        "additional_info": "Innovate Digital Solutions Inc. prefers candidates from reputable institutions such as [University of Lahore], [Punjab University]. Remote work options are available subject to roles and responsibilities. We assess skills through a combination of technical tests, interviews, and real-world problem-solving scenarios to gauge practical competency in strategic marketing contexts.",
        "minimum_requirements": [
            "Proficiency in Microsoft Office and CRM systems",
            "3+ years of experience in SEO and digital marketing",
            "Strong analytical and strategic thinking skills",
            "Proven track record in sales and client relationship management",
            "Master's degree in Business Administration or related field"
        ],
        "resume": "\u00a0 \u00a0\nContact\nDubai,United Arab Emirates \nUAE Number: +971504680678\nPAK Number: +923108141420\nKSA Number: +966546978135\nyahyamalik1@outlook.com\nwww.linkedin.com/in/\nengryahyamalik  (LinkedIn)\nTop Skills\nAutomation\nInstrumentation\nOT Cyber Security\nLanguages\nEnglish  (Professional Working)\nCertifications\nISA 62443 Cybersecurity\nFundamentals Specialist\nNSE 1,2,3 Network Security\nAssociate\nNozomi Certified Sales Professional\n(NNCTSP) \nIELTS General \nHoneywell Certified Sales\nProfessional on Process Control\nSystems\nHonors-Awards\nOrganizer - Annual Technical\nConference 2017\nOrganizer - POGEE 2018\nOrganizer-OT Cybersecurity\nImplementation Conference by ISA\nOrganizer-Cybersecurity for Critical\nAssets MENA\nEmployee of the Month AwardYahya M.\nBusiness Development Manager | Sales Leader | Industrial\nAutomation | Account Manager | OT Cybersecurity ISA 62443 CFS\n| Digital Transformation | IT/OT Integration | Closed Multimillion $\nProjects in last 5 years\nDubai, United Arab Emirates\nSummary\nyahyamalik1@outlook.com \nYahya Malik is a Seasoned Engineer-turned Marketer, with 9+\nyears of diverse experience in the field of B2B Sales, Negotiation,\nCustomer Relations Management, Product Management Process\nAutomation & OT Cybersecurity with a keen interest in IIOT.\nWorked with Industry leaders such as Nozomi Networks, Palo Alto,\nFortinet, ABB, Rockwell Automation, Yokogawa, Honeywell, General\nMonitors, Trend Micro, TXOne & Schneider. Creating win to win\nstrategy for my organization and for my customers as well\nCurrently, I am working as Business Development Manager at ACET\nSolutions. Here, we are not only helping enterprises with our OT and\nICS solutions but also helping them secure their digital infrastructure\nthrough our in-depth cybersecurity practices. With deep expertise in\nmature and emerging OT/IT means, we are helping various verticals\nautomate their processes, secure their infrastructure, and enhance\noperational productivity\nMy forte ranging from Lead Generation, Market Research, Business\nDevelopment, International Sales, Key Accounts Management, Sales\nOperations, Sales Strategy, Product Management, New Business\nDevelopment and Customer Satisfaction\nFundamental understanding of OT/ICS Cyber security basics and\nmodern concepts related to;\n-Firewalls, Intrusion detection and prevention, DMZ's, Remote\nAccess Solutions \n-Data leakage prevention\n-Secure Cloud, Data security, Security operations tools,\n\u00a0 Page 1 of 3\u00a0 \u00a0\n-ISA 62443 & Other OT Cybersecurity Standards\nTechnologies: \nIndustrial Automation | Industry 4.0 | Industrial IOT | IT/OT\nIntegration | Enterprise Management System | Data Historian &\ncloud | Cybersecurity | SCADA | Solar | Electrical | Instrumentation |\nRenewable Energy | \nIndustry Verticals:\nOil & Gas | Process | Utilities & Power | Metals | FMCG\nGeographies:\nPakistan | GCC | West Africa | Singapore | USA\nClients: \nFortune 100 | Government | EPCs | OEMs \nFunctional Competencies: \nStrategy Planning & Execution | Product and Solutions Proposals\n| P&L Management | Key Account Management | Negotiations\n| Business Development | Customer Relationship Management\n| Competitive Analysis | Solution & Services Sales Demand\nGeneration | Brand Positioning | Strategic Alliances & Partnerships |\nDigital transformation | Control Systems (PLC,DCS,SCADA) | EPC\nConnect with Yahya:\nWatsapp UAE: +971 50 468 0678\nWatsapp KSA: +966 54 697 8135\nWatsapp PAK: +92 310 814 1420 \nOfficial Email ID: yahya.malik@acetsolutions.com\nExperience\nACET Solutions\nBusiness Development Manager\nJune 2021\u00a0-\u00a0Present\u00a0 (2 years)\nUnited Arab Emirates\n\u00a0 Page 2 of 3\u00a0 \u00a0\n-Looking after Sales and Business Development of Automation, OT\nCybersecurity & Digital Enterprise Technology solutions in Pakistan & Middle\nEast Market\nInternational Society of Automation (ISA)\n2 years 5 months\nPresident Elect\nOctober 2022\u00a0-\u00a0Present\u00a0 (8 months)\nBoard Member (Webinars & Seminars)\nJanuary 2021\u00a0-\u00a0October 2022\u00a0 (1 year 10 months)\nDescon\nBusiness Development Manager\nNovember 2017\u00a0-\u00a0May 2021\u00a0 (3 years 7 months)\nUnited Arab Emirates\nLean Automation\nDesign Application Engineer\nJanuary 2016\u00a0-\u00a0October 2017\u00a0 (1 year 10 months)\nUnited Arab Emirates\nCoca-Cola Beverages Pakistan Limited\nGraduate Management Trainee\nJanuary 2015\u00a0-\u00a0December 2015\u00a0 (1 year)\nPakistan\nEducation\nLahore University of Management Sciences\nArt of Selling Ideas-Advertising 101,\u00a0Print, Outdoor and Digital\nMarketing \u00a0\u00b7\u00a0(March 2021)\nNEBOSH\nNebosh International General Certificate in Occupational Health and\nSafety,\u00a0Occupational Health and Safety \u00a0\u00b7\u00a0(January 2021)\nCOMSATS University\nEngineer\u2019s Degree,\u00a0Electrical and Electronics Engineering \u00a0\u00b7\u00a0(2010)\n\u00a0 Page 3 of 3"
    },
    "details": {
        "name": "Yahya Malik",
        "number": "971504680678",
        "skills": [
            "Automation",
            "Instrumentation",
            "OT Cyber Security",
            "Industrial Automation",
            "Industry 4.0",
            "Industrial IOT",
            "IT/OT Integration",
            "Enterprise Management System",
            "Data Historian & cloud",
            "Cybersecurity",
            "SCADA",
            "Solar",
            "Electrical",
            "Instrumentation",
            "Renewable Energy"
        ],
        "email_id": "yahyamalik1@outlook.com",
        "location": "Dubai, United Arab Emirates",
        "projects": [],
        "education": [
            {
                "end_date": "03-2021",
                "university": "Lahore University of Management Sciences",
                "degree_title": "Art of Selling Ideas-Advertising 101, Print, Outdoor and Digital Marketing"
            },
            {
                "end_date": "01-2021",
                "university": "NEBOSH",
                "degree_title": "Nebosh International General Certificate in Occupational Health and Safety"
            },
            {
                "end_date": "2010",
                "university": "COMSATS University",
                "degree_title": "Engineer\u2019s Degree, Electrical and Electronics Engineering"
            }
        ],
        "achievements": [
            "Organizer - Annual Technical Conference 2017",
            "Organizer - POGEE 2018",
            "Organizer - OT Cybersecurity Implementation Conference by ISA",
            "Organizer - Cybersecurity for Critical Assets MENA",
            "Employee of the Month Award"
        ],
        "publications": [],
        "certifications": [
            {
                "certification_name": "ISA 62443 Cybersecurity Fundamentals Specialist",
                "issuing_organization": "ISA",
                "date_of_issuance": "01-2021"
            },
            {
                "certification_name": "NSE 1,2,3 Network Security Associate",
                "issuing_organization": "Fortinet",
                "date_of_issuance": "01-2021"
            },
            {
                "certification_name": "Nozomi Certified Sales Professional (NNCTSP)",
                "issuing_organization": "Nozomi Networks",
                "date_of_issuance": "01-2021"
            },
            {
                "certification_name": "IELTS General",
                "issuing_organization": "British Council",
                "date_of_issuance": "01-2021"
            },
            {
                "certification_name": "Honeywell Certified Sales Professional on Process Control Systems",
                "issuing_organization": "Honeywell",
                "date_of_issuance": "01-2021"
            }
        ],
        "additional_urls": [
            {
                "url": "linkedin.com/in/engryahyamalik",
                "website_name": "LinkedIn"
            }
        ],
        "executive_summary": "Yahya Malik is a seasoned engineer-turned marketer with over 9 years of diverse experience in B2B sales, negotiation, customer relations management, product management, process automation, and OT cybersecurity. He has worked with industry leaders and is currently a Business Development Manager at ACET Solutions, focusing on automation and cybersecurity solutions. His expertise includes lead generation, market research, and digital transformation, making him a valuable asset in enhancing operational productivity across various sectors.",
        "employment_history": [
            {
                "details": "Looking after Sales and Business Development of Automation, OT Cybersecurity & Digital Enterprise Technology solutions in Pakistan & Middle East Market",
                "end_date": "Present",
                "location": "United Arab Emirates",
                "job_title": "Business Development Manager",
                "start_date": "06-2021",
                "company_name": "ACET Solutions"
            },
            {
                "details": "President Elect and Board Member (Webinars & Seminars)",
                "end_date": "Present",
                "location": "United Arab Emirates",
                "job_title": "President Elect",
                "start_date": "10-2022",
                "company_name": "International Society of Automation (ISA)"
            },
            {
                "details": "Business Development Manager",
                "end_date": "05-2021",
                "location": "United Arab Emirates",
                "job_title": "Business Development Manager",
                "start_date": "11-2017",
                "company_name": "Descon"
            },
            {
                "details": "Design Application Engineer",
                "end_date": "10-2017",
                "location": "United Arab Emirates",
                "job_title": "Design Application Engineer",
                "start_date": "01-2016",
                "company_name": "Lean Automation"
            },
            {
                "details": "Graduate Management Trainee",
                "end_date": "12-2015",
                "location": "Pakistan",
                "job_title": "Graduate Management Trainee",
                "start_date": "01-2015",
                "company_name": "Coca-Cola Beverages Pakistan Limited"
            }
        ]
    }
}