{
    "output": {
        "justification": [
            "Samha meets the requirement for handling multiple projects thanks to simultaneous roles held at TxLabz.",
            "No mention of strong proficiency in MS Office Suite, but demonstrated in roles requiring multiple software tools.",
            "The education is not from a university deemed top-tier by the company's standards as per additional info.",
            "Relevant business development and project management experience, yet unclear if economic analysis skills were used."
        ],
        "scores": {
            "macro_scores": [
                {
                    "criteria": "experience",
                    "score": 6
                }
            ],
            "micro_scores": [
                {
                    "criteria": "ms word",
                    "score": 5
                }
            ],
            "requirements": [
                {
                    "criteria": "Excellent communication skills",
                    "meets": true
                },
                {
                    "criteria": "Ability to manage multiple projects simultaneously",
                    "meets": true
                },
                {
                    "criteria": "Proficiency in MS Office Suite and data analysis tools",
                    "meets": false
                }
            ],
            "aggregated_scores": {
                "macro_scores": 6.0,
                "micro_scores": 5.0
            }
        },
        "personal_info": {
            "name": "SAMHA AHMED",
            "email": "samhaahmed39@gmail.com",
            "phone": "+923324817353",
            "current_position": "BUSINESS DEVELOPMENT EXECUTIVE",
            "current_company": "Rolustech",
            "employment_start_date_current_company": "09-2021",
            "first_company_start_date": "05-2021",
            "urls": []
        },
        "valid_resume_and_jd": true
    },
    "input": {
        "job_description": "### Business Development Executive\n\n**Company:** Innovate Dynamics Ltd.\n\n**Location:** Hyderabad, India\n\n**Role Overview:**\nJoin Innovate Dynamics Ltd. as a Business Development Executive, where you will play a pivotal role in driving business growth by generating leads and managing key client accounts. Leverage your expertise in economic analysis and marketing strategies to enhance our market presence and build strong client relationships.\n\n**Responsibilities:**\n- Develop and execute comprehensive business development plans to achieve company objectives.\n- Identify and engage prospective clients across diverse niches, including software development and outsourcing.\n- Manage and grow relationships with key accounts to drive long-term success.\n- Utilize digital marketing strategies to boost client engagement and retention.\n- Collaborate with cross-functional teams to develop tailored client solutions.\n- Utilize LinkedIn Sales Navigator to identify and approach new business leads.\n\n**Qualifications:**\n- Bachelor\u2019s degree in Business Administration, Economics, or related field.\n- 3-5 years of experience in business development or related fields.\n- Strong proficiency with MS Office Suite and data analysis tools like Stata.\n- Excellent verbal and written communication skills.\n- Ability to multitask and manage multiple projects simultaneously.",
        "macro_dict": {
            "experience": 100
        },
        "micro_dict": {
            "ms word": 100
        },
        "additional_info": "Innovate Dynamics Ltd. prioritizes applicants from top-tier universities such as [University X] and [University Y]. Relocation assistance is available for candidates willing to move to Hyderabad. Technical skills are assessed through standardized tests and a series of interviews. Our company encourages diversity and inclusivity in the hiring process.",
        "minimum_requirements": [
            "Excellent communication skills",
            "Ability to manage multiple projects simultaneously",
            "Proficiency in MS Office Suite and data analysis tools"
        ],
        "resume": "SAMHA\nAHMED\nAddress: Lahore, Pakistan \u2013 Phone: +923324817353\nEmail:\nsamhaahmed39@gmail.com\nOBJECTIVE\nTo work in a challenging environment where I can better utilize my skills and enhance my experience in\nthe domain of sales and business development.\nWORK EXPERIENCE\nBUSINESS DEVELOPMENT EXECUTIVE\nRolustech\n(September 2021 \u2013 Present)\nBUSINESS DEVELOPMENT EXECUTIVE\nTxLabz\n(May 2021 \u2013 September 2021)\nASSOCIATE PROJECT MANAGER\nTxLabz\n(June 2021 \u2013 September 2021)\nEDUCATION\nBS INFORMATION TECHNOLOGY\n(2017\u20132021)\nPunjab University College of Information Technology, Lahore\n(OOP, DSA, DB, Web, Android, SQA)\nF.SC PRE-ENGINEERING\n(2015 \u2013 2017)\nPunjab College of Science, Lahore\n(Chemistry, Physics, Mathematics)\nPercentage: 80%\nMATRICULATION\n(2013 \u2013 2015)\nWapda Girls High School, Lahore\n(Computer, Mathematics, Physics, Chemistry)\nPercentage: 93%PERSONAL SKILLS\n\u25cf\nStrong interpersonal skills\n\u25cf\nE\ufb00ective Listening\n\u25cf\nAbility to negotiate\n\u25cf\nAbility to Multitask\n\u25cf\nAttention to details\n\u25cf\nProfessional behavior\n\u25cf\nTime and resource \nmanagement\n\u25cf\nE\ufb00ective Decision making\nORGANIZATIONAL/ MANAGERIAL SKILLS\n\u25cf\nBusiness intelligence and marketing skills\n\u25cf\nHands-on experience in Upwork bidding and utilization of freelancing platforms for lead\ngeneration\n\u25cf\nKnowledge of all the stages of a sales cycle\n\u25cf\nExperience with CRM systems\n\u25cf\nStrong knowledge of lead generation using email campaigns and popular marketing tools\n\u25cf\nAbility to analyze market trends and suggest new ideas/strategies for improving sales\n\u25cf\nAbility to interact and e\ufb00ectively communicate with people from diverse backgrounds\n\u25cf\nStrong persuasion skills that help in maximizing customer satisfaction\n\u25cf\nGood at creating and goal setting and meeting goals, decision making, managing\nappointments, team management, and strategic thinking\nSEMESTER PROJECTS\nCAMPUS MANAGEMENT SYSTEM\nSubject: Programming Fundamentals, It was developed in C++.\nNGO DATABASE SYSTEM\nSubject: Database System. It was developed in ORACLE using PHP, HTML, and CSS.\nLUDO GAME\nSubject: OOAD (Object-Oriented Analysis and Design). It was developed in JAVA.\nONLINE ART GALLERY\nSubject: Web Development. It was developed using HTML, CSS, Bootstrap, JavaScript, AJAX,\nJQUERY, and JSON.FINAL YEAR PROJECT\nPU E-BUS TRACKING APPLICATION\nIt is an application that will provide Real-time Bus locations to the students. It is an\nAndroid-based project. The application has two modules; one is for drivers, the other for\nstudents. When a driver opens the app, his real-time location in Firebase is saved. When\na student opens the app, nearby buses within a 3km of radius are shown to the student.\nWe have also developed a Website for admins who can remove or add buses.\nTools for Android: Java, XML, Gradle, and Firebase Database.\nTools for Web: HTML5, CSS3, JavaScript, jQuery, React, Python and MySQL."
    },
    "details": {
        "name": "Samha Ahmed",
        "number": "923324817353",
        "skills": [
            "C++",
            "ORACLE",
            "PHP",
            "HTML",
            "CSS",
            "JAVA",
            "HTML5",
            "CSS3",
            "JavaScript",
            "jQuery",
            "React",
            "Python",
            "MySQL",
            "XML",
            "Gradle",
            "Firebase Database"
        ],
        "email_id": "samhaahmed39@gmail.com",
        "location": "Lahore, Pakistan",
        "projects": [
            {
                "title": "Campus Management System",
                "description": "Developed in C++."
            },
            {
                "title": "NGO Database System",
                "description": "Developed in ORACLE using PHP, HTML, and CSS."
            },
            {
                "title": "Ludo Game",
                "description": "Developed in JAVA."
            },
            {
                "title": "Online Art Gallery",
                "description": "Developed using HTML, CSS, Bootstrap, JavaScript, AJAX, jQuery, and JSON."
            },
            {
                "title": "PU E-Bus Tracking Application",
                "description": "Android-based application providing real-time bus locations."
            }
        ],
        "education": [
            {
                "end_date": "06-2021",
                "university": "Punjab University College of Information Technology, Lahore",
                "degree_title": "BS Information Technology"
            },
            {
                "end_date": "05-2017",
                "university": "Punjab College of Science, Lahore",
                "degree_title": "F.Sc Pre-Engineering"
            },
            {
                "end_date": "05-2015",
                "university": "Wapda Girls High School, Lahore",
                "degree_title": "Matriculation"
            }
        ],
        "achievements": [],
        "publications": [],
        "certifications": [],
        "additional_urls": [],
        "executive_summary": "Samha Ahmed is a skilled business development executive with a strong background in information technology. She has experience in various programming languages and technologies, demonstrating her technical proficiency in software development and project management.",
        "employment_history": [
            {
                "details": "Business Development Executive at Rolustech.",
                "end_date": "Present",
                "location": "Lahore, Pakistan",
                "job_title": "Business Development Executive",
                "start_date": "09-2021",
                "company_name": "Rolustech"
            },
            {
                "details": "Business Development Executive at TxLabz.",
                "end_date": "09-2021",
                "location": "Lahore, Pakistan",
                "job_title": "Business Development Executive",
                "start_date": "05-2021",
                "company_name": "TxLabz"
            },
            {
                "details": "Associate Project Manager at TxLabz.",
                "end_date": "09-2021",
                "location": "Lahore, Pakistan",
                "job_title": "Associate Project Manager",
                "start_date": "06-2021",
                "company_name": "TxLabz"
            }
        ]
    }
}