{
    "output": {
        "justification": [
            "Faique Ali Raza has multiple years of experience in Business Development and related fields, meeting the job's experiential requirements.",
            "However, his educational background in Computer Science is not directly aligned with the specified requirements for a degree in Business Administration, Economics, or related fields.",
            "He demonstrates strong proficiency in relevant business development skills like lead generation and use of LinkedIn Sales Navigator, but his resume lacks specific evidence of proficiency in MS Office Suite and data analysis tools like Stata.",
            "While several experiences and achievements indicate good communication skills, the lack of direct evidence like formal certification in communication impacts the score."
        ],
        "scores": {
            "macro_scores": [
                {
                    "criteria": "leadership",
                    "score": 7
                },
                {
                    "criteria": "experience",
                    "score": 7
                },
                {
                    "criteria": "communication skills",
                    "score": 6
                }
            ],
            "micro_scores": [
                {
                    "criteria": "ms word",
                    "score": 5
                }
            ],
            "requirements": [
                {
                    "criteria": "Bachelor's degree in Business Administration, Economics, or related field",
                    "meets": false
                },
                {
                    "criteria": "Excellent communication skills",
                    "meets": true
                }
            ],
            "aggregated_scores": {
                "macro_scores": 6.87,
                "micro_scores": 5.0
            }
        },
        "personal_info": {
            "name": "Faique Ali Raza",
            "email": "faiquealiraza@gmail.com",
            "phone": "03143631941",
            "current_position": "Business Development Manager",
            "current_company": "Crewlogicx Tech",
            "employment_start_date_current_company": "04-2022",
            "first_company_start_date": "08-2020",
            "urls": [
                {
                    "website_name": "LinkedIn",
                    "url": "linkedin.com/in/FaiqueAliRaza"
                }
            ]
        },
        "valid_resume_and_jd": true
    },
    "input": {
        "job_description": "### Business Development Executive\n\n**Company:** Innovate Dynamics Ltd.\n\n**Location:** Hyderabad, India\n\n**Role Overview:**\nJoin Innovate Dynamics Ltd. as a Business Development Executive, where you will play a pivotal role in driving business growth by generating leads and managing key client accounts. Leverage your expertise in economic analysis and marketing strategies to enhance our market presence and build strong client relationships.\n\n**Responsibilities:**\n- Develop and execute comprehensive business development plans to achieve company objectives.\n- Identify and engage prospective clients across diverse niches, including software development and outsourcing.\n- Manage and grow relationships with key accounts to drive long-term success.\n- Utilize digital marketing strategies to boost client engagement and retention.\n- Collaborate with cross-functional teams to develop tailored client solutions.\n- Utilize LinkedIn Sales Navigator to identify and approach new business leads.\n\n**Qualifications:**\n- Bachelor\u2019s degree in Business Administration, Economics, or related field.\n- 3-5 years of experience in business development or related fields.\n- Strong proficiency with MS Office Suite and data analysis tools like Stata.\n- Excellent verbal and written communication skills.\n- Ability to multitask and manage multiple projects simultaneously.",
        "macro_dict": {
            "leadership": 30,
            "experience": 57,
            "communication skills": 13
        },
        "micro_dict": {
            "ms word": 100
        },
        "additional_info": "Innovate Dynamics Ltd. prioritizes applicants from top-tier universities such as [University X] and [University Y]. Relocation assistance is available for candidates willing to move to Hyderabad. Technical skills are assessed through standardized tests and a series of interviews. Our company encourages diversity and inclusivity in the hiring process.",
        "minimum_requirements": [
            "Bachelor's degree in Business Administration, Economics, or related field",
            "Excellent communication skills"
        ],
        "resume": " \nFaique Ali Raza House # 392, K Block, Model Town, Lahore, Pakistan 03143631941 linkedin.com/in/FaiqueAliRaza faiquealiraza@gmail.com Profile \u2022 An individual who is focused, honest, team-oriented, deliberate, determined, and most importantly, who makes use of his grey matter. \u2022 Multiple years of experience in Business Development, Sales generation, and Marketing fields. \u2022 Top Rated freelancer on Upwork. \u2022 Hands-on experience in Lead Generation, Email Marketing, Tele-sales, Sales Navigator, Salesforce, Documentation, and CRM. \u2022 1 Year of Experience in Communication and Tele-sales Marketing. \u2022 9+ years of experience in the field of Music and Event Management. Education Work Experience \u2022 Matric | Science | Civil Aviation Authority High School Lahore \u2022 Intermediate | Pre Eng. | Government College Gulberg Lahore \u2022 Bachelor in Computer Science | The University of Lahore  Skills Awards, Achievements and Certifications Data Scraping | Data Extraction | Leads | Emails Upwork | Fiverr | Freelancer | Guru | TopTal  Musician | Production | Live | Studio Recordings  \u2022 Course of Film and Documentary | Hunerkada College of Visual & Performing Arts | Lahore | 2020  \n Production Design for Film and Screen | Australian Film Television and Radio School | 2020 \n National Financial Literacy Program for Youth | National Institute of Banking and Finance (NIBAF)-Pakistan | 2020 \n Certification in Critical Thinking - Master Decision Making & Problem Solving. \n Won many Music Battles across Pakistan. \n Having many certifications in different Activities and Courses.  \u2022 Content Marketing and Advertising | Punjab University | E-Rozgaar | Lahore | 2020 \nSRS | GDD | WBD | Milestones | Timelines \u2022 Business Development Manager | Crewlogicx Tech | Origami Studios | April 2022 \u2013 Cont. \u2022 Business Development & Digital Project Manager | FIRTLE Tech | Part Time | June 2019 \u2013 Cont. \u2022 Business Development Executive | Argon Tech | Lahore | May 2021 - April 2022. \u2022 Business Development Executive | Kodex Technologies | Dec 2020 \u2013 May 2021. \u2022 Business Development Executive | GrowHawk | Aug \u2013 Dec 2020. \u2022 Business Development Executive | Bizzclan | Lahore | May \u2013 Aug 2020. \u2022 Telemarketing Agent | Nixxe Solution | 2019. Business Developer | LinkedIn Specialist | Leads/Sales Generator | Top Rated Upwork Freelancer "
    },
    "details": {
        "name": "Faique Ali Raza",
        "number": "03143631941",
        "skills": [
            "Data Scraping",
            "Data Extraction",
            "Leads",
            "Emails",
            "Salesforce",
            "Documentation",
            "CRM"
        ],
        "email_id": "faiquealiraza@gmail.com",
        "location": "Lahore, Pakistan",
        "projects": [],
        "education": [
            {
                "end_date": "06-2020",
                "university": "Civil Aviation Authority High School Lahore",
                "degree_title": "Matric | Science"
            },
            {
                "end_date": "06-2020",
                "university": "Government College Gulberg Lahore",
                "degree_title": "Intermediate | Pre Eng."
            },
            {
                "end_date": "06-2020",
                "university": "The University of Lahore",
                "degree_title": "Bachelor in Computer Science"
            }
        ],
        "achievements": [
            "Top Rated freelancer on Upwork",
            "Won many Music Battles across Pakistan"
        ],
        "publications": [],
        "certifications": [
            {
                "certification_name": "Course of Film and Documentary",
                "issuing_organization": "Hunerkada College of Visual & Performing Arts",
                "date_of_issuance": "06-2020"
            },
            {
                "certification_name": "Production Design for Film and Screen",
                "issuing_organization": "Australian Film Television and Radio School",
                "date_of_issuance": "06-2020"
            },
            {
                "certification_name": "National Financial Literacy Program for Youth",
                "issuing_organization": "National Institute of Banking and Finance (NIBAF)-Pakistan",
                "date_of_issuance": "06-2020"
            },
            {
                "certification_name": "Content Marketing and Advertising",
                "issuing_organization": "Punjab University | E-Rozgaar",
                "date_of_issuance": "06-2020"
            }
        ],
        "additional_urls": [
            {
                "url": "linkedin.com/in/FaiqueAliRaza",
                "website_name": "LinkedIn"
            }
        ],
        "executive_summary": "Faique Ali Raza is a dedicated professional with extensive experience in business development, sales generation, and marketing. He has a strong technical background in data scraping, lead generation, and CRM systems, complemented by a solid educational foundation in computer science. Faique is recognized as a top-rated freelancer on Upwork and has achieved notable success in music battles across Pakistan.",
        "employment_history": [
            {
                "details": "Business Development Manager responsible for driving sales and managing client relationships.",
                "end_date": "Present",
                "location": "Lahore",
                "job_title": "Business Development Manager",
                "start_date": "04-2022",
                "company_name": "Crewlogicx Tech"
            },
            {
                "details": "Part-time Business Development & Digital Project Manager overseeing project execution and client engagement.",
                "end_date": "Present",
                "location": "Lahore",
                "job_title": "Business Development & Digital Project Manager",
                "start_date": "06-2019",
                "company_name": "FIRTLE Tech"
            },
            {
                "details": "Business Development Executive focused on generating leads and closing sales.",
                "end_date": "04-2022",
                "location": "Lahore",
                "job_title": "Business Development Executive",
                "start_date": "05-2021",
                "company_name": "Argon Tech"
            },
            {
                "details": "Business Development Executive responsible for client acquisition and relationship management.",
                "end_date": "05-2021",
                "location": "Lahore",
                "job_title": "Business Development Executive",
                "start_date": "12-2020",
                "company_name": "Kodex Technologies"
            },
            {
                "details": "Business Development Executive tasked with lead generation and sales strategies.",
                "end_date": "12-2020",
                "location": "Lahore",
                "job_title": "Business Development Executive",
                "start_date": "08-2020",
                "company_name": "GrowHawk"
            },
            {
                "details": "Telemarketing Agent engaged in direct sales and customer outreach.",
                "end_date": "12-2019",
                "location": "Lahore",
                "job_title": "Telemarketing Agent",
                "start_date": "01-2019",
                "company_name": "Nixxe Solution"
            }
        ]
    }
}