{
    "output": {
        "justification": [
            "Strong leadership demonstrated through managing a team in Data Analytics.",
            "Relevant experience present in digital marketing and project management roles.",
            "Lack of explicit experience in programming with C++, HTML, and CSS.",
            "Proficient in digital marketing tools but absence of mentioned BI tools usage."
        ],
        "scores": {
            "macro_scores": [
                {
                    "criteria": "leadership",
                    "score": 7
                },
                {
                    "criteria": "experience",
                    "score": 6
                },
                {
                    "criteria": "innovation and adaptability",
                    "score": 7
                }
            ],
            "micro_scores": [
                {
                    "criteria": "c++, html, css",
                    "score": 2
                },
                {
                    "criteria": "business intelligence tools (power bi, sql, tableau)",
                    "score": 3
                },
                {
                    "criteria": "crm and data management",
                    "score": 6
                },
                {
                    "criteria": "digital marketing skills",
                    "score": 8
                }
            ],
            "requirements": [
                {
                    "criteria": "Bachelor's degree in Computer Science, Business, or a related field",
                    "meets": true
                }
            ],
            "aggregated_scores": {
                "macro_scores": 6.74,
                "micro_scores": 6.34
            }
        },
        "personal_info": {
            "name": "SAAD BIN HASSAN",
            "email": "saadbinhassan000@gmail.com",
            "phone": "923133162249",
            "current_position": "Business Development Executive",
            "current_company": "ProntoDigital, LLC",
            "employment_start_date_current_company": "06-2021",
            "first_company_start_date": "06-2018",
            "urls": [
                {
                    "website_name": "LinkedIn",
                    "url": "https://www.linkedin.com/in/saad-bin-hassan-096118183/"
                }
            ]
        },
        "valid_resume_and_jd": true
    },
    "input": {
        "job_description": "## Lead Generation and Business Intelligence Specialist\n\nJoin **Innovate Connections Inc.** as a Lead Generation and Business Intelligence Specialist. You will play a pivotal role in driving business growth by spearheading lead generation initiatives and providing strategic insights through data analytics. We are looking for a highly skilled professional with a strong background in lead generation, data management, and business intelligence.\n\n### Key Responsibilities:\n- Develop and execute lead generation strategies using digital marketing techniques, cold calling, and data scraping tools.\n- Collaborate with cross-functional teams to optimize customer acquisition strategies.\n- Utilize CRM systems to manage and analyze client data for lead qualification.\n- Create and manage detailed project schedules and work plans, utilizing best practices and standards for project execution.\n- Develop financial models and business growth strategies based on data insights.\n- Utilize tools such as Power BI, SQL, and Tableau for developing comprehensive data reports and dashboards.\n\n### Desired Skills and Experience:\n- Strong programming skills in C++, HTML, and CSS.\n- Proficiency in digital marketing, email marketing, and social media platforms.\n- Experience in managing large data sets and using BI tools (Power BI, Excel, Tableau).\n- Excellent communication skills and ability to develop strong client relationships.\n- Ability to work independently and manage multiple projects simultaneously.\n\n### Why Innovate Connections Inc.?\n- We innovate at the forefront of technology and enable our team members to grow alongside the company.\n- We value data-driven decision-making and empower our teams with the right tools to succeed.\n- Offering a supportive work environment and opportunities for career advancement.\n\n### How to Apply:\nSubmit your resume and cover letter detailing your relevant experience and why you are interested in joining Innovate Connections Inc.",
        "macro_dict": {
            "leadership": 42,
            "experience": 26,
            "innovation and adaptability": 32
        },
        "micro_dict": {
            "c++, html, css": 3,
            "business intelligence tools (power bi, sql, tableau)": 28,
            "crm and data management": 4,
            "digital marketing skills": 65
        },
        "additional_info": "Innovate Connections Inc. prefers candidates from recognized universities such as the University of Management & Technology and Lahore School of Economics. We encourage a remote working environment but require physical presence for team-building and strategic sessions twice a quarter. Relocation assistance is available for exceptional candidates. Our comprehensive assessment includes a technical test followed by structured interviews to evaluate both technical and soft skills comprehensively.",
        "minimum_requirements": [
            "Bachelor's degree in Computer Science, Business, or a related field"
        ],
        "resume": "  SAAD BIN HASSAN  \nHometown: Lahore  \nCell: 923133162249  | saadbinhassan000@gmail.com  \nDate of Birth: 0 7/04/1998  \nLinkedin Profile: https://www.linkedin.com/in/saad -bin-hassan -096118183/  \nEDUCATION & QUALIFICATIONS  \nMasters of Business Administration  May 2022 \nLahore School of Economics  \nBachelors in Business Administration  (Honors)   June  2021  \nMajor (Marketing) Minor (Media Studies)  \nLahore School of Economics           \nPROFESSIONAL EXPERIENCE         \nProntoDigital, LLC                                                                                               June  2021 \u2013 February 2022  \nBusiness Development Executive  \n\uf0b7 Responsible for finding and retaining new clients, Handling Upwork profiles.  \n\uf0b7 Maintained relationships with clients by providing them information and guidance.  \n\uf0b7 Generated weekly sales reports and provided useful insights.  \nProntoDigital, LLC                                                                        March  2022 \u2013 May 2022  \nJunior Project Associate  \n\uf0b7 Managed and build a Data Analytics team.  \n\uf0b7 Managed to achieve the target of $20,000 in 3 months.  \nBank of Punjab                       June-August  2018 \nOperations Intern, Operations  \n\uf0b7 Responsible to deal with branch daily operations and Opening of new accounts.  \nDetechgear  \nMarketing Executive                                                                                                                                                     July- Dec 2020  \n\uf0b7 Managed all Digital Marketing  of the business.  \n\uf0b7 Achieved sales of 500,000 in 5 months.  \nPROJECTS  \nStrategic Management : Strategic decision making and analyzing a company\u2019s performance by looking at different factors. \nUsing tools like IFE, EFE, CPM, QSPM , etc.  \nAdvertising:  Product adaption of Clear Shampoo according to Pakistani Market. Devised the entire advertising plan \nincorporating all the strategies and storyboard . \nSales Force Management : Analyzed the Sales channel of FFC and developed the strategy to strengthen the Salesforce  \nchannel.  \nMarketing Research: Conducted qualitative and quantita tive research on Nokia Pakistan.  \nADDITIONAL EXPERIENCE  \nTeacher Assistant , Lahore School of Economics                                                                                                2021 \u2013 2022 \nMarketing Intern , Signature Lifestyle.  \n\uf0b7 Managed all Digital Marketing campaigns and marketing strategies.              March -July 2022   \nHONORS & AWARDS  \n\uf0b7 Winner of LSE Business Fiesta 2021  \n\uf0b7 25% Scholarship in Lahore  School of Economics  \nSKILLS & INTERESTS  \n\uf0b7 Competent user of M icrosoft Office , Vegas Pro, SPSS, Smar t PLS , Shopify, and Ecommerce \nManagement.  \n\uf0b7     Digital Marketing, Upwork , Click Up, Slack, FB Ads, Google AdWords , Google Analytics, Canva.  \n       \uf0b7     Strategic Planning, Leadership, Comfortable in Team work.  \n"
    },
    "details": {
        "name": "Saad Bin Hassan",
        "number": "923133162249",
        "skills": [
            "Microsoft Office",
            "Vegas Pro",
            "SPSS",
            "Smart PLS",
            "Shopify",
            "Ecommerce Management",
            "Digital Marketing",
            "Upwork",
            "Click Up",
            "Slack",
            "FB Ads",
            "Google AdWords",
            "Google Analytics",
            "Canva"
        ],
        "email_id": "saadbinhassan000@gmail.com",
        "location": "Lahore",
        "projects": [
            {
                "title": "Strategic Management",
                "description": "Strategic decision making and analyzing a company\u2019s performance by looking at different factors."
            },
            {
                "title": "Advertising",
                "description": "Product adaption of Clear Shampoo according to Pakistani Market."
            },
            {
                "title": "Sales Force Management",
                "description": "Analyzed the Sales channel of FFC and developed the strategy to strengthen the Salesforce channel."
            },
            {
                "title": "Marketing Research",
                "description": "Conducted qualitative and quantitative research on Nokia Pakistan."
            }
        ],
        "education": [
            {
                "end_date": "05-2022",
                "university": "Lahore School of Economics",
                "degree_title": "Masters of Business Administration"
            },
            {
                "end_date": "06-2021",
                "university": "Lahore School of Economics",
                "degree_title": "Bachelors in Business Administration (Honors)"
            }
        ],
        "achievements": [
            "Winner of LSE Business Fiesta 2021",
            "25% Scholarship in Lahore School of Economics"
        ],
        "publications": [],
        "certifications": [],
        "additional_urls": [
            {
                "url": "linkedin.com/in/saad-bin-hassan-096118183/",
                "website_name": "LinkedIn"
            }
        ],
        "executive_summary": "Saad Bin Hassan is a skilled professional with a strong background in business development and digital marketing, holding an MBA and a Bachelor's in Business Administration. He has demonstrated success in managing teams and achieving sales targets, showcasing his technical proficiency in various software and marketing tools.",
        "employment_history": [
            {
                "details": "Responsible for finding and retaining new clients, Handling Upwork profiles. Maintained relationships with clients by providing them information and guidance. Generated weekly sales reports and provided useful insights.",
                "end_date": "02-2022",
                "location": "ProntoDigital, LLC",
                "job_title": "Business Development Executive",
                "start_date": "06-2021",
                "company_name": "ProntoDigital, LLC"
            },
            {
                "details": "Managed and build a Data Analytics team. Managed to achieve the target of $20,000 in 3 months.",
                "end_date": "05-2022",
                "location": "ProntoDigital, LLC",
                "job_title": "Junior Project Associate",
                "start_date": "03-2022",
                "company_name": "ProntoDigital, LLC"
            },
            {
                "details": "Responsible to deal with branch daily operations and Opening of new accounts.",
                "end_date": "08-2018",
                "location": "Bank of Punjab",
                "job_title": "Operations Intern, Operations",
                "start_date": "06-2018",
                "company_name": "Bank of Punjab"
            },
            {
                "details": "Managed all Digital Marketing of the business. Achieved sales of 500,000 in 5 months.",
                "end_date": "12-2020",
                "location": "Detechgear",
                "job_title": "Marketing Executive",
                "start_date": "07-2020",
                "company_name": "Detechgear"
            },
            {
                "details": "Managed all Digital Marketing campaigns and marketing strategies.",
                "end_date": "07-2022",
                "location": "Signature Lifestyle",
                "job_title": "Marketing Intern",
                "start_date": "03-2022",
                "company_name": "Signature Lifestyle"
            }
        ]
    }
}