{
    "output": {
        "justification": [
            "The candidate meets the requirement of having a Bachelor's degree in Business Administration, although the preferred degree is a Master's.",
            "The candidate has worked less than 5 years in sales or key account management as required, making them not meet the experience requirement.",
            "The candidate does not list proficiency in SAP ERP, Salesforce, or Vistex, which are essential skills for the job.",
            "Leadership roles are not clearly demonstrated in the resume, thus impacting the leadership score."
        ],
        "scores": {
            "macro_scores": [
                {
                    "criteria": "experience",
                    "score": 4
                },
                {
                    "criteria": "strategic thinking",
                    "score": 6
                }
            ],
            "micro_scores": [
                {
                    "criteria": "sap erp",
                    "score": 3
                },
                {
                    "criteria": "salesforce",
                    "score": 3
                },
                {
                    "criteria": "vistex",
                    "score": 2
                }
            ],
            "requirements": [
                {
                    "criteria": "Proficiency in data analysis and forecasting tools",
                    "meets": false
                },
                {
                    "criteria": "5+ years of experience in sales or key account management",
                    "meets": false
                }
            ],
            "aggregated_scores": {
                "macro_scores": 5.18,
                "micro_scores": 2.83
            }
        },
        "personal_info": {
            "name": "Saad Bin Hassan",
            "email": "saadbinhassan000@gmail.com",
            "phone": "923133162249",
            "current_position": "Junior Project Associate",
            "current_company": "ProntoDigital, LLC",
            "employment_start_date_current_company": "03-2022",
            "first_company_start_date": "06-2018",
            "urls": [
                {
                    "website_name": "LinkedIn",
                    "url": "https://www.linkedin.com/in/saad-bin-hassan-096118183/"
                }
            ]
        },
        "valid_resume_and_jd": true
    },
    "input": {
        "job_description": "### Key Account Manager at LuxoTech Solutions\n\n**Location:** Karachi, Pakistan\n\n**Department:** Sales and Marketing\n\n**Reports to:** Director of Sales\n\n**Role Overview:**\nJoin LuxoTech Solutions as a Key Account Manager where you will be responsible for managing major accounts in the Retail & Hospitality segments across Pakistan. You will drive sales growth by managing existing accounts and developing strategies for new accounts. Your role will involve coordinating with cross-functional teams, analyzing market trends, and leading initiatives to meet revenue targets.\n\n#### Responsibilities:\n- Manage a portfolio of 15+ key accounts, comprising both end-users and channel partners.\n- Drive expansion into new market segments by identifying and engaging with potential leads.\n- Develop and execute account management strategies to achieve 110% target attainment in revenue.\n- Utilize data analysis tools such as Power BI to assess market trends and generate insights.\n- Coordinate with internal teams including marketing and operations to ensure strategic alignment.\n- Lead contract negotiations and manage pricing strategies to optimize profitability.\n- Report on account performance and market opportunities to senior management regularly.\n\n#### Essential Skills:\n- Strong leadership and stakeholder management skills.\n- Proficiency in data analysis and forecasting to inform decision-making.\n- Experience with tools such as Salesforce, Vistex, and SAP ERP for managing sales functions.\n- Excellent communication skills for client interactions and internal collaborations.\n\n#### Qualifications:\n- Master's degree preferred; Bachelor's degree in Business Administration or related field is required.\n- 5+ years of experience in sales management or business development, with a focus on key account management.\n- Demonstrated success in growing accounts and achieving revenue targets.\n\n#### Benefits:\n- Competitive salary with performance bonuses.\n- Professional development opportunities and access to industry seminars.\n- Flexible working hours.",
        "macro_dict": {
            "experience": 41,
            "strategic thinking": 59
        },
        "micro_dict": {
            "sap erp": 52,
            "salesforce": 31,
            "vistex": 17
        },
        "additional_info": "LuxoTech Solutions values diversity and seeks candidates from a variety of backgrounds and experiences. Preferred institutions include the Institute of Business Administration, Karachi, and FAST NUCES. The company supports hybrid work arrangements and offers relocation assistance for exceptional candidates. Skills are assessed through a combination of technical tests, case studies, and structured interviews with panel members from various departments.",
        "minimum_requirements": [
            "Proficiency in data analysis and forecasting tools",
            "5+ years of experience in sales or key account management"
        ],
        "resume": "  SAAD BIN HASSAN  \nHometown: Lahore  \nCell: 923133162249  | saadbinhassan000@gmail.com  \nDate of Birth: 0 7/04/1998  \nLinkedin Profile: https://www.linkedin.com/in/saad -bin-hassan -096118183/  \nEDUCATION & QUALIFICATIONS  \nMasters of Business Administration  May 2022 \nLahore School of Economics  \nBachelors in Business Administration  (Honors)   June  2021  \nMajor (Marketing) Minor (Media Studies)  \nLahore School of Economics           \nPROFESSIONAL EXPERIENCE         \nProntoDigital, LLC                                                                                               June  2021 \u2013 February 2022  \nBusiness Development Executive  \n\uf0b7 Responsible for finding and retaining new clients, Handling Upwork profiles.  \n\uf0b7 Maintained relationships with clients by providing them information and guidance.  \n\uf0b7 Generated weekly sales reports and provided useful insights.  \nProntoDigital, LLC                                                                        March  2022 \u2013 May 2022  \nJunior Project Associate  \n\uf0b7 Managed and build a Data Analytics team.  \n\uf0b7 Managed to achieve the target of $20,000 in 3 months.  \nBank of Punjab                       June-August  2018 \nOperations Intern, Operations  \n\uf0b7 Responsible to deal with branch daily operations and Opening of new accounts.  \nDetechgear  \nMarketing Executive                                                                                                                                                     July- Dec 2020  \n\uf0b7 Managed all Digital Marketing  of the business.  \n\uf0b7 Achieved sales of 500,000 in 5 months.  \nPROJECTS  \nStrategic Management : Strategic decision making and analyzing a company\u2019s performance by looking at different factors. \nUsing tools like IFE, EFE, CPM, QSPM , etc.  \nAdvertising:  Product adaption of Clear Shampoo according to Pakistani Market. Devised the entire advertising plan \nincorporating all the strategies and storyboard . \nSales Force Management : Analyzed the Sales channel of FFC and developed the strategy to strengthen the Salesforce  \nchannel.  \nMarketing Research: Conducted qualitative and quantita tive research on Nokia Pakistan.  \nADDITIONAL EXPERIENCE  \nTeacher Assistant , Lahore School of Economics                                                                                                2021 \u2013 2022 \nMarketing Intern , Signature Lifestyle.  \n\uf0b7 Managed all Digital Marketing campaigns and marketing strategies.              March -July 2022   \nHONORS & AWARDS  \n\uf0b7 Winner of LSE Business Fiesta 2021  \n\uf0b7 25% Scholarship in Lahore  School of Economics  \nSKILLS & INTERESTS  \n\uf0b7 Competent user of M icrosoft Office , Vegas Pro, SPSS, Smar t PLS , Shopify, and Ecommerce \nManagement.  \n\uf0b7     Digital Marketing, Upwork , Click Up, Slack, FB Ads, Google AdWords , Google Analytics, Canva.  \n       \uf0b7     Strategic Planning, Leadership, Comfortable in Team work.  \n"
    },
    "details": {
        "name": "Saad Bin Hassan",
        "number": "923133162249",
        "skills": [
            "Microsoft Office",
            "Vegas Pro",
            "SPSS",
            "Smart PLS",
            "Shopify",
            "Ecommerce Management",
            "Digital Marketing",
            "Upwork",
            "Click Up",
            "Slack",
            "FB Ads",
            "Google AdWords",
            "Google Analytics",
            "Canva"
        ],
        "email_id": "saadbinhassan000@gmail.com",
        "location": "Lahore",
        "projects": [
            {
                "title": "Strategic Management",
                "description": "Strategic decision making and analyzing a company\u2019s performance by looking at different factors."
            },
            {
                "title": "Advertising",
                "description": "Product adaption of Clear Shampoo according to Pakistani Market."
            },
            {
                "title": "Sales Force Management",
                "description": "Analyzed the Sales channel of FFC and developed the strategy to strengthen the Salesforce channel."
            },
            {
                "title": "Marketing Research",
                "description": "Conducted qualitative and quantitative research on Nokia Pakistan."
            }
        ],
        "education": [
            {
                "end_date": "05-2022",
                "university": "Lahore School of Economics",
                "degree_title": "Masters of Business Administration"
            },
            {
                "end_date": "06-2021",
                "university": "Lahore School of Economics",
                "degree_title": "Bachelors in Business Administration (Honors)"
            }
        ],
        "achievements": [
            "Winner of LSE Business Fiesta 2021",
            "25% Scholarship in Lahore School of Economics"
        ],
        "publications": [],
        "certifications": [],
        "additional_urls": [
            {
                "url": "linkedin.com/in/saad-bin-hassan-096118183/",
                "website_name": "LinkedIn"
            }
        ],
        "executive_summary": "Saad Bin Hassan is a skilled professional with a strong background in business development and digital marketing, holding an MBA and a Bachelor's in Business Administration. He has demonstrated success in managing teams and achieving sales targets, showcasing his technical proficiency in various software and marketing tools.",
        "employment_history": [
            {
                "details": "Responsible for finding and retaining new clients, Handling Upwork profiles. Maintained relationships with clients by providing them information and guidance. Generated weekly sales reports and provided useful insights.",
                "end_date": "02-2022",
                "location": "ProntoDigital, LLC",
                "job_title": "Business Development Executive",
                "start_date": "06-2021",
                "company_name": "ProntoDigital, LLC"
            },
            {
                "details": "Managed and build a Data Analytics team. Managed to achieve the target of $20,000 in 3 months.",
                "end_date": "05-2022",
                "location": "ProntoDigital, LLC",
                "job_title": "Junior Project Associate",
                "start_date": "03-2022",
                "company_name": "ProntoDigital, LLC"
            },
            {
                "details": "Responsible to deal with branch daily operations and Opening of new accounts.",
                "end_date": "08-2018",
                "location": "Bank of Punjab",
                "job_title": "Operations Intern, Operations",
                "start_date": "06-2018",
                "company_name": "Bank of Punjab"
            },
            {
                "details": "Managed all Digital Marketing of the business. Achieved sales of 500,000 in 5 months.",
                "end_date": "12-2020",
                "location": "Detechgear",
                "job_title": "Marketing Executive",
                "start_date": "07-2020",
                "company_name": "Detechgear"
            },
            {
                "details": "Managed all Digital Marketing campaigns and marketing strategies.",
                "end_date": "07-2022",
                "location": "Signature Lifestyle",
                "job_title": "Marketing Intern",
                "start_date": "03-2022",
                "company_name": "Signature Lifestyle"
            }
        ]
    }
}