{
    "output": {
        "justification": [
            "Candidate lacks explicit SEO management and strategic digital marketing experience, which is pivotal for the role.",
            "The resume shows significant leadership roles indirectly through business development activities, but nothing tightly aligned with leading marketing or sales teams.",
            "The candidate has strong client engagement experience as evidenced by 'Client Relations' and 'Client Dealing' roles in business development.",
            "Applicant lacks specific skills in digital marketing tools or SEO-related expertise, impacting direct relevance."
        ],
        "scores": {
            "macro_scores": [
                {
                    "criteria": "leadership",
                    "score": 5
                }
            ],
            "micro_scores": [
                {
                    "criteria": "client engagement",
                    "score": 7
                }
            ],
            "requirements": [
                {
                    "criteria": "Strong analytical and strategic thinking skills",
                    "meets": true
                }
            ],
            "aggregated_scores": {
                "macro_scores": 5.0,
                "micro_scores": 7.0
            }
        },
        "personal_info": {
            "name": "Shahrukh Ali",
            "email": "shahrukh.ali@descon.com",
            "phone": "4618452",
            "current_position": "Business Development Executive",
            "current_company": "InspecTest (Private) Limited",
            "employment_start_date_current_company": "02-2022",
            "first_company_start_date": "08-2009",
            "urls": [
                {
                    "website_name": "LinkedIn",
                    "url": "linkedin.com/in/shahrukh-ali-3021ab24a"
                }
            ]
        },
        "valid_resume_and_jd": true
    },
    "input": {
        "job_description": "## Job Title: Sales and SEO Management Specialist  \n\n### Location: Lahore, Pakistan  \n\n### Company: Innovate Digital Solutions Inc.  \n\n### Job Summary:  \nJoin Innovate Digital Solutions Inc. as a Sales and SEO Management Specialist. You will be part of a dynamic team responsible for driving client engagement and ensuring optimal performance in digital marketing strategies. Your role will include managing client relationships, improving SEO strategies, and leading your team to achieve sales targets.  \n\n### Key Responsibilities:  \n- Proactively engage with prospective clients to understand their business needs and provide innovative solutions.  \n- Design and execute SEO strategies in alignment with client\u2019s marketing objectives.  \n- Manage and optimize PPC campaigns to maximize ROI and brand visibility.  \n- Develop and maintain strong client relationships through tailored marketing solutions.  \n- Lead a team to achieve and surpass sales targets while providing exceptional customer service.  \n- Analyze market trends and algorithms to tailor SEO strategies accordingly.  \n- Produce reports that track progress and measure success against KPIs.  \n\n### Ideal Candidate Profile:  \nYou are a skilled sales and marketing professional with strong analytical skills suited to identifying and executing SEO opportunities. You excel at client interactions, possessing the ability to transform potential leads into satisfied clients through strategic and well-executed marketing initiatives. Leadership and team management skills will be pivotal to drive sales and motivate your team.  \n\n### Benefits:  \n- Competitive salary package  \n- Health and wellness benefits  \n- Performance bonuses  \n- Opportunities for career advancement  \n\nJoin us to redefine digital engagement and lead market strategies with agility and innovation.",
        "macro_dict": {
            "leadership": 100
        },
        "micro_dict": {
            "client engagement": 100
        },
        "additional_info": "Innovate Digital Solutions Inc. prefers candidates from reputable institutions such as [University of Lahore], [Punjab University]. Remote work options are available subject to roles and responsibilities. We assess skills through a combination of technical tests, interviews, and real-world problem-solving scenarios to gauge practical competency in strategic marketing contexts.",
        "minimum_requirements": [
            "Strong analytical and strategic thinking skills"
        ],
        "resume": "SHAHRUKH ALI\nshahrukh.ali@descon.com 4618452\nlinkedin.com/in/shahrukh-ali-3021ab24a\nSummary\nA highly motivated and result-driven Business Development Executive who also has served as a Finance &\nAccounts Professional with 12 years of invaluable experience including being skilled in numerous business\ndevelopment, financial & accounting fields. I have the ability to handle complex assignments effectively &\npossessing the confidence to work as part of a team or independently. An established reputation for self\u2010\nmotivation, attention to detail excellent organizational skills, and high ethical conduct. Presently looking for the\nbest opportunity with a goal-oriented company where I can excel, deliver and achieve according to my potential. I\nam enthusiastic to learn keenly about emerging developments in my job sector.\nExperience\nSenior Associate\nKPMG In Pakistan\nAug 2021 - Feb 2022 (7 months)\nTeam Supervision and Training\nData entry analyst: Update the system as invoices are received.\nBank Payment Analyst: Processing accounts and incoming payments in compliance.\nSAP ERP\nOracle\nFinancial policies and procedures.\nExceptions analyst: Address disputes and payment failure issues.\nVendor maintenance analyst: Maintain an accurate supplier database.\nFinance Analyst: Performing day-to-day financial transactions, including verifying, classifying,\ncomputing, posting, and recording accounts receivables\u2019 data\nBusiness Development Executive\nInspecTest (Private) Limited\nFeb 2022 - Present (7 months +)\nBusiness Development Accounting, Finance, and Revenue\nClient Relations\nClient Dealing\nAccounts Executive\nDescon Engineering Limited\nAug 2009 - Jul 2021 (12 years)\nData entry analyst: Update the system as invoices are received.\nBank Payment Analyst\nSAP ERP\nOracle\nFinancial policies and procedures.\nExceptions analyst: Address disputes and payment failure issues.\nSHAHRUKH ALI - page 1Vendor maintenance analyst: Maintain an accurate supplier database.\nFinance Analyst: Performing day-to-day financial transactions, including verifying, classifying,\ncomputing, posting, and recording accounts receivables\u2019 data\nEducation\nUniversity Of Central Punjab\nMBA\nHajvery University\nBachelor of Commerce\nSkills\nabacus  \u00a0 \u2022 \u00a0 accountancy  \u00a0 \u2022 \u00a0 accounts receivable  \u00a0 \u2022 \u00a0 accpac  \u00a0 \u2022 \u00a0 analysis  \u00a0 \u2022 \u00a0 business law  \u00a0 \u2022 \u00a0 ceo  \u00a0 \u2022 \u00a0\nconsulting  \u00a0 \u2022 \u00a0 data entry  \u00a0 \u2022 \u00a0 database administration\nSHAHRUKH ALI - page 2"
    },
    "details": {
        "name": "SHAHRUKH ALI",
        "number": "4618452",
        "skills": [
            "SAP ERP",
            "Oracle",
            "abacus",
            "accountancy",
            "accounts receivable",
            "accpac",
            "data entry",
            "database administration"
        ],
        "email_id": "shahrukh.ali@descon.com",
        "location": "",
        "projects": [],
        "education": [
            {
                "end_date": "06-2010",
                "university": "Hajvery University",
                "degree_title": "Bachelor of Commerce"
            },
            {
                "end_date": "06-2012",
                "university": "University Of Central Punjab",
                "degree_title": "MBA"
            }
        ],
        "achievements": [],
        "publications": [],
        "certifications": [],
        "additional_urls": [
            {
                "url": "linkedin.com/in/shahrukh-ali-3021ab24a",
                "website_name": "LinkedIn"
            }
        ],
        "executive_summary": "SHAHRUKH ALI is a highly motivated and result-driven Business Development Executive with 12 years of invaluable experience in business development, finance, and accounting. He possesses strong technical skills in SAP ERP and Oracle, and has a proven track record in handling complex assignments effectively.",
        "employment_history": [
            {
                "details": "Team Supervision and Training, Data entry analyst: Update the system as invoices are received, Bank Payment Analyst: Processing accounts and incoming payments in compliance, Exceptions analyst: Address disputes and payment failure issues, Vendor maintenance analyst: Maintain an accurate supplier database, Finance Analyst: Performing day-to-day financial transactions, including verifying, classifying, computing, posting, and recording accounts receivables\u2019 data.",
                "end_date": "02-2022",
                "location": "Pakistan",
                "job_title": "Senior Associate",
                "start_date": "08-2021",
                "company_name": "KPMG In Pakistan"
            },
            {
                "details": "Business Development Accounting, Finance, and Revenue, Client Relations, Client Dealing.",
                "end_date": "",
                "location": "",
                "job_title": "Business Development Executive",
                "start_date": "02-2022",
                "company_name": "InspecTest (Private) Limited"
            },
            {
                "details": "Data entry analyst: Update the system as invoices are received, Bank Payment Analyst, Exceptions analyst: Address disputes and payment failure issues, Vendor maintenance analyst: Maintain an accurate supplier database, Finance Analyst: Performing day-to-day financial transactions, including verifying, classifying, computing, posting, and recording accounts receivables\u2019 data.",
                "end_date": "07-2021",
                "location": "",
                "job_title": "Accounts Executive",
                "start_date": "08-2009",
                "company_name": "Descon Engineering Limited"
            }
        ]
    }
}