{
    "output": {
        "justification": [
            "Candidate demonstrates significant leadership qualities through management roles in multiple companies.",
            "Has relevant experience in digital marketing and lead generation, aligning closely with job requirements.",
            "Proficiency in Zoho CRM aligns well with job responsibilities involving CRM systems.",
            "No evidence of proficiency in programming languages specified (C++, HTML, CSS)."
        ],
        "scores": {
            "macro_scores": [
                {
                    "criteria": "leadership",
                    "score": 8
                },
                {
                    "criteria": "experience",
                    "score": 7
                },
                {
                    "criteria": "innovation and adaptability",
                    "score": 6
                }
            ],
            "micro_scores": [
                {
                    "criteria": "business intelligence tools (power bi, sql, tableau)",
                    "score": 5
                },
                {
                    "criteria": "crm and data management",
                    "score": 8
                }
            ],
            "requirements": [
                {
                    "criteria": "Proficiency in at least one programming language",
                    "meets": false
                }
            ],
            "aggregated_scores": {
                "macro_scores": 7.720000000000001,
                "micro_scores": 7.28
            }
        },
        "personal_info": {
            "name": "Syed Ali Sher Rizvi",
            "email": "sahibzadaali66@gmail.com",
            "phone": "03015062755",
            "current_position": "Business Development Manager",
            "current_company": "HappyTanent",
            "employment_start_date_current_company": "01-2022",
            "first_company_start_date": "08-2018",
            "urls": [
                {
                    "website_name": "LinkedIn",
                    "url": "linkedin.com/in/syed-ali-shair-rizvi-7bb859171"
                },
                {
                    "website_name": "Minora Cart",
                    "url": "https://www.minoracart.com/"
                }
            ]
        },
        "valid_resume_and_jd": true
    },
    "input": {
        "job_description": "## Lead Generation and Business Intelligence Specialist\n\nJoin **Innovate Connections Inc.** as a Lead Generation and Business Intelligence Specialist. You will play a pivotal role in driving business growth by spearheading lead generation initiatives and providing strategic insights through data analytics. We are looking for a highly skilled professional with a strong background in lead generation, data management, and business intelligence.\n\n### Key Responsibilities:\n- Develop and execute lead generation strategies using digital marketing techniques, cold calling, and data scraping tools.\n- Collaborate with cross-functional teams to optimize customer acquisition strategies.\n- Utilize CRM systems to manage and analyze client data for lead qualification.\n- Create and manage detailed project schedules and work plans, utilizing best practices and standards for project execution.\n- Develop financial models and business growth strategies based on data insights.\n- Utilize tools such as Power BI, SQL, and Tableau for developing comprehensive data reports and dashboards.\n\n### Desired Skills and Experience:\n- Strong programming skills in C++, HTML, and CSS.\n- Proficiency in digital marketing, email marketing, and social media platforms.\n- Experience in managing large data sets and using BI tools (Power BI, Excel, Tableau).\n- Excellent communication skills and ability to develop strong client relationships.\n- Ability to work independently and manage multiple projects simultaneously.\n\n### Why Innovate Connections Inc.?\n- We innovate at the forefront of technology and enable our team members to grow alongside the company.\n- We value data-driven decision-making and empower our teams with the right tools to succeed.\n- Offering a supportive work environment and opportunities for career advancement.\n\n### How to Apply:\nSubmit your resume and cover letter detailing your relevant experience and why you are interested in joining Innovate Connections Inc.",
        "macro_dict": {
            "leadership": 81,
            "experience": 10,
            "innovation and adaptability": 9
        },
        "micro_dict": {
            "business intelligence tools (power bi, sql, tableau)": 24,
            "crm and data management": 76
        },
        "additional_info": "Innovate Connections Inc. prefers candidates from recognized universities such as the University of Management & Technology and Lahore School of Economics. We encourage a remote working environment but require physical presence for team-building and strategic sessions twice a quarter. Relocation assistance is available for exceptional candidates. Our comprehensive assessment includes a technical test followed by structured interviews to evaluate both technical and soft skills comprehensively.",
        "minimum_requirements": [
            "Proficiency in at least one programming language"
        ],
        "resume": "Syed Ali Sher Rizvi \nBusiness Development Manager \nAn organized and creative professional with proven marketing skills and a desire to learn more. Possess\n4+ years of experience working for a diverse group of organizations and clients. Gained expertise in data\nanalysis, publication marketing, and web-based advertising. Looking to utilize my existing skill set to\nincrease company pro\ufb01tability at Spleen Manufacturing (Pvt) Ltd. \nsahibzadaali66@gmail.com \n03015062755 \nLahore, Pakistan \nlinkedin.com/in/syed-ali-shair-rizvi-7bb859171 \nWORK EXPERIENCE \nBusiness Development Manager \nHappyTanent \n01/2022 - Present\n, \n \nLahore/Dubai, UAE \nHappyTenant is UAE base company, I'm working here (remotely) to develop their\nbusiness in Pakistan, USA, and UAE as well. \nSetting goals and developing plans for business and revenue\ngrowth. \nPlanning and overseeing new marketing initiatives. \nIncreasing the value of current customers while attracting new\nones. \nAttending conferences, meetings, and industry events. \nSocial Media Coordinator \nMinora Cart \n01/2022 - Present\n, \n \nLahore/Dubai, UAE \nhttps://www.minoracart.com/ \nAnalyzed and reported social media presence, engagement, and\ne\ufb00ectiveness on all platforms \nEngaged in consistent interactions with clients, donors, and fans \nDoubled website tra\ufb03c from 15,000 average visitors to 31,000 \nAsst. Manager Marketing \nSpleen Manufacturing (Pvt) Ltd 08/2018 - Present, \n10/2018 - 02/2022\n, \n \nLahore, Pakistan \nProviding Engineering Solutions For All Kind Of Light & Heavy Fabrications \nSuccessfully spearhead campaigns on social media platforms\nincluding Facebook, Twitter, and Instagram \nContact \n:\n-\nRana Shahbaz Ahmed (Head BD & marketing) \n0300 8463927 \nEDUCATION \nMSC Marketing \nNational Collage of Business Administration &\nEconomics \n2020 - Present\n, \n \nLahore. Pakistan \nGlobal Outsourcing \nContract Management \nEntrepreneurship \nFinical Management \nBachelor in Commerce \nUniversity Of Punjab \n12/2016 - 05/2018\n, \n \nLahore Pakistan \nSKILLS \nMS O\ufb03ce \nZoho CRM \nMailChimp \nNegotiation \nAbility to engage \nExcellent verbal and written communication \nAbility to persuade \nEmail Marketing \nLead Generation \nSales Navigator \nSignalHire \nApollo.io \nBu\ufb00er \nDigital advertising \nACHIEVEMENTS \nDigital Marketing Course From PNY Institute\n (09/2021)\n \nSocial Media Marketing, Google Ad words, SMM, Mobile\nMarketing \nHuawei Managment\n (2018 - Present)\n \nFull handling Huawei portal \nfully coordinate with their team for\nrecent contracts and future negotiation in cotracts \nERP (SARP) \nFull handle ERP Software and have enough awareness that can\nhandle each department through it. \nAchiever of the Year (Spleen Manufacturing)\n (2019 - 2020)\n \nCOMPANY PROJECTS \nMinora cart\n (06/2022 - Present)\n \nSocial Media Advertisement \nProject Name \nDelux - Pest Control Services\n (12/2022 - Present)\n \nSocial Media Marketing (LOW CPC - High Conversions) \n220 kV Dhabji Transmission Line Projects\n (09/2021 - 11/2021)\n \nHuawei Projects (CMPAK, JAZZ, Ufone Telenor)\n (02/2021 - Present)\n \nCERTIFICATES \nDigital Marketing\n (2021 - Present)\n \nYoutube Marketing\n (2021 - Present)\n \nAchievements/Tasks \nAchievements/Tasks \nAchievements/Tasks \nCourses "
    },
    "details": {
        "name": "Syed Ali Sher Rizvi",
        "number": "03015062755",
        "skills": [
            "MS Office",
            "Zoho CRM",
            "MailChimp",
            "Email Marketing",
            "Lead Generation",
            "Sales Navigator",
            "SignalHire",
            "Apollo.io",
            "Buffer",
            "Digital advertising"
        ],
        "email_id": "sahibzadaali66@gmail.com",
        "location": "Lahore, Pakistan",
        "projects": [
            {
                "title": "Minora cart",
                "description": "Social Media Advertisement"
            },
            {
                "title": "Delux - Pest Control Services",
                "description": "Social Media Marketing (LOW CPC - High Conversions)"
            },
            {
                "title": "220 kV Dhabji Transmission Line Projects",
                "description": ""
            },
            {
                "title": "Huawei Projects (CMPAK, JAZZ, Ufone Telenor)",
                "description": ""
            }
        ],
        "education": [
            {
                "end_date": "05-2018",
                "university": "University Of Punjab",
                "degree_title": "Bachelor in Commerce"
            },
            {
                "end_date": "Present",
                "university": "National Collage of Business Administration & Economics",
                "degree_title": "MSC Marketing"
            }
        ],
        "achievements": [
            "Digital Marketing Course From PNY Institute (09-2021)",
            "Achiever of the Year (Spleen Manufacturing) (2019 - 2020)"
        ],
        "publications": [],
        "certifications": [
            {
                "certification_name": "Digital Marketing",
                "issuing_organization": "Not specified",
                "date_of_issuance": "2021"
            },
            {
                "certification_name": "Youtube Marketing",
                "issuing_organization": "Not specified",
                "date_of_issuance": "2021"
            }
        ],
        "additional_urls": [
            {
                "url": "linkedin.com/in/syed-ali-shair-rizvi-7bb859171",
                "website_name": "LinkedIn"
            }
        ],
        "executive_summary": "Syed Ali Sher Rizvi is a Business Development Manager with over 4 years of experience in marketing and business growth strategies. He has a strong background in data analysis, publication marketing, and web-based advertising, and is currently focused on enhancing profitability for Spleen Manufacturing (Pvt) Ltd.",
        "employment_history": [
            {
                "details": "Developing business in Pakistan, USA, and UAE, setting goals and developing plans for business and revenue growth.",
                "end_date": "Present",
                "location": "Lahore/Dubai, UAE",
                "job_title": "Business Development Manager",
                "start_date": "01-2022",
                "company_name": "HappyTanent"
            },
            {
                "details": "Analyzed and reported social media presence, engagement, and effectiveness on all platforms, doubled website traffic.",
                "end_date": "Present",
                "location": "Lahore/Dubai, UAE",
                "job_title": "Social Media Coordinator",
                "start_date": "01-2022",
                "company_name": "Minora Cart"
            },
            {
                "details": "Successfully spearheaded campaigns on social media platforms including Facebook, Twitter, and Instagram.",
                "end_date": "02-2022",
                "location": "Lahore, Pakistan",
                "job_title": "Asst. Manager Marketing",
                "start_date": "10-2018",
                "company_name": "Spleen Manufacturing (Pvt) Ltd"
            }
        ]
    }
}