{
    "output": {
        "justification": [
            "The candidate lacks specific key account management experience as required by the job description.",
            "Candidate does not possess a degree in Business Administration or a related field.",
            "Only limited experience with CRM systems is mentioned without specifics like Salesforce or SAP ERP.",
            "There is no mention of proficiency in data analysis tools or similar platforms."
        ],
        "scores": {
            "macro_scores": [
                {
                    "criteria": "experience",
                    "score": 4
                }
            ],
            "micro_scores": [
                {
                    "criteria": "stakeholder management",
                    "score": 4
                },
                {
                    "criteria": "sap erp",
                    "score": 1
                },
                {
                    "criteria": "salesforce",
                    "score": 3
                }
            ],
            "requirements": [
                {
                    "criteria": "5+ years of experience in sales or key account management",
                    "meets": false
                },
                {
                    "criteria": "Bachelor's degree in Business Administration or related field",
                    "meets": false
                },
                {
                    "criteria": "Experience with CRM and ERP systems such as SAP and Salesforce",
                    "meets": false
                },
                {
                    "criteria": "Proficiency in data analysis and forecasting tools",
                    "meets": false
                }
            ],
            "aggregated_scores": {
                "macro_scores": 4.0,
                "micro_scores": 2.45
            }
        },
        "personal_info": {
            "name": "Samha Ahmed",
            "email": "samhaahmed39@gmail.com",
            "phone": "+923324817353",
            "current_position": "Business Development Executive",
            "current_company": "Rolustech",
            "employment_start_date_current_company": "09-2021",
            "first_company_start_date": "05-2021",
            "urls": []
        },
        "valid_resume_and_jd": true
    },
    "input": {
        "job_description": "### Key Account Manager at LuxoTech Solutions\n\n**Location:** Karachi, Pakistan\n\n**Department:** Sales and Marketing\n\n**Reports to:** Director of Sales\n\n**Role Overview:**\nJoin LuxoTech Solutions as a Key Account Manager where you will be responsible for managing major accounts in the Retail & Hospitality segments across Pakistan. You will drive sales growth by managing existing accounts and developing strategies for new accounts. Your role will involve coordinating with cross-functional teams, analyzing market trends, and leading initiatives to meet revenue targets.\n\n#### Responsibilities:\n- Manage a portfolio of 15+ key accounts, comprising both end-users and channel partners.\n- Drive expansion into new market segments by identifying and engaging with potential leads.\n- Develop and execute account management strategies to achieve 110% target attainment in revenue.\n- Utilize data analysis tools such as Power BI to assess market trends and generate insights.\n- Coordinate with internal teams including marketing and operations to ensure strategic alignment.\n- Lead contract negotiations and manage pricing strategies to optimize profitability.\n- Report on account performance and market opportunities to senior management regularly.\n\n#### Essential Skills:\n- Strong leadership and stakeholder management skills.\n- Proficiency in data analysis and forecasting to inform decision-making.\n- Experience with tools such as Salesforce, Vistex, and SAP ERP for managing sales functions.\n- Excellent communication skills for client interactions and internal collaborations.\n\n#### Qualifications:\n- Master's degree preferred; Bachelor's degree in Business Administration or related field is required.\n- 5+ years of experience in sales management or business development, with a focus on key account management.\n- Demonstrated success in growing accounts and achieving revenue targets.\n\n#### Benefits:\n- Competitive salary with performance bonuses.\n- Professional development opportunities and access to industry seminars.\n- Flexible working hours.",
        "macro_dict": {
            "experience": 100
        },
        "micro_dict": {
            "stakeholder management": 37,
            "sap erp": 46,
            "salesforce": 17
        },
        "additional_info": "LuxoTech Solutions values diversity and seeks candidates from a variety of backgrounds and experiences. Preferred institutions include the Institute of Business Administration, Karachi, and FAST NUCES. The company supports hybrid work arrangements and offers relocation assistance for exceptional candidates. Skills are assessed through a combination of technical tests, case studies, and structured interviews with panel members from various departments.",
        "minimum_requirements": [
            "5+ years of experience in sales or key account management",
            "Bachelor's degree in Business Administration or related field",
            "Experience with CRM and ERP systems such as SAP and Salesforce",
            "Proficiency in data analysis and forecasting tools"
        ],
        "resume": "SAMHA\nAHMED\nAddress: Lahore, Pakistan \u2013 Phone: +923324817353\nEmail:\nsamhaahmed39@gmail.com\nOBJECTIVE\nTo work in a challenging environment where I can better utilize my skills and enhance my experience in\nthe domain of sales and business development.\nWORK EXPERIENCE\nBUSINESS DEVELOPMENT EXECUTIVE\nRolustech\n(September 2021 \u2013 Present)\nBUSINESS DEVELOPMENT EXECUTIVE\nTxLabz\n(May 2021 \u2013 September 2021)\nASSOCIATE PROJECT MANAGER\nTxLabz\n(June 2021 \u2013 September 2021)\nEDUCATION\nBS INFORMATION TECHNOLOGY\n(2017\u20132021)\nPunjab University College of Information Technology, Lahore\n(OOP, DSA, DB, Web, Android, SQA)\nF.SC PRE-ENGINEERING\n(2015 \u2013 2017)\nPunjab College of Science, Lahore\n(Chemistry, Physics, Mathematics)\nPercentage: 80%\nMATRICULATION\n(2013 \u2013 2015)\nWapda Girls High School, Lahore\n(Computer, Mathematics, Physics, Chemistry)\nPercentage: 93%PERSONAL SKILLS\n\u25cf\nStrong interpersonal skills\n\u25cf\nE\ufb00ective Listening\n\u25cf\nAbility to negotiate\n\u25cf\nAbility to Multitask\n\u25cf\nAttention to details\n\u25cf\nProfessional behavior\n\u25cf\nTime and resource \nmanagement\n\u25cf\nE\ufb00ective Decision making\nORGANIZATIONAL/ MANAGERIAL SKILLS\n\u25cf\nBusiness intelligence and marketing skills\n\u25cf\nHands-on experience in Upwork bidding and utilization of freelancing platforms for lead\ngeneration\n\u25cf\nKnowledge of all the stages of a sales cycle\n\u25cf\nExperience with CRM systems\n\u25cf\nStrong knowledge of lead generation using email campaigns and popular marketing tools\n\u25cf\nAbility to analyze market trends and suggest new ideas/strategies for improving sales\n\u25cf\nAbility to interact and e\ufb00ectively communicate with people from diverse backgrounds\n\u25cf\nStrong persuasion skills that help in maximizing customer satisfaction\n\u25cf\nGood at creating and goal setting and meeting goals, decision making, managing\nappointments, team management, and strategic thinking\nSEMESTER PROJECTS\nCAMPUS MANAGEMENT SYSTEM\nSubject: Programming Fundamentals, It was developed in C++.\nNGO DATABASE SYSTEM\nSubject: Database System. It was developed in ORACLE using PHP, HTML, and CSS.\nLUDO GAME\nSubject: OOAD (Object-Oriented Analysis and Design). It was developed in JAVA.\nONLINE ART GALLERY\nSubject: Web Development. It was developed using HTML, CSS, Bootstrap, JavaScript, AJAX,\nJQUERY, and JSON.FINAL YEAR PROJECT\nPU E-BUS TRACKING APPLICATION\nIt is an application that will provide Real-time Bus locations to the students. It is an\nAndroid-based project. The application has two modules; one is for drivers, the other for\nstudents. When a driver opens the app, his real-time location in Firebase is saved. When\na student opens the app, nearby buses within a 3km of radius are shown to the student.\nWe have also developed a Website for admins who can remove or add buses.\nTools for Android: Java, XML, Gradle, and Firebase Database.\nTools for Web: HTML5, CSS3, JavaScript, jQuery, React, Python and MySQL."
    },
    "details": {
        "name": "Samha Ahmed",
        "number": "923324817353",
        "skills": [
            "C++",
            "ORACLE",
            "PHP",
            "HTML",
            "CSS",
            "JAVA",
            "HTML5",
            "CSS3",
            "JavaScript",
            "jQuery",
            "React",
            "Python",
            "MySQL",
            "XML",
            "Gradle",
            "Firebase Database"
        ],
        "email_id": "samhaahmed39@gmail.com",
        "location": "Lahore, Pakistan",
        "projects": [
            {
                "title": "Campus Management System",
                "description": "Developed in C++."
            },
            {
                "title": "NGO Database System",
                "description": "Developed in ORACLE using PHP, HTML, and CSS."
            },
            {
                "title": "Ludo Game",
                "description": "Developed in JAVA."
            },
            {
                "title": "Online Art Gallery",
                "description": "Developed using HTML, CSS, Bootstrap, JavaScript, AJAX, jQuery, and JSON."
            },
            {
                "title": "PU E-Bus Tracking Application",
                "description": "Android-based project providing real-time bus locations."
            }
        ],
        "education": [
            {
                "end_date": "06-2021",
                "university": "Punjab University College of Information Technology, Lahore",
                "degree_title": "BS Information Technology"
            },
            {
                "end_date": "05-2017",
                "university": "Punjab College of Science, Lahore",
                "degree_title": "F.Sc Pre-Engineering"
            },
            {
                "end_date": "05-2015",
                "university": "Wapda Girls High School, Lahore",
                "degree_title": "Matriculation"
            }
        ],
        "achievements": [],
        "publications": [],
        "certifications": [],
        "additional_urls": [],
        "executive_summary": "Samha Ahmed is a dedicated business development executive with a strong educational background in Information Technology. She possesses a diverse skill set in programming and web development, demonstrated through various projects and practical experience in the field.",
        "employment_history": [
            {
                "details": "Business Development Executive at Rolustech.",
                "end_date": "Present",
                "location": "Lahore, Pakistan",
                "job_title": "Business Development Executive",
                "start_date": "09-2021",
                "company_name": "Rolustech"
            },
            {
                "details": "Business Development Executive at TxLabz.",
                "end_date": "09-2021",
                "location": "Lahore, Pakistan",
                "job_title": "Business Development Executive",
                "start_date": "05-2021",
                "company_name": "TxLabz"
            },
            {
                "details": "Associate Project Manager at TxLabz.",
                "end_date": "09-2021",
                "location": "Lahore, Pakistan",
                "job_title": "Associate Project Manager",
                "start_date": "06-2021",
                "company_name": "TxLabz"
            }
        ]
    }
}