{
    "output": {
        "justification": [
            "The candidate did not graduate from a preferred business school like COMSATS Institute of Information and Technology.",
            "Leadership experience is apparent in the Business Development Manager role at HappyTenant.",
            "Proficient in using CRM tools such as Zoho CRM which meets the proficiency requirement.",
            "The candidate has direct experience in lead generation from current and previous roles which aligns with the job description requirements."
        ],
        "scores": {
            "macro_scores": [
                {
                    "criteria": "strategic planning",
                    "score": 7
                }
            ],
            "micro_scores": [
                {
                    "criteria": "lead generation",
                    "score": 8
                },
                {
                    "criteria": "project management",
                    "score": 6
                }
            ],
            "requirements": [
                {
                    "criteria": "Bachelor's degree in Business Administration or related field",
                    "meets": true
                },
                {
                    "criteria": "Proficiency in CRM tools and Microsoft Office Suite",
                    "meets": true
                },
                {
                    "criteria": "Proven track record in lead generation and client engagement",
                    "meets": true
                }
            ],
            "aggregated_scores": {
                "macro_scores": 7.0,
                "micro_scores": 6.58
            }
        },
        "personal_info": {
            "name": "Syed Ali Sher Rizvi",
            "email": "sahibzadaali66@gmail.com",
            "phone": "03015062755",
            "current_position": "Business Development Manager",
            "current_company": "HappyTanent",
            "employment_start_date_current_company": "01-2022",
            "first_company_start_date": "08-2018",
            "urls": [
                {
                    "website_name": "LinkedIn",
                    "url": "https://www.linkedin.com/in/syed-ali-shair-rizvi-7bb859171"
                },
                {
                    "website_name": "Minora Cart",
                    "url": "https://www.minoracart.com/"
                }
            ]
        },
        "valid_resume_and_jd": true
    },
    "input": {
        "job_description": "### Business Development Manager\n\nJoin **InnovateCorp** as a Business Development Manager to contribute to our growing team and drive strategic initiatives in the technology services sector. The ideal candidate will leverage their extensive experience in business development, client relations, and project management to expand our market presence and build lasting partnerships.\n\n#### Key Responsibilities:\n- Develop and implement strategic business development plans to achieve company goals.\n- Lead generation and relationship building with potential clients.\n- Oversee client acquisition strategies, including exploration beyond freelance markets.\n- Collaborate with cross-functional teams to ensure smooth project delivery.\n- Utilize CRM software for tracking client engagement and development progress.\n- Conduct market research to stay abreast of industry trends and inform business strategies.\n- Manage and report on business development metrics.\n\n#### Skills and Competencies:\n- Strong communication and interpersonal skills for client engagement and collaboration.\n- Excellent analytical abilities to inform proposals and strategic decisions.\n- Experience with Microsoft Office for documentation and presentations.\n- Proficiency in CRM software for managing client relationships.\n\n#### Benefits:\n- Competitive salary with bonus incentives.\n- Opportunities for professional development and career advancement.\n- Health and dental insurance packages.\n- Flexible working hours and a positive, team-oriented environment.",
        "macro_dict": {
            "strategic planning": 100
        },
        "micro_dict": {
            "lead generation": 29,
            "project management": 71
        },
        "additional_info": "InnovateCorp prefers candidates from leading business schools such as COMSATS Institute of Information and Technology. We support relocation for the right candidate and offer remote work opportunities. Skills are assessed through a combination of technical interviews and practical case studies, ensuring candidates meet our high standards of performance before offering a position.",
        "minimum_requirements": [
            "Bachelor's degree in Business Administration or related field",
            "Proficiency in CRM tools and Microsoft Office Suite",
            "Proven track record in lead generation and client engagement"
        ],
        "resume": "Syed Ali Sher Rizvi \nBusiness Development Manager \nAn organized and creative professional with proven marketing skills and a desire to learn more. Possess\n4+ years of experience working for a diverse group of organizations and clients. Gained expertise in data\nanalysis, publication marketing, and web-based advertising. Looking to utilize my existing skill set to\nincrease company pro\ufb01tability at Spleen Manufacturing (Pvt) Ltd. \nsahibzadaali66@gmail.com \n03015062755 \nLahore, Pakistan \nlinkedin.com/in/syed-ali-shair-rizvi-7bb859171 \nWORK EXPERIENCE \nBusiness Development Manager \nHappyTanent \n01/2022 - Present\n, \n \nLahore/Dubai, UAE \nHappyTenant is UAE base company, I'm working here (remotely) to develop their\nbusiness in Pakistan, USA, and UAE as well. \nSetting goals and developing plans for business and revenue\ngrowth. \nPlanning and overseeing new marketing initiatives. \nIncreasing the value of current customers while attracting new\nones. \nAttending conferences, meetings, and industry events. \nSocial Media Coordinator \nMinora Cart \n01/2022 - Present\n, \n \nLahore/Dubai, UAE \nhttps://www.minoracart.com/ \nAnalyzed and reported social media presence, engagement, and\ne\ufb00ectiveness on all platforms \nEngaged in consistent interactions with clients, donors, and fans \nDoubled website tra\ufb03c from 15,000 average visitors to 31,000 \nAsst. Manager Marketing \nSpleen Manufacturing (Pvt) Ltd 08/2018 - Present, \n10/2018 - 02/2022\n, \n \nLahore, Pakistan \nProviding Engineering Solutions For All Kind Of Light & Heavy Fabrications \nSuccessfully spearhead campaigns on social media platforms\nincluding Facebook, Twitter, and Instagram \nContact \n:\n-\nRana Shahbaz Ahmed (Head BD & marketing) \n0300 8463927 \nEDUCATION \nMSC Marketing \nNational Collage of Business Administration &\nEconomics \n2020 - Present\n, \n \nLahore. Pakistan \nGlobal Outsourcing \nContract Management \nEntrepreneurship \nFinical Management \nBachelor in Commerce \nUniversity Of Punjab \n12/2016 - 05/2018\n, \n \nLahore Pakistan \nSKILLS \nMS O\ufb03ce \nZoho CRM \nMailChimp \nNegotiation \nAbility to engage \nExcellent verbal and written communication \nAbility to persuade \nEmail Marketing \nLead Generation \nSales Navigator \nSignalHire \nApollo.io \nBu\ufb00er \nDigital advertising \nACHIEVEMENTS \nDigital Marketing Course From PNY Institute\n (09/2021)\n \nSocial Media Marketing, Google Ad words, SMM, Mobile\nMarketing \nHuawei Managment\n (2018 - Present)\n \nFull handling Huawei portal \nfully coordinate with their team for\nrecent contracts and future negotiation in cotracts \nERP (SARP) \nFull handle ERP Software and have enough awareness that can\nhandle each department through it. \nAchiever of the Year (Spleen Manufacturing)\n (2019 - 2020)\n \nCOMPANY PROJECTS \nMinora cart\n (06/2022 - Present)\n \nSocial Media Advertisement \nProject Name \nDelux - Pest Control Services\n (12/2022 - Present)\n \nSocial Media Marketing (LOW CPC - High Conversions) \n220 kV Dhabji Transmission Line Projects\n (09/2021 - 11/2021)\n \nHuawei Projects (CMPAK, JAZZ, Ufone Telenor)\n (02/2021 - Present)\n \nCERTIFICATES \nDigital Marketing\n (2021 - Present)\n \nYoutube Marketing\n (2021 - Present)\n \nAchievements/Tasks \nAchievements/Tasks \nAchievements/Tasks \nCourses "
    },
    "details": {
        "name": "Syed Ali Sher Rizvi",
        "number": "03015062755",
        "skills": [
            "MS Office",
            "Zoho CRM",
            "MailChimp",
            "Email Marketing",
            "Lead Generation",
            "Sales Navigator",
            "SignalHire",
            "Apollo.io",
            "Buffer",
            "Digital advertising"
        ],
        "email_id": "sahibzadaali66@gmail.com",
        "location": "Lahore, Pakistan",
        "projects": [
            {
                "title": "Minora cart",
                "description": "Social Media Advertisement"
            },
            {
                "title": "Delux - Pest Control Services",
                "description": "Social Media Marketing (LOW CPC - High Conversions)"
            },
            {
                "title": "220 kV Dhabji Transmission Line Projects",
                "description": ""
            },
            {
                "title": "Huawei Projects (CMPAK, JAZZ, Ufone Telenor)",
                "description": ""
            }
        ],
        "education": [
            {
                "end_date": "05-2018",
                "university": "University Of Punjab",
                "degree_title": "Bachelor in Commerce"
            },
            {
                "end_date": "Present",
                "university": "National Collage of Business Administration & Economics",
                "degree_title": "MSC Marketing"
            }
        ],
        "achievements": [
            "Digital Marketing Course From PNY Institute (09-2021)",
            "Achiever of the Year (Spleen Manufacturing) (2019 - 2020)"
        ],
        "publications": [],
        "certifications": [
            {
                "certification_name": "Digital Marketing",
                "issuing_organization": "Not specified",
                "date_of_issuance": "2021"
            },
            {
                "certification_name": "Youtube Marketing",
                "issuing_organization": "Not specified",
                "date_of_issuance": "2021"
            }
        ],
        "additional_urls": [
            {
                "url": "linkedin.com/in/syed-ali-shair-rizvi-7bb859171",
                "website_name": "LinkedIn"
            }
        ],
        "executive_summary": "Syed Ali Sher Rizvi is a Business Development Manager with over 4 years of experience in marketing and business growth strategies. He has a strong background in data analysis, publication marketing, and web-based advertising, and is currently focused on enhancing profitability for Spleen Manufacturing (Pvt) Ltd.",
        "employment_history": [
            {
                "details": "Developing business in Pakistan, USA, and UAE, setting goals and developing plans for business and revenue growth.",
                "end_date": "Present",
                "location": "Lahore/Dubai, UAE",
                "job_title": "Business Development Manager",
                "start_date": "01-2022",
                "company_name": "HappyTanent"
            },
            {
                "details": "Analyzed and reported social media presence, engagement, and effectiveness on all platforms, doubled website traffic.",
                "end_date": "Present",
                "location": "Lahore/Dubai, UAE",
                "job_title": "Social Media Coordinator",
                "start_date": "01-2022",
                "company_name": "Minora Cart"
            },
            {
                "details": "Successfully spearheaded campaigns on social media platforms including Facebook, Twitter, and Instagram.",
                "end_date": "02-2022",
                "location": "Lahore, Pakistan",
                "job_title": "Asst. Manager Marketing",
                "start_date": "10-2018",
                "company_name": "Spleen Manufacturing (Pvt) Ltd"
            }
        ]
    }
}