{
    "output": {
        "justification": [
            "Hassan has extensive experience in business development roles from various companies like HOMI Solutions, DEVBUNCH, etc.",
            "He has managed client engagement and lead generation roles, aligning with the job's requirements.",
            "Project Management was explicitly mentioned as a skill, indicating capability in managing business projects.",
            "No mention of experience using CRM software, crucial for Business Development Manager role."
        ],
        "scores": {
            "macro_scores": [
                {
                    "criteria": "experience",
                    "score": 8
                }
            ],
            "micro_scores": [
                {
                    "criteria": "lead generation",
                    "score": 8
                },
                {
                    "criteria": "market research",
                    "score": 6
                },
                {
                    "criteria": "project management",
                    "score": 7
                }
            ],
            "requirements": [
                {
                    "criteria": "Proven track record in lead generation and client engagement",
                    "meets": true
                }
            ],
            "aggregated_scores": {
                "macro_scores": 8.0,
                "micro_scores": 6.760000000000001
            }
        },
        "personal_info": {
            "name": "Hassan Saeed",
            "email": "hassansaeed3328@gmail.com",
            "phone": "+923053328700",
            "current_position": "Business Development Manager",
            "current_company": "HOMI SOLUTIONS",
            "employment_start_date_current_company": "06-2022",
            "first_company_start_date": "05-2020",
            "urls": []
        },
        "valid_resume_and_jd": true
    },
    "input": {
        "job_description": "### Business Development Manager\n\nJoin **InnovateCorp** as a Business Development Manager to contribute to our growing team and drive strategic initiatives in the technology services sector. The ideal candidate will leverage their extensive experience in business development, client relations, and project management to expand our market presence and build lasting partnerships.\n\n#### Key Responsibilities:\n- Develop and implement strategic business development plans to achieve company goals.\n- Lead generation and relationship building with potential clients.\n- Oversee client acquisition strategies, including exploration beyond freelance markets.\n- Collaborate with cross-functional teams to ensure smooth project delivery.\n- Utilize CRM software for tracking client engagement and development progress.\n- Conduct market research to stay abreast of industry trends and inform business strategies.\n- Manage and report on business development metrics.\n\n#### Skills and Competencies:\n- Strong communication and interpersonal skills for client engagement and collaboration.\n- Excellent analytical abilities to inform proposals and strategic decisions.\n- Experience with Microsoft Office for documentation and presentations.\n- Proficiency in CRM software for managing client relationships.\n\n#### Benefits:\n- Competitive salary with bonus incentives.\n- Opportunities for professional development and career advancement.\n- Health and dental insurance packages.\n- Flexible working hours and a positive, team-oriented environment.",
        "macro_dict": {
            "experience": 100
        },
        "micro_dict": {
            "lead generation": 3,
            "market research": 27,
            "project management": 70
        },
        "additional_info": "InnovateCorp prefers candidates from leading business schools such as COMSATS Institute of Information and Technology. We support relocation for the right candidate and offer remote work opportunities. Skills are assessed through a combination of technical interviews and practical case studies, ensuring candidates meet our high standards of performance before offering a position.",
        "minimum_requirements": [
            "Proven track record in lead generation and client engagement"
        ],
        "resume": "HASSAN SAEED\nBusiness De velopment Manager\nCONTACT\nAddress :Sadiq Abad\nMobile Number :+923053328700\nEmail ID :hassansaeed3328@gmail.com\nDate Of Birth: 02-Sep-1996\nGender :Male\nNationality :Pakistan\nMarital Status:Married\nLanguages:English\nSKILLS\nFreelancing Project Management\nBusiness Development\nREFERENCE\nName :Oneeb Arif\nDetail :InvoZone - Development Lead\nEmail :Oneeb@invozone.com\nMobile :03051234640\nName :Raheel Ahmed\nDetail :CodFelix - Project Manager\nEmail :raheelahmed121@gmail.com\nMobile :03053661152\nWORK EXPERIENCE\nHOMI SOLUTIONS\nBusiness Development Manager\nDuration : 06-2022 - Till Today\nDEVBUNCH\nBusiness Development Team Lead\nDuration : 09-2021 - 06-2022\nLeading Executives and managing all business clients\nINVOZONE\nBusiness Development Executive\nDuration : 03-2021 - 08-2021\nMy core responsibilities was to lock the client from several freelancing platforms,\nCommunication with clients, Follow up the client, Understading project scope, Schedule\nmeeting with Technical person, Manage the lead using slack\nCODFELIX\nBusiness Developer\nDuration : 05-2020 - 02-2021\nSending proposals to the client on Upwork, Respond to client, Non Technical Calls,\nDeveloper's Engagement, Client Locking\nEDUCATION\nBISE BAHAWALPUR\nMTB H/S School, SDK - Matriculation\nGrades - 74 %\nYear of passing : 2011\nPBTE LAHORE\nGCT college, RYK. - Intermediate\nGrades - 75 %\nYear of passing : 2014\nKFUEIT, RYK\n- BS Information Technology\nGrades - 3.00 CGPA\nYear of passing : 2020\nPROJECTS\nCUSTOME MAP API\nBusiness Developer\nDuration : 01-2022 -\nTeam Size - 4\nNFT METAVERSE\nBusiness Developer\nDuration : 01-2022 -\nTeam Size - 4\nACHIEVEMENTS\nMOS 2013\nProject Hunting"
    },
    "details": {
        "name": "Hassan Saeed",
        "number": "923053328700",
        "skills": [
            "Freelancing",
            "Project Management",
            "Business Development"
        ],
        "email_id": "hassansaeed3328@gmail.com",
        "location": "Sadiq Abad",
        "projects": [
            {
                "title": "CUSTOME MAP API",
                "description": "Business Developer"
            },
            {
                "title": "NFT METAVERSE",
                "description": "Business Developer"
            }
        ],
        "education": [
            {
                "end_date": "2011",
                "university": "MTB H/S School, SDK",
                "degree_title": "Matriculation"
            },
            {
                "end_date": "2014",
                "university": "GCT college, RYK",
                "degree_title": "Intermediate"
            },
            {
                "end_date": "2020",
                "university": "KFUEIT, RYK",
                "degree_title": "BS Information Technology"
            }
        ],
        "achievements": [
            "MOS 2013",
            "Project Hunting"
        ],
        "publications": [],
        "certifications": [],
        "additional_urls": [],
        "executive_summary": "Hassan Saeed is a skilled Business Development Manager with extensive experience in freelancing and project management. He has a strong background in business development, having worked with various companies to enhance client engagement and project execution.",
        "employment_history": [
            {
                "details": "Leading Executives and managing all business clients",
                "end_date": "Till Today",
                "location": "",
                "job_title": "Business Development Manager",
                "start_date": "06-2022",
                "company_name": "HOMI SOLUTIONS"
            },
            {
                "details": "Leading Executives and managing all business clients",
                "end_date": "06-2022",
                "location": "",
                "job_title": "Business Development Team Lead",
                "start_date": "09-2021",
                "company_name": "DEVBUNCH"
            },
            {
                "details": "Locking clients from several freelancing platforms, communication with clients, follow up, understanding project scope, scheduling meetings with technical personnel, managing leads using Slack",
                "end_date": "08-2021",
                "location": "",
                "job_title": "Business Development Executive",
                "start_date": "03-2021",
                "company_name": "INVOZONE"
            },
            {
                "details": "Sending proposals to clients on Upwork, responding to clients, non-technical calls, developer's engagement, client locking",
                "end_date": "02-2021",
                "location": "",
                "job_title": "Business Developer",
                "start_date": "05-2020",
                "company_name": "CODFELIX"
            }
        ]
    }
}