{
    "output": {
        "justification": [
            "The resume shows strong leadership with roles like Founder of Al-Maqsad Foundation, managing a team of 20 and engaging with 50 donors.",
            "Relevant experience includes sales and business development roles, though they are relatively short in duration and somewhat limited in strategic planning.",
            "Proposal writing is noted in the resume from the Sales Management Trainee role, aligning with drafting business proposals for clients.",
            "The candidate does not explicitly mention proficiency in CRM tools like Salesforce, indicating a gap in a key job requirement."
        ],
        "scores": {
            "macro_scores": [
                {
                    "criteria": "leadership",
                    "score": 7
                },
                {
                    "criteria": "experience",
                    "score": 6
                }
            ],
            "micro_scores": [
                {
                    "criteria": "proposal writing",
                    "score": 7
                }
            ],
            "requirements": [
                {
                    "criteria": "Strong analytical and strategic planning skills",
                    "meets": false
                },
                {
                    "criteria": "Proficiency in CRM tools like Salesforce or HubSpot",
                    "meets": true
                },
                {
                    "criteria": "Bachelor's degree in Business Administration or related field",
                    "meets": true
                }
            ],
            "aggregated_scores": {
                "macro_scores": 6.73,
                "micro_scores": 7.0
            }
        },
        "personal_info": {
            "name": "MUHAMMAD SHERAZ GUL",
            "email": "muhammad.sheraz.gul301@gmail.com",
            "phone": "+92 304 9760528",
            "current_position": "Sales Coordinator",
            "current_company": "Careem (Uber Inc)",
            "employment_start_date_current_company": "11-2022",
            "first_company_start_date": "09-2021",
            "urls": [
                {
                    "website_name": "LinkedIn",
                    "url": "linkedin.com/in/muhammad-sheraz1/"
                }
            ]
        },
        "valid_resume_and_jd": true
    },
    "input": {
        "job_description": "**Title: Business Development Manager**  \n\n**Company: MarketPros Enterprises**  \n\n**Location: Remote with potential travel to client locations**  \n\n**About Us:**  \nMarketPros Enterprises is a leading global provider of innovative business solutions with the aim of maximizing brand growth. We work with diverse industries to enhance their sales infrastructure and provide unparalleled customer engagement strategies.  \n\n**Role Overview:**  \nAs a Business Development Manager at MarketPros Enterprises, you will be responsible for leading strategic initiatives that drive business growth, increase market share, and strengthen client relationships. You will manage cross-functional teams to implement sales strategies, harness market insights, and drive brand expansion.  \n\n**Key Responsibilities:**  \n- Develop and implement comprehensive business strategies to enhance revenue growth.  \n- Lead a team in executing marketing campaigns and optimizing sales pipelines.  \n- Utilize data analytics tools to produce actionable insights improving overall performance.  \n- Conduct market research to identify industry trends and new business opportunities.  \n- Engage with potential clients via presentations and foster long-term relationships.  \n- Manage CRM systems (Salesforce, HubSpot) to streamline operations and enhance productivity.  \n\n**Preferred Skills:**  \n- Proficiency in strategic planning and market analysis.  \n- Strong leadership skills with proven experience in team development.  \n- Advanced knowledge of CRM software and digital marketing tools.  \n- Excellent communication and negotiation skills.  \n\nJoin us to push the boundaries of business innovation and help us achieve our expansion goals.  \n",
        "macro_dict": {
            "leadership": 73,
            "experience": 27
        },
        "micro_dict": {
            "proposal writing": 100
        },
        "additional_info": "MarketPros Enterprises values diversity in hiring and encourages applications from seasoned business professionals with varied backgrounds. Preferred universities include Ivy League institutions and top business schools. We offer relocation benefits for exceptional candidates and facilitate remote working arrangements. Technical and strategic competencies are assessed through a mix of psychometric evaluations and case study interviews.",
        "minimum_requirements": [
            "Strong analytical and strategic planning skills",
            "Proficiency in CRM tools like Salesforce or HubSpot",
            "Bachelor's degree in Business Administration or related field"
        ],
        "resume": "                                                            MUHAMMAD SHERAZ GUL                       \u2022 +92 304 9760528 \u2022 muhammad.sheraz.gul301@gmail.com \u2022 linkedin.com/in/muhammad-sheraz1/  Education  Lahore University of Management Sciences                                                                                                    BSc. Economics                 (Sep 2017 - May 2022) Relevant courses: Business Communication, Statistics and Data Analysis, Game Theory, Professional Communication Skills, Intro to Programming, Principles of Management, Time Series Economics, Methods and Practice of Impact Evaluation      Professional Experience  Careem (Uber Inc) Sales Coordinator:                                                                                                                                       (Nov 2022 \u2013 Dec 2022) \u2022 Oversaw the Careem for Business operations for 4 key accounts comprising 50+ users across the city. Optimized routes for ride-sharing to reduce costs and commute time. \u2022 Improved customer experience by resolving customer complaints. Liaised with the captains to address any technical issues. Monitored the progress using the Careem Solutions Portal.  Instructor Brandon | Dynatuners Sales Management Trainee:                                                                                                                     (Jan 2022 \u2013 May 2022) \u2022 Drafted business proposals for 4 prospective clients. Collaborated with the developers to provide product demos. \u2022 Shortlisted, interviewed and onboarded 15 Interns. Conducted trainings covering key concepts of B2B Sales including Buyer Personas, Customer Journey Mapping, Product-Market Fit, Competitive Analysis, Sales Flow Charts and Product Lifecycle. Created a Sales Playbook for the team.  PureLogics                                                                                                                                                    Sales Development Intern:                                                                                                                         (Sep 2021 - Oct 2021) \u2022 Generated qualified leads using LinkedIn Sales Navigator, CrunchBase and HubSpot.  Projects  Amal Academy Fellowship Program                                 (May 2021 \u2013 Jul 2021) \u2022 Completed a competitive written application and interview process to be selected from over 4500 applicants for intensive 3-month Fellowship funded by PEPSICO and Stanford University. \u2022 Invested 150 hours in order to develop business skills (e.g. Communication, Leadership, Problem Solving, Teamwork etc.) that will help me make a deeper impact on the job.  Course Project \u2013 Principles of Management              (Sep 2018 \u2013 Dec 2018) \u2022 Collaborated with a team of 5 students to conduct SWOT Analysis of the Sales Model of Nestle. Interviewed the leadership to understand the business dynamics, identify challenges and opportunities.  Extracurricular Experience  Al-Maqsad Foundation     Founder:                                                                                                                                                      (Apr 2022 \u2013 Present) \u2022 Managing a team of 20 core team members to oversee operations including fundraising through social media campaigns, case verification, field visits, updates, record keeping and monthly reports. \u2022 Partnered with 50 donors to generate regular donations to purchase monthly ration for 17 families. \u2022 Raised and disbursed PKR 20 Million for various cases related to education, healthcare, loan repayment and construction.  LUMS Religious Society     Team Member:                                                                                                                                           (Oct 2017 \u2013 May 2018) \u2022 Collaborated with a team of 15 members to conduct weekly sessions for ~300 students at an underprivileged school to deliver lectures and organize activities aiming to develop a better understanding of Islamic teachings and values.   Honors and Awards  LUMS National Outreach Program S                                                                                                     (Aug 2017)  \u2022 Got admitted to LUMS with 120% scholarship on the basis of excellent academic and extracurricular achievements.  Merit Scholarship Award \u2013 Superior Group of Colleges                                                                    (Aug 2015)  \u2022 Awarded 100% Merit Scholarship for Intermediate based on outstanding academic performance in Matriculation.  2nd Position in Inter-school Mathematics Olympiad (ISMO)                                                             (Mar 2011)  \u2022 Achieved 2nd position out of 1600 participants twice in the PakTurk ISMO competition in Peshawar.                                                                                                                                                                      Skills  \u2022 Soft Skills:  Leadership, Problem-solving, Adaptability, Time Management, Teamwork, Written & Verbal Communication \u2022 Hard Skills: B2B Sales, LinkedIn Sales Navigator, CrunchBase, HubSpot, Research, Data Analysis, Microsoft Office (Word, Excel, PowerPoint), Canva, Adobe Photoshop "
    },
    "details": {
        "name": "Muhammad Sheraz Gul",
        "number": "923049760528",
        "skills": [
            "B2B Sales",
            "LinkedIn Sales Navigator",
            "CrunchBase",
            "HubSpot",
            "Research",
            "Data Analysis",
            "Microsoft Office (Word, Excel, PowerPoint)",
            "Canva",
            "Adobe Photoshop"
        ],
        "email_id": "muhammad.sheraz.gul301@gmail.com",
        "location": "",
        "projects": [
            {
                "title": "Amal Academy Fellowship Program",
                "description": "Completed a competitive written application and interview process to be selected from over 4500 applicants for intensive 3-month Fellowship funded by PEPSICO and Stanford University."
            },
            {
                "title": "Course Project \u2013 Principles of Management",
                "description": "Collaborated with a team of 5 students to conduct SWOT Analysis of the Sales Model of Nestle."
            }
        ],
        "education": [
            {
                "end_date": "05-2022",
                "university": "Lahore University of Management Sciences",
                "degree_title": "BSc. Economics"
            }
        ],
        "achievements": [
            "Got admitted to LUMS with 120% scholarship on the basis of excellent academic and extracurricular achievements.",
            "Awarded 100% Merit Scholarship for Intermediate based on outstanding academic performance in Matriculation.",
            "Achieved 2nd position out of 1600 participants twice in the PakTurk ISMO competition in Peshawar."
        ],
        "publications": [],
        "certifications": [],
        "additional_urls": [
            {
                "url": "linkedin.com/in/muhammad-sheraz1/",
                "website_name": "LinkedIn"
            }
        ],
        "executive_summary": "Muhammad Sheraz Gul is a dedicated professional with a strong background in B2B sales and technical proficiency in various software tools. He has demonstrated his ability to manage operations effectively and has been recognized for his academic achievements and competitive selections.",
        "employment_history": [
            {
                "details": "Oversaw the Careem for Business operations for 4 key accounts comprising 50+ users across the city. Optimized routes for ride-sharing to reduce costs and commute time. Improved customer experience by resolving customer complaints. Liaised with the captains to address any technical issues. Monitored the progress using the Careem Solutions Portal.",
                "end_date": "12-2022",
                "location": "",
                "job_title": "Sales Coordinator",
                "start_date": "11-2022",
                "company_name": "Careem (Uber Inc)"
            },
            {
                "details": "Drafted business proposals for 4 prospective clients. Collaborated with the developers to provide product demos. Shortlisted, interviewed and onboarded 15 Interns. Conducted trainings covering key concepts of B2B Sales including Buyer Personas, Customer Journey Mapping, Product-Market Fit, Competitive Analysis, Sales Flow Charts and Product Lifecycle. Created a Sales Playbook for the team.",
                "end_date": "05-2022",
                "location": "",
                "job_title": "Sales Management Trainee",
                "start_date": "01-2022",
                "company_name": "Instructor Brandon | Dynatuners"
            },
            {
                "details": "Generated qualified leads using LinkedIn Sales Navigator, CrunchBase and HubSpot.",
                "end_date": "10-2021",
                "location": "",
                "job_title": "Sales Development Intern",
                "start_date": "09-2021",
                "company_name": "PureLogics"
            }
        ]
    }
}