{
    "output": {
        "justification": [
            "The candidate has multiple years of experience in business development, relevant to the job role, but lacks detail on leadership in cross-functional teams.",
            "Leadership experience is moderate; involved in event management and has managing roles but lacks specific leadership achievements.",
            "Proficient in Salesforce and other CRM tools as indicated, fulfilling key job requirement.",
            "Lacks formal education in business administration; degree is in computer science, which is less relevant to this role."
        ],
        "scores": {
            "macro_scores": [
                {
                    "criteria": "experience",
                    "score": 7
                }
            ],
            "micro_scores": [
                {
                    "criteria": "salesforce",
                    "score": 8
                },
                {
                    "criteria": "crm proficiency",
                    "score": 7
                },
                {
                    "criteria": "market research",
                    "score": 5
                },
                {
                    "criteria": "proposal writing",
                    "score": 6
                },
                {
                    "criteria": "digital marketing",
                    "score": 7
                }
            ],
            "requirements": [
                {
                    "criteria": "Proficiency in CRM tools like Salesforce or HubSpot",
                    "meets": true
                },
                {
                    "criteria": "Bachelor's degree in Business Administration or related field",
                    "meets": false
                }
            ],
            "aggregated_scores": {
                "macro_scores": 7.0,
                "micro_scores": 6.969999999999999
            }
        },
        "personal_info": {
            "name": "Faique Ali Raza",
            "email": "faiquealiraza@gmail.com",
            "phone": "03143631941",
            "current_position": "Business Development Manager",
            "current_company": "Crewlogicx Tech",
            "employment_start_date_current_company": "04-2022",
            "first_company_start_date": "08-2020",
            "urls": [
                {
                    "website_name": "LinkedIn",
                    "url": "linkedin.com/in/FaiqueAliRaza"
                }
            ]
        },
        "valid_resume_and_jd": true
    },
    "input": {
        "job_description": "**Title: Business Development Manager**  \n\n**Company: MarketPros Enterprises**  \n\n**Location: Remote with potential travel to client locations**  \n\n**About Us:**  \nMarketPros Enterprises is a leading global provider of innovative business solutions with the aim of maximizing brand growth. We work with diverse industries to enhance their sales infrastructure and provide unparalleled customer engagement strategies.  \n\n**Role Overview:**  \nAs a Business Development Manager at MarketPros Enterprises, you will be responsible for leading strategic initiatives that drive business growth, increase market share, and strengthen client relationships. You will manage cross-functional teams to implement sales strategies, harness market insights, and drive brand expansion.  \n\n**Key Responsibilities:**  \n- Develop and implement comprehensive business strategies to enhance revenue growth.  \n- Lead a team in executing marketing campaigns and optimizing sales pipelines.  \n- Utilize data analytics tools to produce actionable insights improving overall performance.  \n- Conduct market research to identify industry trends and new business opportunities.  \n- Engage with potential clients via presentations and foster long-term relationships.  \n- Manage CRM systems (Salesforce, HubSpot) to streamline operations and enhance productivity.  \n\n**Preferred Skills:**  \n- Proficiency in strategic planning and market analysis.  \n- Strong leadership skills with proven experience in team development.  \n- Advanced knowledge of CRM software and digital marketing tools.  \n- Excellent communication and negotiation skills.  \n\nJoin us to push the boundaries of business innovation and help us achieve our expansion goals.  \n",
        "macro_dict": {
            "experience": 100
        },
        "micro_dict": {
            "salesforce": 36,
            "crm proficiency": 24,
            "market research": 16,
            "proposal writing": 7,
            "digital marketing": 17
        },
        "additional_info": "MarketPros Enterprises values diversity in hiring and encourages applications from seasoned business professionals with varied backgrounds. Preferred universities include Ivy League institutions and top business schools. We offer relocation benefits for exceptional candidates and facilitate remote working arrangements. Technical and strategic competencies are assessed through a mix of psychometric evaluations and case study interviews.",
        "minimum_requirements": [
            "Proficiency in CRM tools like Salesforce or HubSpot",
            "Bachelor's degree in Business Administration or related field"
        ],
        "resume": " \nFaique Ali Raza House # 392, K Block, Model Town, Lahore, Pakistan 03143631941 linkedin.com/in/FaiqueAliRaza faiquealiraza@gmail.com Profile \u2022 An individual who is focused, honest, team-oriented, deliberate, determined, and most importantly, who makes use of his grey matter. \u2022 Multiple years of experience in Business Development, Sales generation, and Marketing fields. \u2022 Top Rated freelancer on Upwork. \u2022 Hands-on experience in Lead Generation, Email Marketing, Tele-sales, Sales Navigator, Salesforce, Documentation, and CRM. \u2022 1 Year of Experience in Communication and Tele-sales Marketing. \u2022 9+ years of experience in the field of Music and Event Management. Education Work Experience \u2022 Matric | Science | Civil Aviation Authority High School Lahore \u2022 Intermediate | Pre Eng. | Government College Gulberg Lahore \u2022 Bachelor in Computer Science | The University of Lahore  Skills Awards, Achievements and Certifications Data Scraping | Data Extraction | Leads | Emails Upwork | Fiverr | Freelancer | Guru | TopTal  Musician | Production | Live | Studio Recordings  \u2022 Course of Film and Documentary | Hunerkada College of Visual & Performing Arts | Lahore | 2020  \n Production Design for Film and Screen | Australian Film Television and Radio School | 2020 \n National Financial Literacy Program for Youth | National Institute of Banking and Finance (NIBAF)-Pakistan | 2020 \n Certification in Critical Thinking - Master Decision Making & Problem Solving. \n Won many Music Battles across Pakistan. \n Having many certifications in different Activities and Courses.  \u2022 Content Marketing and Advertising | Punjab University | E-Rozgaar | Lahore | 2020 \nSRS | GDD | WBD | Milestones | Timelines \u2022 Business Development Manager | Crewlogicx Tech | Origami Studios | April 2022 \u2013 Cont. \u2022 Business Development & Digital Project Manager | FIRTLE Tech | Part Time | June 2019 \u2013 Cont. \u2022 Business Development Executive | Argon Tech | Lahore | May 2021 - April 2022. \u2022 Business Development Executive | Kodex Technologies | Dec 2020 \u2013 May 2021. \u2022 Business Development Executive | GrowHawk | Aug \u2013 Dec 2020. \u2022 Business Development Executive | Bizzclan | Lahore | May \u2013 Aug 2020. \u2022 Telemarketing Agent | Nixxe Solution | 2019. Business Developer | LinkedIn Specialist | Leads/Sales Generator | Top Rated Upwork Freelancer "
    },
    "details": {
        "name": "Faique Ali Raza",
        "number": "03143631941",
        "skills": [
            "Data Scraping",
            "Data Extraction",
            "Leads",
            "Emails",
            "Salesforce",
            "Documentation",
            "CRM"
        ],
        "email_id": "faiquealiraza@gmail.com",
        "location": "Lahore, Pakistan",
        "projects": [],
        "education": [
            {
                "end_date": "06-2020",
                "university": "Civil Aviation Authority High School Lahore",
                "degree_title": "Matric | Science"
            },
            {
                "end_date": "06-2020",
                "university": "Government College Gulberg Lahore",
                "degree_title": "Intermediate | Pre Eng."
            },
            {
                "end_date": "06-2020",
                "university": "The University of Lahore",
                "degree_title": "Bachelor in Computer Science"
            }
        ],
        "achievements": [
            "Top Rated freelancer on Upwork",
            "Won many Music Battles across Pakistan"
        ],
        "publications": [],
        "certifications": [
            {
                "certification_name": "Course of Film and Documentary",
                "issuing_organization": "Hunerkada College of Visual & Performing Arts",
                "date_of_issuance": "06-2020"
            },
            {
                "certification_name": "Production Design for Film and Screen",
                "issuing_organization": "Australian Film Television and Radio School",
                "date_of_issuance": "06-2020"
            },
            {
                "certification_name": "National Financial Literacy Program for Youth",
                "issuing_organization": "National Institute of Banking and Finance (NIBAF)-Pakistan",
                "date_of_issuance": "06-2020"
            },
            {
                "certification_name": "Content Marketing and Advertising",
                "issuing_organization": "Punjab University | E-Rozgaar",
                "date_of_issuance": "06-2020"
            }
        ],
        "additional_urls": [
            {
                "url": "linkedin.com/in/FaiqueAliRaza",
                "website_name": "LinkedIn"
            }
        ],
        "executive_summary": "Faique Ali Raza is a dedicated professional with extensive experience in business development, sales generation, and marketing. He has a strong technical background in data scraping, lead generation, and CRM systems, complemented by a solid educational foundation in computer science. Faique is recognized as a top-rated freelancer on Upwork and has achieved notable success in music battles across Pakistan.",
        "employment_history": [
            {
                "details": "Business Development Manager responsible for driving sales and managing client relationships.",
                "end_date": "Present",
                "location": "Lahore",
                "job_title": "Business Development Manager",
                "start_date": "04-2022",
                "company_name": "Crewlogicx Tech"
            },
            {
                "details": "Part-time role focusing on business development and digital project management.",
                "end_date": "Present",
                "location": "Lahore",
                "job_title": "Business Development & Digital Project Manager",
                "start_date": "06-2019",
                "company_name": "FIRTLE Tech"
            },
            {
                "details": "Engaged in business development activities to enhance sales and client acquisition.",
                "end_date": "04-2022",
                "location": "Lahore",
                "job_title": "Business Development Executive",
                "start_date": "05-2021",
                "company_name": "Argon Tech"
            },
            {
                "details": "Responsible for generating leads and managing client communications.",
                "end_date": "05-2021",
                "location": "Lahore",
                "job_title": "Business Development Executive",
                "start_date": "12-2020",
                "company_name": "Kodex Technologies"
            },
            {
                "details": "Focused on lead generation and client outreach.",
                "end_date": "12-2020",
                "location": "Lahore",
                "job_title": "Business Development Executive",
                "start_date": "08-2020",
                "company_name": "GrowHawk"
            },
            {
                "details": "Conducted telemarketing and client engagement activities.",
                "end_date": "12-2019",
                "location": "Lahore",
                "job_title": "Telemarketing Agent",
                "start_date": "01-2019",
                "company_name": "Nixxe Solution"
            }
        ]
    }
}