{
    "output": {
        "justification": [
            "Macro scores are based on experience in leadership roles and relevant experience as a Business Development Executive.",
            "Micro scores take into account specific skills like market research and CRM tool proficiency.",
            "The resume did not mention Salesforce or other CRMs specifically, impacting scores related to minimum requirements.",
            "Relevant projects and tools mentioned in the resume do not align specifically with job description requirements for CRM and business strategies."
        ],
        "scores": {
            "macro_scores": [
                {
                    "criteria": "leadership",
                    "score": 6
                },
                {
                    "criteria": "experience",
                    "score": 5
                },
                {
                    "criteria": "strategic planning",
                    "score": 4
                }
            ],
            "micro_scores": [
                {
                    "criteria": "salesforce",
                    "score": 3
                },
                {
                    "criteria": "market research",
                    "score": 6
                }
            ],
            "requirements": [
                {
                    "criteria": "Proficiency in CRM tools like Salesforce or HubSpot",
                    "meets": false
                }
            ],
            "aggregated_scores": {
                "macro_scores": 5.14,
                "micro_scores": 3.9299999999999997
            }
        },
        "personal_info": {
            "name": "Izma Bint-E-Atif",
            "email": "izma.b.atif@gmail.com",
            "phone": "+92 331 0483113",
            "current_position": "Business Development Executive",
            "current_company": "Nextbridge Pvt. Ltd.",
            "employment_start_date_current_company": "01-2021",
            "first_company_start_date": "01-2020",
            "urls": []
        },
        "valid_resume_and_jd": true
    },
    "input": {
        "job_description": "**Title: Business Development Manager**  \n\n**Company: MarketPros Enterprises**  \n\n**Location: Remote with potential travel to client locations**  \n\n**About Us:**  \nMarketPros Enterprises is a leading global provider of innovative business solutions with the aim of maximizing brand growth. We work with diverse industries to enhance their sales infrastructure and provide unparalleled customer engagement strategies.  \n\n**Role Overview:**  \nAs a Business Development Manager at MarketPros Enterprises, you will be responsible for leading strategic initiatives that drive business growth, increase market share, and strengthen client relationships. You will manage cross-functional teams to implement sales strategies, harness market insights, and drive brand expansion.  \n\n**Key Responsibilities:**  \n- Develop and implement comprehensive business strategies to enhance revenue growth.  \n- Lead a team in executing marketing campaigns and optimizing sales pipelines.  \n- Utilize data analytics tools to produce actionable insights improving overall performance.  \n- Conduct market research to identify industry trends and new business opportunities.  \n- Engage with potential clients via presentations and foster long-term relationships.  \n- Manage CRM systems (Salesforce, HubSpot) to streamline operations and enhance productivity.  \n\n**Preferred Skills:**  \n- Proficiency in strategic planning and market analysis.  \n- Strong leadership skills with proven experience in team development.  \n- Advanced knowledge of CRM software and digital marketing tools.  \n- Excellent communication and negotiation skills.  \n\nJoin us to push the boundaries of business innovation and help us achieve our expansion goals.  \n",
        "macro_dict": {
            "leadership": 34,
            "experience": 46,
            "strategic planning": 20
        },
        "micro_dict": {
            "salesforce": 69,
            "market research": 31
        },
        "additional_info": "MarketPros Enterprises values diversity in hiring and encourages applications from seasoned business professionals with varied backgrounds. Preferred universities include Ivy League institutions and top business schools. We offer relocation benefits for exceptional candidates and facilitate remote working arrangements. Technical and strategic competencies are assessed through a mix of psychometric evaluations and case study interviews.",
        "minimum_requirements": [
            "Proficiency in CRM tools like Salesforce or HubSpot"
        ],
        "resume": "IZMA BINT-E-ATIF\nBUSINESS ANALYST\nCritical thinking\nMaintaining confidentiality\nQuality control\nDistribution\nOrganizational skills\nTroubleshooting\nStatistical analysis\nVerbal/virtual communication\nStrong analytical skills\nAssist technical product management\nCircuit designingSKILLS+92 331 0483113\nHouse  No. 530, Block J3, Johar\nTown, Lahore izma.b.atif@gmail.comStrong background working with internal and external clients to gather\nand elicit requirements, provide analysis, assist with creating user\ninterfaces, and develop implementation timelines in agile environment.\nSeeking a challenging opportunity where I will be able to utilize my\nstrong organizational skills, educational background, and ability to work\nwell with people, which will allow me to grow personally and\nprofessionallyCAREER PROFILE\nEXPERIENCES\nNextbridge Pvt. Ltd. \nRed Communication Arts Pvt. Ltd2021 - Present\n2020 - 2021BUSINESS DEVELOPMENT EXECUTIVE\nConduct market analyses for both product lines and the overall\nprofitability of the business\nAssisting with the planning and execution of test plans for integration\nand process testing, including the raising of fault logs.\nDevelop project concepts and maintain optimal workflow.\nStrong communication and interpersonal skills for building meaningful\nrelationships with clients. \nAttention to detail for honing in on each necessary task. \nAdvanced decision-making and problem-solving skills.\nJUNIOR BUSINESS ANALYST\nAnalyze and prioritize client requirements. \nTranslating client requirements into specified project briefs by\nunderstanding software development life cycle.\nWorking directly with users/clients and understanding business problems,\nlaying out solution and presenting back to key stakeholders\nCreating a detailed business analysis, outlining problems, opportunities\nand solutions for a business\nProcess analysis and production of agreed artefact suitable for internal\nuse and/or client review and sign off.EDUCATION\nFASTNUCES2020 - BACHELOR IN\nELECTRICAL ENGINEERING\nQueen Mary College for Women2015 - FSC PRE ENGINEERING\nSacred Heart Convent School2013 - MATRICULATIONBalsamiq \nMatlab \nAuto CAD\nSketchUP \nVisual Studio SOFTWARE \nPROJECTS\n3D PRINTER WITH CARTESIAN MECHANISM (FYP) \nDesigned a 3D printer with Cartesian mechanism using Fused Deposition\nModeling (FDM) technology following Additive Manufacturing Method. \nEnglish\nUrduLANGUAGESMicrosoft Office \nProgramming languages (C++, C, Assembly language,\nOOP) \nSQL \nCircuit designing, PLC\nHOSPITAL MANAGEMENT PROGRAM\nDesigned an OPD (Outdoor Patient Department) code in C++.\nREFERENCES\nCan be furnished upon requirement.Business Development\nBusiness Analysis \nLeadership \nProblem-solving \nNegotiation \nCritical Thinker \nStrong Presentation & Negotiation Skills COMPETENCIES\nTravelling\nSports \nWriting \nWatching MoviesINTERESTS &\nHOBBIES"
    },
    "details": {
        "name": "Izma Bint-e-Atif",
        "number": "923310483113",
        "skills": [
            "Circuit designing",
            "Balsamiq",
            "Matlab",
            "Auto CAD",
            "SketchUP",
            "Visual Studio",
            "C++",
            "C",
            "Assembly language",
            "OOP",
            "SQL",
            "Microsoft Office"
        ],
        "email_id": "izma.b.atif@gmail.com",
        "location": "House No. 530, Block J3, Johar Town, Lahore",
        "projects": [
            {
                "title": "3D Printer with Cartesian Mechanism",
                "description": "Designed a 3D printer with Cartesian mechanism using Fused Deposition Modeling (FDM) technology following Additive Manufacturing Method."
            },
            {
                "title": "Hospital Management Program",
                "description": "Designed an OPD (Outdoor Patient Department) code in C++."
            }
        ],
        "education": [
            {
                "end_date": "06-2020",
                "university": "FASTNUCES",
                "degree_title": "Bachelor in Electrical Engineering"
            },
            {
                "end_date": "06-2015",
                "university": "Queen Mary College for Women",
                "degree_title": "FSC Pre Engineering"
            },
            {
                "end_date": "06-2013",
                "university": "Sacred Heart Convent School",
                "degree_title": "Matriculation"
            }
        ],
        "achievements": [],
        "publications": [],
        "certifications": [],
        "additional_urls": [
            {
                "url": "linkedin.com/in/izma-b-atif",
                "website_name": "LinkedIn"
            }
        ],
        "executive_summary": "Izma Bint-e-Atif is a skilled business analyst with a strong background in electrical engineering and extensive experience in market analysis, project management, and client relations. She has demonstrated proficiency in various technical skills, including programming and software design, and is committed to delivering effective solutions in an agile environment.",
        "employment_history": [
            {
                "details": "Conduct market analyses for both product lines and the overall profitability of the business. Assisting with the planning and execution of test plans for integration and process testing, including the raising of fault logs. Develop project concepts and maintain optimal workflow.",
                "end_date": "Present",
                "location": "Nextbridge Pvt. Ltd.",
                "job_title": "Business Development Executive",
                "start_date": "01-2021",
                "company_name": "Nextbridge Pvt. Ltd."
            },
            {
                "details": "Analyze and prioritize client requirements. Translating client requirements into specified project briefs by understanding software development life cycle. Working directly with users/clients and understanding business problems, laying out solution and presenting back to key stakeholders. Creating a detailed business analysis, outlining problems, opportunities and solutions for a business. Process analysis and production of agreed artefact suitable for internal use and/or client review and sign off.",
                "end_date": "12-2021",
                "location": "Red Communication Arts Pvt. Ltd.",
                "job_title": "Junior Business Analyst",
                "start_date": "01-2020",
                "company_name": "Red Communication Arts Pvt. Ltd."
            }
        ]
    }
}