{
    "output": {
        "justification": [
            "Leadership experience is evident through multiple roles in business development and project management, but specific team leadership examples are not clearly detailed.",
            "Relevant experience in SEO and digital marketing is lacking. More focused on business development and sales, with no explicit SEO strategy context.",
            "No specific mention of SEO strategy development or market analysis skills in the resume.",
            "Team management experience is implied but not explicitly stated. Resume mentions business development roles which typically involve some level of team coordination."
        ],
        "scores": {
            "macro_scores": [
                {
                    "criteria": "leadership",
                    "score": 6
                },
                {
                    "criteria": "experience",
                    "score": 4
                },
                {
                    "criteria": "client relationship management",
                    "score": 7
                }
            ],
            "micro_scores": [
                {
                    "criteria": "seo strategy development",
                    "score": 3
                },
                {
                    "criteria": "team management",
                    "score": 5
                },
                {
                    "criteria": "market analysis",
                    "score": 4
                }
            ],
            "requirements": [
                {
                    "criteria": "3+ years of experience in SEO and digital marketing",
                    "meets": false
                },
                {
                    "criteria": "Master's degree in Business Administration or related field",
                    "meets": false
                },
                {
                    "criteria": "Strong analytical and strategic thinking skills",
                    "meets": true
                }
            ],
            "aggregated_scores": {
                "macro_scores": 6.0,
                "micro_scores": 3.94
            }
        },
        "personal_info": {
            "name": "Faique Ali Raza",
            "email": "faiquealiraza@gmail.com",
            "phone": "03143631941",
            "current_position": "Business Development Manager",
            "current_company": "Crewlogicx Tech",
            "employment_start_date_current_company": "04-2022",
            "first_company_start_date": "2019",
            "urls": [
                {
                    "website_name": "LinkedIn",
                    "url": "linkedin.com/in/FaiqueAliRaza"
                }
            ]
        },
        "valid_resume_and_jd": true
    },
    "input": {
        "job_description": "## Job Title: Sales and SEO Management Specialist  \n\n### Location: Lahore, Pakistan  \n\n### Company: Innovate Digital Solutions Inc.  \n\n### Job Summary:  \nJoin Innovate Digital Solutions Inc. as a Sales and SEO Management Specialist. You will be part of a dynamic team responsible for driving client engagement and ensuring optimal performance in digital marketing strategies. Your role will include managing client relationships, improving SEO strategies, and leading your team to achieve sales targets.  \n\n### Key Responsibilities:  \n- Proactively engage with prospective clients to understand their business needs and provide innovative solutions.  \n- Design and execute SEO strategies in alignment with client\u2019s marketing objectives.  \n- Manage and optimize PPC campaigns to maximize ROI and brand visibility.  \n- Develop and maintain strong client relationships through tailored marketing solutions.  \n- Lead a team to achieve and surpass sales targets while providing exceptional customer service.  \n- Analyze market trends and algorithms to tailor SEO strategies accordingly.  \n- Produce reports that track progress and measure success against KPIs.  \n\n### Ideal Candidate Profile:  \nYou are a skilled sales and marketing professional with strong analytical skills suited to identifying and executing SEO opportunities. You excel at client interactions, possessing the ability to transform potential leads into satisfied clients through strategic and well-executed marketing initiatives. Leadership and team management skills will be pivotal to drive sales and motivate your team.  \n\n### Benefits:  \n- Competitive salary package  \n- Health and wellness benefits  \n- Performance bonuses  \n- Opportunities for career advancement  \n\nJoin us to redefine digital engagement and lead market strategies with agility and innovation.",
        "macro_dict": {
            "leadership": 28,
            "experience": 24,
            "client relationship management": 48
        },
        "micro_dict": {
            "seo strategy development": 42,
            "team management": 36,
            "market analysis": 22
        },
        "additional_info": "Innovate Digital Solutions Inc. prefers candidates from reputable institutions such as [University of Lahore], [Punjab University]. Remote work options are available subject to roles and responsibilities. We assess skills through a combination of technical tests, interviews, and real-world problem-solving scenarios to gauge practical competency in strategic marketing contexts.",
        "minimum_requirements": [
            "3+ years of experience in SEO and digital marketing",
            "Master's degree in Business Administration or related field",
            "Strong analytical and strategic thinking skills"
        ],
        "resume": " \nFaique Ali Raza House # 392, K Block, Model Town, Lahore, Pakistan 03143631941 linkedin.com/in/FaiqueAliRaza faiquealiraza@gmail.com Profile \u2022 An individual who is focused, honest, team-oriented, deliberate, determined, and most importantly, who makes use of his grey matter. \u2022 Multiple years of experience in Business Development, Sales generation, and Marketing fields. \u2022 Top Rated freelancer on Upwork. \u2022 Hands-on experience in Lead Generation, Email Marketing, Tele-sales, Sales Navigator, Salesforce, Documentation, and CRM. \u2022 1 Year of Experience in Communication and Tele-sales Marketing. \u2022 9+ years of experience in the field of Music and Event Management. Education Work Experience \u2022 Matric | Science | Civil Aviation Authority High School Lahore \u2022 Intermediate | Pre Eng. | Government College Gulberg Lahore \u2022 Bachelor in Computer Science | The University of Lahore  Skills Awards, Achievements and Certifications Data Scraping | Data Extraction | Leads | Emails Upwork | Fiverr | Freelancer | Guru | TopTal  Musician | Production | Live | Studio Recordings  \u2022 Course of Film and Documentary | Hunerkada College of Visual & Performing Arts | Lahore | 2020  \n Production Design for Film and Screen | Australian Film Television and Radio School | 2020 \n National Financial Literacy Program for Youth | National Institute of Banking and Finance (NIBAF)-Pakistan | 2020 \n Certification in Critical Thinking - Master Decision Making & Problem Solving. \n Won many Music Battles across Pakistan. \n Having many certifications in different Activities and Courses.  \u2022 Content Marketing and Advertising | Punjab University | E-Rozgaar | Lahore | 2020 \nSRS | GDD | WBD | Milestones | Timelines \u2022 Business Development Manager | Crewlogicx Tech | Origami Studios | April 2022 \u2013 Cont. \u2022 Business Development & Digital Project Manager | FIRTLE Tech | Part Time | June 2019 \u2013 Cont. \u2022 Business Development Executive | Argon Tech | Lahore | May 2021 - April 2022. \u2022 Business Development Executive | Kodex Technologies | Dec 2020 \u2013 May 2021. \u2022 Business Development Executive | GrowHawk | Aug \u2013 Dec 2020. \u2022 Business Development Executive | Bizzclan | Lahore | May \u2013 Aug 2020. \u2022 Telemarketing Agent | Nixxe Solution | 2019. Business Developer | LinkedIn Specialist | Leads/Sales Generator | Top Rated Upwork Freelancer "
    },
    "details": {
        "name": "Faique Ali Raza",
        "number": "03143631941",
        "skills": [
            "Data Scraping",
            "Data Extraction",
            "Leads",
            "Emails",
            "Salesforce",
            "Documentation",
            "CRM"
        ],
        "email_id": "faiquealiraza@gmail.com",
        "location": "Lahore, Pakistan",
        "projects": [],
        "education": [
            {
                "end_date": "06-2020",
                "university": "Civil Aviation Authority High School Lahore",
                "degree_title": "Matric | Science"
            },
            {
                "end_date": "06-2020",
                "university": "Government College Gulberg Lahore",
                "degree_title": "Intermediate | Pre Eng."
            },
            {
                "end_date": "06-2020",
                "university": "The University of Lahore",
                "degree_title": "Bachelor in Computer Science"
            }
        ],
        "achievements": [
            "Top Rated freelancer on Upwork",
            "Won many Music Battles across Pakistan"
        ],
        "publications": [],
        "certifications": [
            {
                "certification_name": "Course of Film and Documentary",
                "issuing_organization": "Hunerkada College of Visual & Performing Arts",
                "date_of_issuance": "06-2020"
            },
            {
                "certification_name": "Production Design for Film and Screen",
                "issuing_organization": "Australian Film Television and Radio School",
                "date_of_issuance": "06-2020"
            },
            {
                "certification_name": "National Financial Literacy Program for Youth",
                "issuing_organization": "National Institute of Banking and Finance (NIBAF)-Pakistan",
                "date_of_issuance": "06-2020"
            },
            {
                "certification_name": "Content Marketing and Advertising",
                "issuing_organization": "Punjab University | E-Rozgaar",
                "date_of_issuance": "06-2020"
            }
        ],
        "additional_urls": [
            {
                "url": "linkedin.com/in/FaiqueAliRaza",
                "website_name": "LinkedIn"
            }
        ],
        "executive_summary": "Faique Ali Raza is a dedicated professional with extensive experience in business development, sales generation, and marketing. He has a strong technical background in data scraping, lead generation, and CRM systems, complemented by a solid educational foundation in computer science. Faique is recognized as a top-rated freelancer on Upwork and has achieved notable success in music battles across Pakistan.",
        "employment_history": [
            {
                "details": "Business Development Manager responsible for driving sales and managing client relationships.",
                "end_date": "Present",
                "location": "Lahore",
                "job_title": "Business Development Manager",
                "start_date": "04-2022",
                "company_name": "Crewlogicx Tech"
            },
            {
                "details": "Part-time Business Development & Digital Project Manager overseeing project execution and client engagement.",
                "end_date": "Present",
                "location": "Lahore",
                "job_title": "Business Development & Digital Project Manager",
                "start_date": "06-2019",
                "company_name": "FIRTLE Tech"
            },
            {
                "details": "Business Development Executive focused on generating leads and closing sales.",
                "end_date": "04-2022",
                "location": "Lahore",
                "job_title": "Business Development Executive",
                "start_date": "05-2021",
                "company_name": "Argon Tech"
            },
            {
                "details": "Business Development Executive responsible for client acquisition and relationship management.",
                "end_date": "05-2021",
                "location": "Lahore",
                "job_title": "Business Development Executive",
                "start_date": "12-2020",
                "company_name": "Kodex Technologies"
            },
            {
                "details": "Business Development Executive tasked with lead generation and sales strategies.",
                "end_date": "12-2020",
                "location": "Lahore",
                "job_title": "Business Development Executive",
                "start_date": "08-2020",
                "company_name": "GrowHawk"
            },
            {
                "details": "Telemarketing Agent engaged in direct sales and customer outreach.",
                "end_date": "12-2019",
                "location": "Lahore",
                "job_title": "Telemarketing Agent",
                "start_date": "01-2019",
                "company_name": "Nixxe Solution"
            }
        ]
    }
}