{
    "output": {
        "justification": [
            "The candidate shows substantial leadership skills through roles such as Business Development Manager and board roles at ISA.",
            "The resume shows 9+ years of experience, which aligns well with the requirement of 5+ years, although the sector exposure is indirect for the job description.",
            "The candidate has not explicitly mentioned experience with Vistex, which is crucial for scoring in micro criteria appropriately.",
            "The candidate has substantial experience in using CRM systems, but specific mention of SAP and Salesforce is missing. However, general CRM experience can be inferred."
        ],
        "scores": {
            "macro_scores": [
                {
                    "criteria": "leadership",
                    "score": 9
                },
                {
                    "criteria": "experience",
                    "score": 8
                },
                {
                    "criteria": "strategic thinking",
                    "score": 7
                }
            ],
            "micro_scores": [
                {
                    "criteria": "vistex",
                    "score": 0
                }
            ],
            "requirements": [
                {
                    "criteria": "Experience with CRM and ERP systems such as SAP and Salesforce",
                    "meets": false
                },
                {
                    "criteria": "5+ years of experience in sales or key account management",
                    "meets": true
                },
                {
                    "criteria": "Bachelor's degree in Business Administration or related field",
                    "meets": true
                },
                {
                    "criteria": "Proficiency in data analysis and forecasting tools",
                    "meets": false
                }
            ],
            "aggregated_scores": {
                "macro_scores": 7.65,
                "micro_scores": 0.0
            }
        },
        "personal_info": {
            "name": "Yahya Malik",
            "email": "yahyamalik1@outlook.com",
            "phone": "+971504680678",
            "current_position": "Business Development Manager",
            "current_company": "ACET Solutions",
            "employment_start_date_current_company": "06-2021",
            "first_company_start_date": "01-2015",
            "urls": [
                {
                    "website_name": "LinkedIn",
                    "url": "www.linkedin.com/in/engryahyamalik"
                }
            ]
        },
        "valid_resume_and_jd": true
    },
    "input": {
        "job_description": "### Key Account Manager at LuxoTech Solutions\n\n**Location:** Karachi, Pakistan\n\n**Department:** Sales and Marketing\n\n**Reports to:** Director of Sales\n\n**Role Overview:**\nJoin LuxoTech Solutions as a Key Account Manager where you will be responsible for managing major accounts in the Retail & Hospitality segments across Pakistan. You will drive sales growth by managing existing accounts and developing strategies for new accounts. Your role will involve coordinating with cross-functional teams, analyzing market trends, and leading initiatives to meet revenue targets.\n\n#### Responsibilities:\n- Manage a portfolio of 15+ key accounts, comprising both end-users and channel partners.\n- Drive expansion into new market segments by identifying and engaging with potential leads.\n- Develop and execute account management strategies to achieve 110% target attainment in revenue.\n- Utilize data analysis tools such as Power BI to assess market trends and generate insights.\n- Coordinate with internal teams including marketing and operations to ensure strategic alignment.\n- Lead contract negotiations and manage pricing strategies to optimize profitability.\n- Report on account performance and market opportunities to senior management regularly.\n\n#### Essential Skills:\n- Strong leadership and stakeholder management skills.\n- Proficiency in data analysis and forecasting to inform decision-making.\n- Experience with tools such as Salesforce, Vistex, and SAP ERP for managing sales functions.\n- Excellent communication skills for client interactions and internal collaborations.\n\n#### Qualifications:\n- Master's degree preferred; Bachelor's degree in Business Administration or related field is required.\n- 5+ years of experience in sales management or business development, with a focus on key account management.\n- Demonstrated success in growing accounts and achieving revenue targets.\n\n#### Benefits:\n- Competitive salary with performance bonuses.\n- Professional development opportunities and access to industry seminars.\n- Flexible working hours.",
        "macro_dict": {
            "leadership": 25,
            "experience": 15,
            "strategic thinking": 60
        },
        "micro_dict": {
            "vistex": 100
        },
        "additional_info": "LuxoTech Solutions values diversity and seeks candidates from a variety of backgrounds and experiences. Preferred institutions include the Institute of Business Administration, Karachi, and FAST NUCES. The company supports hybrid work arrangements and offers relocation assistance for exceptional candidates. Skills are assessed through a combination of technical tests, case studies, and structured interviews with panel members from various departments.",
        "minimum_requirements": [
            "Experience with CRM and ERP systems such as SAP and Salesforce",
            "5+ years of experience in sales or key account management",
            "Bachelor's degree in Business Administration or related field",
            "Proficiency in data analysis and forecasting tools"
        ],
        "resume": "\u00a0 \u00a0\nContact\nDubai,United Arab Emirates \nUAE Number: +971504680678\nPAK Number: +923108141420\nKSA Number: +966546978135\nyahyamalik1@outlook.com\nwww.linkedin.com/in/\nengryahyamalik  (LinkedIn)\nTop Skills\nAutomation\nInstrumentation\nOT Cyber Security\nLanguages\nEnglish  (Professional Working)\nCertifications\nISA 62443 Cybersecurity\nFundamentals Specialist\nNSE 1,2,3 Network Security\nAssociate\nNozomi Certified Sales Professional\n(NNCTSP) \nIELTS General \nHoneywell Certified Sales\nProfessional on Process Control\nSystems\nHonors-Awards\nOrganizer - Annual Technical\nConference 2017\nOrganizer - POGEE 2018\nOrganizer-OT Cybersecurity\nImplementation Conference by ISA\nOrganizer-Cybersecurity for Critical\nAssets MENA\nEmployee of the Month AwardYahya M.\nBusiness Development Manager | Sales Leader | Industrial\nAutomation | Account Manager | OT Cybersecurity ISA 62443 CFS\n| Digital Transformation | IT/OT Integration | Closed Multimillion $\nProjects in last 5 years\nDubai, United Arab Emirates\nSummary\nyahyamalik1@outlook.com \nYahya Malik is a Seasoned Engineer-turned Marketer, with 9+\nyears of diverse experience in the field of B2B Sales, Negotiation,\nCustomer Relations Management, Product Management Process\nAutomation & OT Cybersecurity with a keen interest in IIOT.\nWorked with Industry leaders such as Nozomi Networks, Palo Alto,\nFortinet, ABB, Rockwell Automation, Yokogawa, Honeywell, General\nMonitors, Trend Micro, TXOne & Schneider. Creating win to win\nstrategy for my organization and for my customers as well\nCurrently, I am working as Business Development Manager at ACET\nSolutions. Here, we are not only helping enterprises with our OT and\nICS solutions but also helping them secure their digital infrastructure\nthrough our in-depth cybersecurity practices. With deep expertise in\nmature and emerging OT/IT means, we are helping various verticals\nautomate their processes, secure their infrastructure, and enhance\noperational productivity\nMy forte ranging from Lead Generation, Market Research, Business\nDevelopment, International Sales, Key Accounts Management, Sales\nOperations, Sales Strategy, Product Management, New Business\nDevelopment and Customer Satisfaction\nFundamental understanding of OT/ICS Cyber security basics and\nmodern concepts related to;\n-Firewalls, Intrusion detection and prevention, DMZ's, Remote\nAccess Solutions \n-Data leakage prevention\n-Secure Cloud, Data security, Security operations tools,\n\u00a0 Page 1 of 3\u00a0 \u00a0\n-ISA 62443 & Other OT Cybersecurity Standards\nTechnologies: \nIndustrial Automation | Industry 4.0 | Industrial IOT | IT/OT\nIntegration | Enterprise Management System | Data Historian &\ncloud | Cybersecurity | SCADA | Solar | Electrical | Instrumentation |\nRenewable Energy | \nIndustry Verticals:\nOil & Gas | Process | Utilities & Power | Metals | FMCG\nGeographies:\nPakistan | GCC | West Africa | Singapore | USA\nClients: \nFortune 100 | Government | EPCs | OEMs \nFunctional Competencies: \nStrategy Planning & Execution | Product and Solutions Proposals\n| P&L Management | Key Account Management | Negotiations\n| Business Development | Customer Relationship Management\n| Competitive Analysis | Solution & Services Sales Demand\nGeneration | Brand Positioning | Strategic Alliances & Partnerships |\nDigital transformation | Control Systems (PLC,DCS,SCADA) | EPC\nConnect with Yahya:\nWatsapp UAE: +971 50 468 0678\nWatsapp KSA: +966 54 697 8135\nWatsapp PAK: +92 310 814 1420 \nOfficial Email ID: yahya.malik@acetsolutions.com\nExperience\nACET Solutions\nBusiness Development Manager\nJune 2021\u00a0-\u00a0Present\u00a0 (2 years)\nUnited Arab Emirates\n\u00a0 Page 2 of 3\u00a0 \u00a0\n-Looking after Sales and Business Development of Automation, OT\nCybersecurity & Digital Enterprise Technology solutions in Pakistan & Middle\nEast Market\nInternational Society of Automation (ISA)\n2 years 5 months\nPresident Elect\nOctober 2022\u00a0-\u00a0Present\u00a0 (8 months)\nBoard Member (Webinars & Seminars)\nJanuary 2021\u00a0-\u00a0October 2022\u00a0 (1 year 10 months)\nDescon\nBusiness Development Manager\nNovember 2017\u00a0-\u00a0May 2021\u00a0 (3 years 7 months)\nUnited Arab Emirates\nLean Automation\nDesign Application Engineer\nJanuary 2016\u00a0-\u00a0October 2017\u00a0 (1 year 10 months)\nUnited Arab Emirates\nCoca-Cola Beverages Pakistan Limited\nGraduate Management Trainee\nJanuary 2015\u00a0-\u00a0December 2015\u00a0 (1 year)\nPakistan\nEducation\nLahore University of Management Sciences\nArt of Selling Ideas-Advertising 101,\u00a0Print, Outdoor and Digital\nMarketing \u00a0\u00b7\u00a0(March 2021)\nNEBOSH\nNebosh International General Certificate in Occupational Health and\nSafety,\u00a0Occupational Health and Safety \u00a0\u00b7\u00a0(January 2021)\nCOMSATS University\nEngineer\u2019s Degree,\u00a0Electrical and Electronics Engineering \u00a0\u00b7\u00a0(2010)\n\u00a0 Page 3 of 3"
    },
    "details": {
        "name": "Yahya Malik",
        "number": "971504680678",
        "skills": [
            "Automation",
            "Instrumentation",
            "OT Cyber Security",
            "Industrial Automation",
            "Industry 4.0",
            "Industrial IOT",
            "IT/OT Integration",
            "Enterprise Management System",
            "Data Historian & cloud",
            "Cybersecurity",
            "SCADA",
            "Solar",
            "Electrical",
            "Instrumentation",
            "Renewable Energy"
        ],
        "email_id": "yahyamalik1@outlook.com",
        "location": "Dubai, United Arab Emirates",
        "projects": [],
        "education": [
            {
                "end_date": "03-2021",
                "university": "Lahore University of Management Sciences",
                "degree_title": "Art of Selling Ideas-Advertising 101, Print, Outdoor and Digital Marketing"
            },
            {
                "end_date": "01-2021",
                "university": "NEBOSH",
                "degree_title": "Nebosh International General Certificate in Occupational Health and Safety"
            },
            {
                "end_date": "2010",
                "university": "COMSATS University",
                "degree_title": "Engineer\u2019s Degree, Electrical and Electronics Engineering"
            }
        ],
        "achievements": [
            "Organizer - Annual Technical Conference 2017",
            "Organizer - POGEE 2018",
            "Organizer - OT Cybersecurity Implementation Conference by ISA",
            "Organizer - Cybersecurity for Critical Assets MENA",
            "Employee of the Month Award"
        ],
        "publications": [],
        "certifications": [
            {
                "certification_name": "ISA 62443 Cybersecurity Fundamentals Specialist",
                "issuing_organization": "ISA",
                "date_of_issuance": "01-2021"
            },
            {
                "certification_name": "NSE 1,2,3 Network Security Associate",
                "issuing_organization": "Fortinet",
                "date_of_issuance": "01-2021"
            },
            {
                "certification_name": "Nozomi Certified Sales Professional (NNCTSP)",
                "issuing_organization": "Nozomi Networks",
                "date_of_issuance": "01-2021"
            },
            {
                "certification_name": "IELTS General",
                "issuing_organization": "British Council",
                "date_of_issuance": "01-2021"
            },
            {
                "certification_name": "Honeywell Certified Sales Professional on Process Control Systems",
                "issuing_organization": "Honeywell",
                "date_of_issuance": "01-2021"
            }
        ],
        "additional_urls": [
            {
                "url": "linkedin.com/in/engryahyamalik",
                "website_name": "LinkedIn"
            }
        ],
        "executive_summary": "Yahya Malik is a seasoned engineer-turned marketer with over 9 years of diverse experience in B2B sales, negotiation, customer relations management, product management, process automation, and OT cybersecurity. He has worked with industry leaders and is currently a Business Development Manager at ACET Solutions, focusing on automation and cybersecurity solutions. His expertise includes lead generation, market research, and digital transformation, making him a valuable asset in enhancing operational productivity across various sectors.",
        "employment_history": [
            {
                "details": "Looking after Sales and Business Development of Automation, OT Cybersecurity & Digital Enterprise Technology solutions in Pakistan & Middle East Market",
                "end_date": "Present",
                "location": "United Arab Emirates",
                "job_title": "Business Development Manager",
                "start_date": "06-2021",
                "company_name": "ACET Solutions"
            },
            {
                "details": "President Elect and Board Member (Webinars & Seminars)",
                "end_date": "Present",
                "location": "United Arab Emirates",
                "job_title": "President Elect",
                "start_date": "10-2022",
                "company_name": "International Society of Automation (ISA)"
            },
            {
                "details": "Business Development Manager",
                "end_date": "05-2021",
                "location": "United Arab Emirates",
                "job_title": "Business Development Manager",
                "start_date": "11-2017",
                "company_name": "Descon"
            },
            {
                "details": "Design Application Engineer",
                "end_date": "10-2017",
                "location": "United Arab Emirates",
                "job_title": "Design Application Engineer",
                "start_date": "01-2016",
                "company_name": "Lean Automation"
            },
            {
                "details": "Graduate Management Trainee",
                "end_date": "12-2015",
                "location": "Pakistan",
                "job_title": "Graduate Management Trainee",
                "start_date": "01-2015",
                "company_name": "Coca-Cola Beverages Pakistan Limited"
            }
        ]
    }
}