{
    "output": {
        "justification": [
            "The candidate has relevant experience as a Business Development Officer and Account Executive which relates to lead generation and client management.",
            "While the candidate has years of business-related roles, there\u2019s a lack of direct evidence of BI tools experience like Power BI or Tableau.",
            "The candidate does not possess desired programming skills in C++, HTML, or CSS.",
            "The candidate's education does not align with the preferred institutions per company preferences."
        ],
        "scores": {
            "macro_scores": [
                {
                    "criteria": "innovation and adaptability",
                    "score": 5
                }
            ],
            "micro_scores": [
                {
                    "criteria": "c++, html, css",
                    "score": 2
                }
            ],
            "requirements": [
                {
                    "criteria": "3+ years of experience in lead generation or business intelligence",
                    "meets": true
                }
            ],
            "aggregated_scores": {
                "macro_scores": 5.0,
                "micro_scores": 2.0
            }
        },
        "personal_info": {
            "name": "Umer Saleem",
            "email": "umersaleemzaman1308@gmail.com",
            "phone": "+923475130731",
            "current_position": "Account Executive",
            "current_company": "Keep Truckin",
            "employment_start_date_current_company": "11-2021",
            "first_company_start_date": "07-2020",
            "urls": [
                {
                    "website_name": "LinkedIn",
                    "url": "linkedin.com/in/umersaleemzaman/"
                }
            ]
        },
        "valid_resume_and_jd": true
    },
    "input": {
        "job_description": "## Lead Generation and Business Intelligence Specialist\n\nJoin **Innovate Connections Inc.** as a Lead Generation and Business Intelligence Specialist. You will play a pivotal role in driving business growth by spearheading lead generation initiatives and providing strategic insights through data analytics. We are looking for a highly skilled professional with a strong background in lead generation, data management, and business intelligence.\n\n### Key Responsibilities:\n- Develop and execute lead generation strategies using digital marketing techniques, cold calling, and data scraping tools.\n- Collaborate with cross-functional teams to optimize customer acquisition strategies.\n- Utilize CRM systems to manage and analyze client data for lead qualification.\n- Create and manage detailed project schedules and work plans, utilizing best practices and standards for project execution.\n- Develop financial models and business growth strategies based on data insights.\n- Utilize tools such as Power BI, SQL, and Tableau for developing comprehensive data reports and dashboards.\n\n### Desired Skills and Experience:\n- Strong programming skills in C++, HTML, and CSS.\n- Proficiency in digital marketing, email marketing, and social media platforms.\n- Experience in managing large data sets and using BI tools (Power BI, Excel, Tableau).\n- Excellent communication skills and ability to develop strong client relationships.\n- Ability to work independently and manage multiple projects simultaneously.\n\n### Why Innovate Connections Inc.?\n- We innovate at the forefront of technology and enable our team members to grow alongside the company.\n- We value data-driven decision-making and empower our teams with the right tools to succeed.\n- Offering a supportive work environment and opportunities for career advancement.\n\n### How to Apply:\nSubmit your resume and cover letter detailing your relevant experience and why you are interested in joining Innovate Connections Inc.",
        "macro_dict": {
            "innovation and adaptability": 100
        },
        "micro_dict": {
            "c++, html, css": 100
        },
        "additional_info": "Innovate Connections Inc. prefers candidates from recognized universities such as the University of Management & Technology and Lahore School of Economics. We encourage a remote working environment but require physical presence for team-building and strategic sessions twice a quarter. Relocation assistance is available for exceptional candidates. Our comprehensive assessment includes a technical test followed by structured interviews to evaluate both technical and soft skills comprehensively.",
        "minimum_requirements": [
            "3+ years of experience in lead generation or business intelligence"
        ],
        "resume": "LANGUAGES SPOKENProspecting, Qualifying, Sales Pipeline Development.\nProduct Demonstrations.\nProduct Owner.\nLead generation and fostering them: Generate the new lead and\nfoster them.\nExamine the requirement of the customer and, maintaining the\ndocuments of requirement.\nSales prospects, maintaining healthy prospects of sales. Acting as a\nliaison between the development team and the business team,\nstaying connected with the Client.\nMonthly demonstration of MVPs to the Clients.\nCold Calling - Cold Emailing: Reaching new clients and taking follow-\nups for future prospects.\nInitiating the relationship with the healthy prospects through\nLinkedIn.\nProduct demonstrations to the clients after setting successful\nmeetings.\nSenior Customer Support Specialist Hired Support | July 2020 - Jan\n2021\nI have joined Hired Support as a Senior Customer Support Specialist\nto foster my written skills.\nReceive and Promptly Respond to Customer Queries.\nDocument Issues and Resolutions.\nLearn About New Products and Services.Keep Truckin\nAccount Executive | Nov 2021 - Present\nViral Square\nBusiness Development Officer | Feb 2021- Nov 2021\nHired Support\nUniversity Of Central Punjab\nMasters of Business Administration 2021 - Present\nI have started my Masters Of Business Administration from the University\nof Central Punjab to foster my expertise even more as per need of the\nmarket, to better understand Sales prospects.\nHazara University\nBachelors of Business Administration 2014 - 2018\nI have done my Bachelors from the University of Hazara securing colorful\ngrades, chose Finance as my major area of research.WORK EXPERIENCE\nEDUCATION HIGHLIGHTSMobile: +923475130731\numersaleemzaman1308@gmail.com\nlinkedin.com/in/umersaleemzaman/ \nJohar Town, Lahore, PakistanUMER SALEEM\nBUSINESS DEVELOPMENT OFFICER\nExperienced Business\nDevelopment & Client\nExecutive with a\ndemonstrated history of\nworking as a sales liaison\nbetween the customer and the\nCompany. I have acuminated\nskills in Client Management,\nRequirement Gathering, and\nConvincing potential\nCustomers, a think-thank who\ndrives execution, highly\nknowledgeable in a wide\nvariety of professional\ndisciplines that maximize\nbrand growth including\nfinance, marketing, and all\nfacets of business operations\nfrom product development to\ncustomer engagement.EXECUTIVE SUMMARY\nLead Generation\nSalesFroce\nSalsLoft\nMicrosoft Office\nZendesk\nTawlk.to\nSales Pipeline\nSales Development\nProduct DemonstrationsSKILLS\nENGLISH\nURDU \nHINDI\n "
    },
    "details": {
        "name": "Umer Saleem",
        "number": "923475130731",
        "skills": [
            "Lead Generation",
            "SalesFroce",
            "SalsLoft",
            "Microsoft Office",
            "Zendesk",
            "Tawlk.to",
            "Sales Pipeline",
            "Sales Development",
            "Product Demonstrations"
        ],
        "email_id": "umersaleemzaman1308@gmail.com",
        "location": "Johar Town, Lahore, Pakistan",
        "projects": [],
        "education": [
            {
                "end_date": "12-2021",
                "university": "University Of Central Punjab",
                "degree_title": "Masters of Business Administration"
            },
            {
                "end_date": "05-2018",
                "university": "Hazara University",
                "degree_title": "Bachelors of Business Administration"
            }
        ],
        "achievements": [],
        "publications": [],
        "certifications": [],
        "additional_urls": [
            {
                "url": "linkedin.com/in/umersaleemzaman/",
                "website_name": "LinkedIn"
            }
        ],
        "executive_summary": "Umer Saleem is an experienced Business Development Officer with a strong background in client management and sales. He has demonstrated expertise in lead generation, product demonstrations, and maintaining healthy sales prospects, effectively acting as a liaison between customers and the company.",
        "employment_history": [
            {
                "details": "Acting as a liaison between the development team and the business team, staying connected with the Client. Monthly demonstration of MVPs to the Clients. Cold Calling - Cold Emailing: Reaching new clients and taking follow-ups for future prospects.",
                "end_date": "Present",
                "location": "",
                "job_title": "Account Executive",
                "start_date": "11-2021",
                "company_name": "Keep Truckin"
            },
            {
                "details": "Fostering written skills and responding to customer queries promptly. Documenting issues and resolutions.",
                "end_date": "01-2021",
                "location": "",
                "job_title": "Senior Customer Support Specialist",
                "start_date": "07-2020",
                "company_name": "Hired Support"
            },
            {
                "details": "Responsible for business development and client management, focusing on generating new leads and maintaining relationships with prospects.",
                "end_date": "11-2021",
                "location": "",
                "job_title": "Business Development Officer",
                "start_date": "02-2021",
                "company_name": "Viral Square"
            }
        ]
    }
}