{
    "output": {
        "justification": [
            "The resume does not align with the job description for a Business Development Manager.",
            "The candidate's education and experience focus on Electrical Engineering, which is unrelated to business development.",
            "Key skills such as digital marketing, CRM tool proficiency, and business analytics expertise are missing.",
            "The role's requirements for sales and negotiation experience are not addressed in the resume."
        ],
        "scores": {
            "macro_scores": [
                {
                    "criteria": "business development experience",
                    "score": 0
                }
            ],
            "micro_scores": [
                {
                    "criteria": "data analysis",
                    "score": 0
                }
            ],
            "requirements": [
                {
                    "criteria": "Strong understanding of sales processes and negotiation skills",
                    "meets": false
                },
                {
                    "criteria": "Bachelor's degree in Business Administration or related field",
                    "meets": false
                },
                {
                    "criteria": "5+ years of business development experience in a leadership role",
                    "meets": false
                },
                {
                    "criteria": "Proficiency in business analytics and digital strategy",
                    "meets": false
                }
            ],
            "aggregated_scores": {
                "macro_scores": 0.0,
                "micro_scores": 0.0
            }
        },
        "personal_info": {
            "name": "Hasan Bin Zulfiqar",
            "email": "hasanbinzulfiqar@gmail.com",
            "phone": "0301-5138489",
            "current_position": "Electrical Engineer",
            "current_company": "",
            "employment_start_date_current_company": "",
            "first_company_start_date": "07-2023",
            "urls": [
                {
                    "website_name": "LinkedIn",
                    "url": "https://rb.gy/rnnsby"
                }
            ]
        },
        "valid_resume_and_jd": false
    },
    "input": {
        "job_description": "**Business Development Manager**  \nJoin [Fictional Company] as a Business Development Manager, where you will lead strategies for expanding our market presence. Responsibilities include driving sales growth, developing key client relationships, and implementing innovative solutions to improve efficiencies using data-driven insights.\n\n**Key Responsibilities:**\n\n- Identify new business opportunities and potential clients through market research and networking.\n- Develop strategies to enhance business processes, improve workflows, and maximize operational efficiency.\n- Work collaboratively with senior management to provide strategic recommendations based on market analysis.\n- Lead and mentor a team of business development professionals, focusing on achieving company sales targets.\n- Engage in high-stakes negotiation and strategy discussions with existing and potential partners.\n\n**Preferred Skills:**\n\n- Proficiency in business analytics tools like GA4 and Power BI.\n- Strong capability in digital marketing strategies including SEO and influencer marketing.\n- Expertise in using CRM tools such as JIRA and Asana.\n\n**Our Ideal Candidate:**\n\nYou are proactive, strategic, and data-oriented with a firm background in business development and a passion for driving sales excellence. You are eager to lead and inspire a team while focusing on achieving ambitious growth targets.\n\nJoin us and be a part of a collaborative environment driving innovation and success.\n\n[Apply Now]",
        "macro_dict": {
            "business development experience": 100
        },
        "micro_dict": {
            "data analysis": 100
        },
        "additional_info": "[Fictional Company] values candidates from top-tier universities such as [University A] and [University B]. We support diversity and inclusion in our hiring processes. Relocation assistance is provided on a case-by-case basis. We assess skills through a combination of technical interviews, case studies, and practical tests to ensure the candidate\u2019s fitment with the organizational culture and job requirements.",
        "minimum_requirements": [
            "Strong understanding of sales processes and negotiation skills",
            "Bachelor's degree in Business Administration or related field",
            "5+ years of business development experience in a leadership role",
            "Proficiency in business analytics and digital strategy"
        ],
        "resume": "Fresh Electrical Engineering graduate with strong skills in circuit design, MATLAB, PLC programming, and solar design. I\nhave practical experience in distribution and transmission systems and am passionate about new discoveries in the\nfield. I am seeking a role that fosters growth and satisfies my drive for knowledge in a collaborative environment.\nCommunication\nProblem Solving\nCritical ThinkingProteus\nCX-One\nHelioScope\nArduino IDE\nPVWattsMATLAB\nNi Multisim\nLTspice\nPSS/E\nDev-C++Intermediate | FG Sir Syed College The Mall, Rawalpindi\nMatric | Siddeeq Public School, RawalpindiAchieved an 80.36% score in my Intermediate examination.\nSecured 94.45% in my Intermediate examination.BSc Electrical Engineering | University of Engineering & Technology, Taxila                                 Aug 2020 - July 2024\nAug 2018 - July 2020\nMarch 2016 - June 2018ABOUTAddress : House 439, D-block, Rwp\nPhone : 0301-5138489\nEmail : hasanbinzulfiqar@gmail.com\nLinkedIn : https://rb.gy/rnnsbyHASAN BIN ZULFIQAR\nELECTRICAL ENGINEER\nEDUCATION\nINTERNSHIP\nPROJECTSSOFTWARE SOFT SKILLS\nFYP                                                  \nDeveloped a highly accurate observer-based SoC estimator, achieving rapid convergence within 0.35 seconds\nduring MATLAB simulations.\nImplemented real-time SOC monitoring with dual charging and discharging modes, displayed on an LCD screen for\neffective energy management.\nDemonstrated potential applications in electric vehicles and renewable energy storage systems through accurate\nSOC estimation and system performance validation.State Machine Design For BMS\n IESCO (July 2023 - Sept 2023)\nCompleted a two-month internship at IESCO's 132KV grid station, gaining hands-on experience in high-voltage\ndistribution systems.\nEnhanced understanding of grid operations and maintenance through practical training sessions.\nDeveloped communication and management skills, gaining insights into corporate operations and organizational\ndynamics.\nACHIEVEMENTS\n Awarded certificates for ISMO (Inter-School Maths\nOlympiad) participation.1.\n Participated in \"World Space Week\" event on    \n\"Glider Flying\" by SUPARCO.2.\n Completed \"National Financial Literacy Program\nfor Youth\" by State Bank of Pakistan.3.AC to DC Converter Circuit\nDigital Clock using PIC 16f877A\nDesign and Simulation of Solid-State Circuit Breaker\nTemperature sensor using Arduino UNO\nSolar system design for 10MW system\nPower system design along with fault analysis\nBoiler Automation system DesignLANGUAGES\nEnglish\nUrdu\nPunjabiCompleted my bachelors with a CGPA of 3.39 out of 4.0.\nRESEARCH WORK\nEnhancing Student Learning Outcomes and Critical Thinking Skills through Problem-Based Learning in Economics and\nPhysics"
    },
    "details": {
        "name": "Hasan Bin Zulfiqar",
        "number": "03015138489",
        "skills": [
            "MATLAB",
            "PLC programming",
            "solar design",
            "Proteus",
            "CX-One",
            "HelioScope",
            "Arduino IDE",
            "PVWatts",
            "Ni Multisim",
            "LTspice",
            "PSS/E",
            "Dev-C++"
        ],
        "email_id": "hasanbinzulfiqar@gmail.com",
        "location": "House 439, D-block, Rwp",
        "projects": [
            {
                "title": "FYP",
                "description": "Developed a highly accurate observer-based SoC estimator, achieving rapid convergence within 0.35 seconds during MATLAB simulations."
            },
            {
                "title": "State Machine Design For BMS",
                "description": "Implemented real-time SOC monitoring with dual charging and discharging modes, displayed on an LCD screen for effective energy management."
            },
            {
                "title": "AC to DC Converter Circuit",
                "description": "Designed and simulated an AC to DC converter circuit."
            },
            {
                "title": "Digital Clock using PIC 16f877A",
                "description": "Created a digital clock using PIC 16f877A."
            },
            {
                "title": "Design and Simulation of Solid-State Circuit Breaker",
                "description": "Designed and simulated a solid-state circuit breaker."
            },
            {
                "title": "Temperature sensor using Arduino UNO",
                "description": "Developed a temperature sensor using Arduino UNO."
            },
            {
                "title": "Solar system design for 10MW system",
                "description": "Designed a solar system for a 10MW capacity."
            },
            {
                "title": "Power system design along with fault analysis",
                "description": "Conducted power system design and fault analysis."
            },
            {
                "title": "Boiler Automation system Design",
                "description": "Designed a boiler automation system."
            }
        ],
        "education": [
            {
                "end_date": "07-2024",
                "university": "University of Engineering & Technology, Taxila",
                "degree_title": "BSc Electrical Engineering"
            },
            {
                "end_date": "07-2020",
                "university": "FG Sir Syed College The Mall, Rawalpindi",
                "degree_title": "Intermediate"
            },
            {
                "end_date": "06-2018",
                "university": "Siddeeq Public School, Rawalpindi",
                "degree_title": "Matric"
            }
        ],
        "achievements": [
            "Achieved an 80.36% score in my Intermediate examination.",
            "Secured 94.45% in my Intermediate examination.",
            "Awarded certificates for ISMO (Inter-School Maths Olympiad) participation.",
            "Participated in 'World Space Week' event on 'Glider Flying' by SUPARCO.",
            "Completed 'National Financial Literacy Program for Youth' by State Bank of Pakistan."
        ],
        "publications": [],
        "certifications": [
            {
                "certification_name": "National Financial Literacy Program for Youth",
                "issuing_organization": "State Bank of Pakistan",
                "date_of_issuance": "07-2023"
            }
        ],
        "additional_urls": [
            {
                "url": "rb.gy/rnnsby",
                "website_name": "LinkedIn"
            }
        ],
        "executive_summary": "Hasan Bin Zulfiqar is a fresh Electrical Engineering graduate with strong skills in circuit design, MATLAB, PLC programming, and solar design. He has practical experience in distribution and transmission systems and is passionate about new discoveries in the field, seeking a role that fosters growth and satisfies his drive for knowledge in a collaborative environment.",
        "employment_history": [
            {
                "details": "Completed a two-month internship at IESCO's 132KV grid station, gaining hands-on experience in high-voltage distribution systems.",
                "end_date": "09-2023",
                "location": "IESCO",
                "job_title": "Intern",
                "start_date": "07-2023",
                "company_name": "IESCO"
            }
        ]
    }
}