{
    "output": {
        "justification": [
            "The candidate lacks experience in a leadership role in business development which is critical for the position.",
            "While the candidate has SEO experience, there's limited demonstration of strategic planning involvement.",
            "The resume demonstrates some skills relevant to the job description but lacks advanced skills in analytics tools and CRM specific experience mentioned in the JD.",
            "The candidate has less than the required 5+ years in a leadership role for business development, impacting the relevant experience score."
        ],
        "scores": {
            "macro_scores": [
                {
                    "criteria": "leadership",
                    "score": 4
                },
                {
                    "criteria": "strategic planning",
                    "score": 3
                }
            ],
            "micro_scores": [
                {
                    "criteria": "negotiation",
                    "score": 3
                },
                {
                    "criteria": "seo",
                    "score": 6
                }
            ],
            "requirements": [
                {
                    "criteria": "5+ years of business development experience in a leadership role",
                    "meets": false
                }
            ],
            "aggregated_scores": {
                "macro_scores": 3.5500000000000003,
                "micro_scores": 5.52
            }
        },
        "personal_info": {
            "name": "Subhan Tariq",
            "email": "Subhantariq893@live.com",
            "phone": "+92 331 4404135",
            "current_position": "Support Manager",
            "current_company": "Semalt Digital Agency",
            "employment_start_date_current_company": "2019",
            "first_company_start_date": "2016",
            "urls": [
                {
                    "website_name": "Facebook",
                    "url": "https://web.facebook.com/SubhaX25"
                }
            ]
        },
        "valid_resume_and_jd": true
    },
    "input": {
        "job_description": "**Business Development Manager**  \nJoin [Fictional Company] as a Business Development Manager, where you will lead strategies for expanding our market presence. Responsibilities include driving sales growth, developing key client relationships, and implementing innovative solutions to improve efficiencies using data-driven insights.\n\n**Key Responsibilities:**\n\n- Identify new business opportunities and potential clients through market research and networking.\n- Develop strategies to enhance business processes, improve workflows, and maximize operational efficiency.\n- Work collaboratively with senior management to provide strategic recommendations based on market analysis.\n- Lead and mentor a team of business development professionals, focusing on achieving company sales targets.\n- Engage in high-stakes negotiation and strategy discussions with existing and potential partners.\n\n**Preferred Skills:**\n\n- Proficiency in business analytics tools like GA4 and Power BI.\n- Strong capability in digital marketing strategies including SEO and influencer marketing.\n- Expertise in using CRM tools such as JIRA and Asana.\n\n**Our Ideal Candidate:**\n\nYou are proactive, strategic, and data-oriented with a firm background in business development and a passion for driving sales excellence. You are eager to lead and inspire a team while focusing on achieving ambitious growth targets.\n\nJoin us and be a part of a collaborative environment driving innovation and success.\n\n[Apply Now]",
        "macro_dict": {
            "leadership": 55,
            "strategic planning": 45
        },
        "micro_dict": {
            "negotiation": 16,
            "seo": 84
        },
        "additional_info": "[Fictional Company] values candidates from top-tier universities such as [University A] and [University B]. We support diversity and inclusion in our hiring processes. Relocation assistance is provided on a case-by-case basis. We assess skills through a combination of technical interviews, case studies, and practical tests to ensure the candidate\u2019s fitment with the organizational culture and job requirements.",
        "minimum_requirements": [
            "5+ years of business development experience in a leadership role"
        ],
        "resume": "Semalt Digital Agency\nSupport Manager ( Johar Town )\nRecommended changes to website architecture, content, and linking to improve SEO positions\nfor target keywords.\nManaged SEO campaign expenses, estimated monthly costs and reconciled discrepancies to\nmaximize the budget.\nPlanned, ran, and analyzed client PPC initiatives and campaigns to increase sales, generate\nleads and promote brand awareness.\nResearched and implemented search engine optimization recommendations in accordance\nwith the development methodology.\nProduced and submitted weekly reports outlining progress against KPI objectives.\nBuilt, implemented, and updated effective SEO strategies.\nCodified office structures and processes to promote teamwork and performance.\nMaintained accurate, current, and compliant financial records by monitoring and addressing\nvariances.\nEstablished and administered annual budget with effective controls to prevent overages,\nminimize burn rate, and support sustainability objectives.\nMaintained knowledge of current market trends and algorithm updates of top search engines.\nCompleted keyword research to target clients based on keyword targeting.\nMaximized strategic approaches by keeping a close eye on performance and making\nappropriate adjustments.\nHelped clients develop website portals and social media pages to promote businesses.\nUtilized search engine optimization and emphasized the importance of link building.\nApplied performance data to evaluate and improve operations, target current business\nconditions, and forecast needs.\nHandled complaints, provided appropriate solutions and alternatives within appropriate\ntimeframes, and followed up to achieve resolution.\nResearched and analyzed competitor websites and advertising links to gain insight into new\nstrategies.\nProposed technical feasibility solutions for new system designs and suggested options for\nperformance improvement of technical components.\nManaged department call volume of 100+ calls per day and coordinated department schedules\nto maximize coverage during peak hours.\nHelped employees with day-to-day work and complex problems by applying motivational and\nanalytical strategies.CONTACT\nINFORMATION\nPhone Number :\n +92 331 4404135 \n +92 324 3271794\nEmail Address;\nSubhantariq893@live.com\nsubhantaruq892@gmail.com\nHome Address;  Ganj  Bazar,\nMughalpura, Lahore, Pakistan\nFacebook;\nhttps://web.facebook.com/SubhaX252010-2014 | Art High school ABOUT ME\nEDUCATION\nAllama Iqbal Open University (AIOU)\nP.E.C.H.S High School Karachi Block 6 2020 - 2024 | Faculty of Arts (FA) Lahore Proven skills in increasing customer engagement and business visibility in\nonline searches through successful SEO approaches. Experienced in\ndeveloping marketing initiatives, increasing business success, and boost\nsales. Excellent analytical, organizational, and decision-making abilities.\nExperienced digital marketing with over 3 years of experience in Semalt\nExcellent reputation for resolving problems and improving customer\nsatisfaction. Highly motivated Sales Associate with extensive customer\nservice and sales experience. Outgoing sales professional with a track\nrecord of driving increased sales, improving buying experience, and\nelevating company profile with the target market. Consistently recognized\nfor sales performance and excellence in customer service.SALES AND\nMARKETING\nSubhan\nTariq\nEXPERIENCE\nSince 2019 till 2021 JuneMilvik Mobile Pakistan \nInbound & outbound Agent ( Model Town )\nDelivered exceptional customer service to every customer by\nleveraging extensive knowledge of products and services and creating\nwelcoming, positive experiences.\nUsed computer databases to keep track of phone calls, confidential\nnotes about conversations, and customer contact information.\nResponded to customer requests, offering excellent support and\ntailored recommendations to address needs.\nAchieved and consistently exceeded revenue quota through product\nand service promotion during routine calls.\nMemorized scripts to achieve easy conversational flow in interactions\nwith potential customers\nEnhanced productivity by staying on top of call scripts and maintaining\ncontrol over the direction of conversations.\nUsed Microsoft Word and other software tools to create documents\nand other communications.\nMaintained user account data by initiating account access and\nestablishing in database.\nAnswered phone with a friendly greeting to create a positive outbound\n& inbound calling experience for customers.\nEngaged with customers to effectively build rapport and lasting\nrelationships.\nIncreased sales by offering advice on purchases and promoting\nadditional products.\nUfone Franchise \nRetail sales store activities ( Garhi Shahu )\nExceeded goals through effective task prioritization and a great work\nethic.\nManaged team of 3 to 6 employees, overseeing hiring, training, and\nprofessional growth of employees.\nResolved problems, improved operations, and provided exceptional\nservice.\nUsed critical thinking to break down problems, evaluate solutions and\nmake decisions.\nWorked to maintain outstanding attendance record, consistently\narriving to work ready to start immediately.\nIncreased sales by offering advice on purchases and promoting\nadditional products.\nTracked stock using company inventory management software.\nPrepared sims for sales floor by pricing or tagging.\nLANGUAGES\nmicrosoft office\nCRM System\nSEO & PPC\nComputer Skills\nGoogle Analytics \nemail writing CONTACT\nINFORMATION\nPhone Number :\n +92 331 4404135 \n +92 324 3271794\nEmail Address;\nSubhantariq893@live.com\nsubhantaruq892@gmail.com\nFacebook;\nhttps://web.facebook.com/SubhaX25EXPERIENCE \nWORK\n2016 -\n20172018 -\n2019\nEnglish\nPunjabi\nUrdu\nSindhi \nPortuguese\nHindi \nSKILLS "
    },
    "details": {
        "name": "Subhan Tariq",
        "number": "923314404135",
        "skills": [
            "SEO",
            "PPC",
            "Google Analytics",
            "Microsoft Office",
            "CRM System",
            "Email Writing"
        ],
        "email_id": "subhantariq893@live.com",
        "location": "Ganj Bazar, Mughalpura, Lahore, Pakistan",
        "projects": [],
        "education": [
            {
                "end_date": "06-2024",
                "university": "Allama Iqbal Open University (AIOU)",
                "degree_title": "Faculty of Arts (FA)"
            }
        ],
        "achievements": [],
        "publications": [],
        "certifications": [],
        "additional_urls": [
            {
                "url": "web.facebook.com/SubhaX25",
                "website_name": "Facebook"
            }
        ],
        "executive_summary": "Subhan Tariq is a skilled digital marketing professional with over 3 years of experience in SEO and PPC strategies. He has a proven track record of enhancing customer engagement and business visibility through effective online marketing initiatives. Subhan is adept at utilizing tools like Google Analytics and Microsoft Office to drive results and improve operations.",
        "employment_history": [
            {
                "details": "Delivered exceptional customer service, managed inbound and outbound calls, and exceeded revenue quotas through effective product promotion.",
                "end_date": "06-2021",
                "location": "Model Town",
                "job_title": "Inbound & Outbound Agent",
                "start_date": "2019",
                "company_name": "Milvik Mobile Pakistan"
            },
            {
                "details": "Managed retail sales activities, trained employees, and resolved customer issues while exceeding sales goals.",
                "end_date": "2019",
                "location": "Garhi Shahu",
                "job_title": "Retail Sales Associate",
                "start_date": "2018",
                "company_name": "Ufone Franchise"
            }
        ]
    }
}