{
    "output": {
        "justification": [
            "The candidate has strong leadership experience demonstrated through team roles, but lacks marketing leadership specific experience.",
            "The candidate lacks dedicated digital marketing experience, primarily focusing on machine learning roles.",
            "No specific social media marketing experience evident from the resume.",
            "No mention of Google Analytics experience in the resume."
        ],
        "scores": {
            "macro_scores": [
                {
                    "criteria": "leadership and management",
                    "score": 6
                },
                {
                    "criteria": "digital marketing experience",
                    "score": 2
                }
            ],
            "micro_scores": [
                {
                    "criteria": "social media marketing",
                    "score": 2
                },
                {
                    "criteria": "google analytics",
                    "score": 1
                },
                {
                    "criteria": "crm software expertise",
                    "score": 1
                },
                {
                    "criteria": "content development",
                    "score": 2
                }
            ],
            "requirements": [
                {
                    "criteria": "Familiarity with Google Analytics and CRM tools",
                    "meets": false
                },
                {
                    "criteria": "2+ years of experience in digital marketing",
                    "meets": false
                },
                {
                    "criteria": "Bachelor's degree in Business Administration, Marketing, or related field",
                    "meets": false
                },
                {
                    "criteria": "Strong project management and communication skills",
                    "meets": true
                },
                {
                    "criteria": "Proven work experience in social media marketing and SEO/SEM",
                    "meets": false
                }
            ],
            "aggregated_scores": {
                "macro_scores": 3.16,
                "micro_scores": 1.81
            }
        },
        "personal_info": {
            "name": "Muhammad Junaid",
            "email": "junaid.72528@gmail.com",
            "phone": "+92 312-4276180",
            "current_position": "Machine Learning Engineer",
            "current_company": "NKU Technologies",
            "employment_start_date_current_company": "09-2023",
            "first_company_start_date": "06-2022",
            "urls": [
                {
                    "website_name": "LinkedIn",
                    "url": "linkedin.com/mjunaid"
                },
                {
                    "website_name": "GitHub",
                    "url": "github.com/johnny463"
                }
            ]
        },
        "valid_resume_and_jd": true
    },
    "input": {
        "job_description": "### Digital Marketing Strategist at InnovateTech Corp\n\n**Location:** Lahore, Pakistan  \n**Position:** Full-Time  \n**Department:** Marketing \n\n**About Us:**  \nInnovateTech Corp is at the forefront of providing integrated digital solutions tailored to drive business success. Our expertise in leveraging technology to enhance branding and market reach sets us apart in the dynamic world of marketing.\n\n**Role Summary:**  \nWe are seeking a talented and experienced Digital Marketing Strategist to join our team. You will play a crucial role in designing, implementing, and managing digital marketing strategies aligned with our business goals. Your exceptional communication skills and marketing expertise will be pivotal in enhancing our online presence and fostering client relationships.\n\n**Key Responsibilities:**\n- Develop, implement, and manage marketing campaigns that promote the company and its products/services.\n- Enhance brand awareness in the digital space.\n- Drive website traffic and acquire leads/customers.\n- Manage social media strategy and presence.\n- Coordinate with the sales team to create marketing campaigns.\n- Drive strategies to ensure the achievement of marketing targets.\n\n**Skills & Competencies:**\n- Strong analytical and project management skills.\n- Deep understanding of how all digital marketing channels function.\n- Solid knowledge of online marketing tools and best practices.\n- Hands-on experience with SEO/SEM, Google Analytics, and CRM software.\n- Excellent verbal and written communication skills.\n- Strong decision-making and problem-solving skills.\n- Ability to manage multiple projects simultaneously and work collaboratively.\n\n**Why InnovateTech Corp?**\n- Innovative and growth-driven workplace.\n- Opportunities for professional development.\n- Competitive salary and benefits.\n\nJoin us to reshape the future of digital interaction and marketing!",
        "macro_dict": {
            "leadership and management": 29,
            "digital marketing experience": 71
        },
        "micro_dict": {
            "social media marketing": 39,
            "google analytics": 12,
            "crm software expertise": 7,
            "content development": 42
        },
        "additional_info": "Our company embraces diversity and is an equal opportunity employer. We encourage candidates from top universities such as Lahore School of Economics and University of Central Punjab. Relocation support is not provided; however, we offer a flexible work-from-home policy. Candidates will be assessed based on a comprehensive online skills test followed by behavioral interviews with the leadership team.",
        "minimum_requirements": [
            "Familiarity with Google Analytics and CRM tools",
            "2+ years of experience in digital marketing",
            "Bachelor's degree in Business Administration, Marketing, or related field",
            "Strong project management and communication skills",
            "Proven work experience in social media marketing and SEO/SEM"
        ],
        "resume": "Muhammad Junaid\nMachine Learning Engineer\n\u2642phone(+92)312-4276180 /envel\u2322pemjunaid.72528@gmail.com /linkedinlinkedin.com/mjunaid /githubgithub.com/johnny463\nExperience\nNKU Technologies September 2023 \u2013 Present\nMachine Learning Engineer Lahore\n\u2022Spearheaded projects ranging from a dynamic Manufacturing Chatbot to a Cybersecurity Alert System, showcasing\nadaptability and diverse skill application.\n\u2022Led projects optimizing web application performance on AWS, Azure servers, Showing a keen focus on maintenance and\nseamless deployment strategies.\n\u2022Utilized Dockers to provide a continuous integration service in order to automate the entire process of loading the latest\nbuild code and test files, running the tests, and generating a report of the results once per day.\nSoftware Alliance June 2023 \u2013 September 2023\nMachine Learning Engineer Lahore\n\u2022Leveraged DVC and Docker for version control and deployment, while implementing cutting-edge vector databases and\nweb frameworks for efficient AI solutions.\n\u2022Implemented advanced techniques to instruct,full fine-tune LLMs with soft prompts tuning and engineering, from RLHF\nto optimized deployment.\n\u2022Swiftly adapted ETL, MVC and Solid Principles while employing transformers, LSTM, and deep learning for versatile\nmachine learning solutions.\nINeuorn.AI June 2022 \u2013 March 2023\nJunior Machine Learning Engineer India\n\u2022Demonstrated proficiency in techniques such as data preprocessing, model training, and hyperparameter tuning, resulting\nin a 10% improvement in model accuracy and a 15% reduction in training time.\n\u2022Successfully deployed a web apps on Heroku, a scalable and reliable cloud platform, enabling it to handle a 100% increase\nin concurrent users while maintaining high availability and performance.\nProjects\nBrand Measure |OpenAI,Django, SQL, AWS 2023\n\u2217Leveraged AI to analyze massive audio datasets from customer conversations, extracting valuable insights.\n\u2217Developed a sentiment analysis system that gauged client feedback and predicted product performance, contributing to\ndata-driven strategies for brand improvement and sales forecasting..\nWaferGuard Pro |Python, Django, Docker, Kubernetes, MLFlow, AWS October 2022\n\u2217Developed a holistic project encompassing data ingestion, processing, and deployment, ensuring a seamless flow from data\ncollection to model deployment.\n\u2217Implemented Docker and Kubernetes for scalable, consistent deployment, while integrating MLflow to streamline machine\nlearning operations, enhancing reproducibility and collaboration.\nFranchise Management Assistant |OpenAi, PineCone , RAG 2024\n\u2217Leveraged OpenAI\u2019s GPT-4 to design an AI assistant that supports franchisors and franchisees in contract negotiation,\ndispute resolution, and scenario simulation. Utilized Retrieval-Augmented Generation (RAG) to enhance response\naccuracy by integrating up-to-date information from relevant documents\n\u2217Incorporated Retrieval-Augmented Generation (RAG) techniques in the AI assistant to provide accurate and contextually\nrelevant answers by retrieving pertinent data from franchise agreements and related legal documents, ensuring informed\ndecision-making during contract negotiations and dispute resolutions.\nEducation\nCOMSATS University\nBachelor of Science in Computer Science 3.12/4Technical Skills\nLanguages : Python, HTML/CSS, SQL\nDeveloper Tools : VS Code, Spyder, Azure, Google Cloud Platform, AWS\nTechnologies/Frameworks : Python, Django, Linux, Jenkins, MongoDB, Docker, IIS Deployment, Stripe, MLFlow,\nSagemaker, OpenAI, LangChain,Llamaindex,Retrieval-augmented generation(RAG), Dagshub, PineCone, DeepLake, CI/CD\npipeline, Voiceflow , Uipath\nMethodologies : Agile/Scrum\nLeadership / Extracurricular\nNGIRI 2023 FYP Winner Batch 2019 \u2013 2023\nTeam Leader COMSATS\n\u2217Awarded the prestigious NGIRI FYP 2023 Winner title and One Lac Rupees Funding at COMSATS for outstanding\ncontributions and excellence in research, showcasing innovation and dedication within the 2019-2023 Batch\nCOMSATS Football Triumph: CS Department Champions Sport Week 2022 \u2013 2023\nVice Captain COMSATS\n\u2217Led the team to victory in the department-wise football championship.\n\u2217Demonstrated strong leadership by effectively organizing team strategies and fostering a positive team environment.\nCertifications\nMachine Learning in Production(MLOPS) Jan, 2024\nSpecialization Coursera\nLangchain and Vector Databases in Production Dec, 2023\nAdvanced Activeloop,IBM\nGenerative AI with LLMs Aug, 2023\nAdvanced Coursera\nHobbies\nTeamwork: Collaborative approach to achieve common goals, fostering open communication and mutual support\nwithin diverse teams.\nManagement: Proven ability to organize and coordinate tasks, ensuring efficient workflow and meeting project\ndeadlines.\nExploring New Technologies: Enthusiastic about staying updated with emerging technologies, consistently\nseeking opportunities to learn and apply new skills."
    },
    "details": {
        "name": "Muhammad Junaid",
        "number": "923124276180",
        "skills": [
            "Python",
            "HTML/CSS",
            "SQL",
            "VS Code",
            "Spyder",
            "Azure",
            "Google Cloud Platform",
            "AWS",
            "Django",
            "Linux",
            "Jenkins",
            "MongoDB",
            "Docker",
            "IIS Deployment",
            "Stripe",
            "MLFlow",
            "Sagemaker",
            "OpenAI",
            "LangChain",
            "Llamaindex",
            "Retrieval-augmented generation(RAG)",
            "Dagshub",
            "PineCone",
            "DeepLake",
            "CI/CD pipeline",
            "Voiceflow",
            "Uipath"
        ],
        "email_id": "pemjunaid.72528@gmail.com",
        "location": "Lahore",
        "projects": [
            {
                "title": "Brand Measure",
                "description": "Leveraged AI to analyze massive audio datasets from customer conversations, extracting valuable insights."
            },
            {
                "title": "WaferGuard Pro",
                "description": "Developed a holistic project encompassing data ingestion, processing, and deployment, ensuring a seamless flow from data collection to model deployment."
            },
            {
                "title": "Franchise Management Assistant",
                "description": "Leveraged OpenAI\u2019s GPT-4 to design an AI assistant that supports franchisors and franchisees in contract negotiation, dispute resolution, and scenario simulation."
            }
        ],
        "education": [
            {
                "end_date": "06-2023",
                "university": "COMSATS University",
                "degree_title": "Bachelor of Science in Computer Science"
            }
        ],
        "achievements": [
            "Awarded the prestigious NGIRI FYP 2023 Winner title and One Lac Rupees Funding at COMSATS for outstanding contributions and excellence in research, showcasing innovation and dedication within the 2019-2023 Batch",
            "Led the team to victory in the department-wise football championship."
        ],
        "publications": [],
        "certifications": [
            {
                "certification_name": "Machine Learning in Production(MLOPS)",
                "issuing_organization": "Coursera",
                "date_of_issuance": "01-2024"
            },
            {
                "certification_name": "Langchain and Vector Databases in Production",
                "issuing_organization": "Activeloop,IBM",
                "date_of_issuance": "12-2023"
            },
            {
                "certification_name": "Generative AI with LLMs",
                "issuing_organization": "Coursera",
                "date_of_issuance": "08-2023"
            }
        ],
        "additional_urls": [
            {
                "url": "linkedin.com/mjunaid",
                "website_name": "LinkedIn"
            },
            {
                "url": "github.com/johnny463",
                "website_name": "Github"
            }
        ],
        "executive_summary": "Muhammad Junaid is a skilled Machine Learning Engineer with a strong background in Python and various machine learning technologies. He has successfully led projects in AI and machine learning, demonstrating his ability to adapt and innovate in diverse technical environments.",
        "employment_history": [
            {
                "details": "Spearheaded projects ranging from a dynamic Manufacturing Chatbot to a Cybersecurity Alert System, showcasing adaptability and diverse skill application. Led projects optimizing web application performance on AWS, Azure servers, showing a keen focus on maintenance and seamless deployment strategies. Utilized Dockers to provide a continuous integration service in order to automate the entire process of loading the latest build code and test files, running the tests, and generating a report of the results once per day.",
                "end_date": "Present",
                "location": "Lahore",
                "job_title": "Machine Learning Engineer",
                "start_date": "09-2023",
                "company_name": "NKU Technologies"
            },
            {
                "details": "Leveraged DVC and Docker for version control and deployment, while implementing cutting-edge vector databases and web frameworks for efficient AI solutions. Implemented advanced techniques to instruct, full fine-tune LLMs with soft prompts tuning and engineering, from RLHF to optimized deployment. Swiftly adapted ETL, MVC and Solid Principles while employing transformers, LSTM, and deep learning for versatile machine learning solutions.",
                "end_date": "09-2023",
                "location": "Lahore",
                "job_title": "Machine Learning Engineer",
                "start_date": "06-2023",
                "company_name": "Software Alliance"
            },
            {
                "details": "Demonstrated proficiency in techniques such as data preprocessing, model training, and hyperparameter tuning, resulting in a 10% improvement in model accuracy and a 15% reduction in training time. Successfully deployed a web apps on Heroku, a scalable and reliable cloud platform, enabling it to handle a 100% increase in concurrent users while maintaining high availability and performance.",
                "end_date": "03-2023",
                "location": "India",
                "job_title": "Junior Machine Learning Engineer",
                "start_date": "06-2022",
                "company_name": "INeuorn.AI"
            }
        ]
    }
}